Workbook

Sheet Landed cost blocks
A1: What the landed cost in Ukraine is made of · ₴ per pack
A2: SIAS purchase + delivery + import VAT + financing = landed cost. Delivery = freight, broker, terminal and certification of the batch, per pack. Customs duty 0 %.
A4: 33 PALLETS · FULL TRUCK
B5: SIAS purchase pack price × rate | C5: Delivery freight, broker, terminal | D5: Import VAT 20 % on goods and freight | E5: Financing 2.5 % of the sum | F5: Landed cost, ₴ (sum of blocks) | G5: Landed cost, € | H5: Check vs model sheet
A6: BEFORE · 4 SKUs (Vegetable, Spicy, Beef, Chicken) | B6: 33.28 | C6: 3.6684464 | D6: 7.1275274 | E6: 1.1018993 | F6: =SUM(B6:E6) -> 45.177873 | G6: =F6/'33 pallets'!F14 -> 0.88238033 | H6: =ROUND(F6-'33 pallets'!C4,4) -> 0
A7: BEFORE · 2 SKUs (Gouda, Carbonara) | B7: 38.4 | C7: 4.2328228 | D7: 8.22407 | E7: 1.2714223 | F7: =SUM(B7:E7) -> 52.128315 | G7: =F7/'33 pallets'!F14 -> 1.0181312 | H7: =ROUND(F7-'33 pallets'!C6,4) -> 0
A8: AFTER · SIAS request (all 6 SKUs) | B8: ='33 pallets'!B19*'33 pallets'!F14 -> 27.648 | C8: =('33 pallets'!E16+'33 pallets'!F16+'33 pallets'!G16)/('33 pallets'!C18*'33 pallets'!D18)*'33 pallets'!F14 -> 3.9078788 | D8: =('33 pallets'!B19+'33 pallets'!E16*'33 pallets'!B18/('33 pallets'!C18*'33 pallets'!D18))*(1+'33 pallets'!D16)*'33 pallets'!B16*'33 pallets'!F14 -> 6.031903 | E8: =(B8+C8+D8+('33 pallets'!B19+'33 pallets'!E16*'33 pallets'!B18/('33 pallets'!C18*'33 pallets'!D18))*'33 pallets'!D16*'33 pallets'!F14)*'33 pallets'!C16 -> 0.93969455 | F8: =SUM(B8:E8) -> 38.527476 | G8: =F8/'33 pallets'!F14 -> 0.75248977 | H8: =ROUND(F8-'33 pallets'!C8,4) -> 0
A10: 6 PALLETS
B11: SIAS purchase pack price × rate | C11: Delivery freight, broker, terminal | D11: Import VAT 20 % on goods and freight | E11: Financing 2.5 % of the sum | F11: Landed cost, ₴ (sum of blocks) | G11: Landed cost, € | H11: Check vs model sheet
A12: BEFORE · 4 SKUs (Vegetable, Spicy, Beef, Chicken) | B12: 33.28 | C12: 14.86439 | D12: 8.5026341 | E12: 1.4161756 | F12: =SUM(B12:E12) -> 58.0632 | G12: =F12/'6 pallets'!F14 -> 1.1340469 | H12: =ROUND(F12-'6 pallets'!C4,4) -> 0
A13: BEFORE · 2 SKUs (Gouda, Carbonara) | B13: 38.4 | C13: 17.15122 | D13: 9.8107317 | E13: 1.6340488 | F13: =SUM(B13:E13) -> 66.996 | G13: =F13/'6 pallets'!F14 -> 1.3085156 | H13: =ROUND(F13-'6 pallets'!C6,4) -> 0
A14: AFTER · SIAS request (all 6 SKUs) | B14: ='6 pallets'!B20*'6 pallets'!F14 -> 16.384 | C14: =('6 pallets'!E16+'6 pallets'!F16+'6 pallets'!G16)/('6 pallets'!C18*'6 pallets'!D18)*'6 pallets'!F14 -> 15.626667 | D14: =('6 pallets'!B20+'6 pallets'!E16*'6 pallets'!B18/('6 pallets'!C18*'6 pallets'!D18))*(1+'6 pallets'!D16)*'6 pallets'!B16*'6 pallets'!F14 -> 5.2181333 | E14: =(B14+C14+D14+('6 pallets'!B20+'6 pallets'!E16*'6 pallets'!B18/('6 pallets'!C18*'6 pallets'!D18))*'6 pallets'!D16*'6 pallets'!F14)*'6 pallets'!C16 -> 0.93072 | F14: =SUM(B14:E14) -> 38.15952 | G14: =F14/'6 pallets'!F14 -> 0.74530312 | H14: =ROUND(F14-'6 pallets'!C8,4) -> 0
A16: "Before": per our cost file (logistics allocated by value). "After": at the requested price, logistics spread evenly per pack. The smaller the batch, the higher the delivery cost per pack.

Sheet 6 pallets
A1: SIAS · from purchase price to shelf price, one line · 6 pallets
A2: REQUEST TO SIAS, €/pack | B2: =B20 -> 0.32 | D2: ="now €"&B5&" (4 SKUs) / €"&B7&" (2 SKUs)" -> now €0.65 (4 SKUs) / €0.75 (2 SKUs) | F2: ="reduction −"&ROUND((1-B20/B5)*100,0)&" % / −"&ROUND((1-B20/B7)*100,0)&" %" -> reduction −51 % / −57 % | H2: one price for all 6 SKUs
A3: Scenario | B3: SIAS purchase per pack | C3: Landed cost in Ukraine product + costs in Ukraine | D3: Partner price cost ÷ (1 − bonus − our share) | E3: ="Chain bonus"&CHAR(10)&ROUND(D14*100,0)&" % of partner price" -> Chain bonus 35 % of partner price | F3: ="Left for us"&CHAR(10)&"costs & margin" -> Left for us costs & margin | G3: Store markup +40 % on partner price | H3: SHELF PRICE incl. VAT partner price × 1.40
A4: BEFORE · Vegetable, Spicy, Beef, Chicken (4 SKUs) | B4: =B5*F14 -> 33.28 | C4: =$B$24*F14 -> 58.0632 | D4: =C4/(1-D14-C14) -> 129.02933 | E4: =D4*D14 -> 45.160267 | F4: =D4-C4-E4 -> 25.805867 | G4: =D4*(E14-1) -> 51.611733 | H4: =D4*E14 -> 180.64107
B5: 0.65 | C5: =C4/F14 -> 1.1340469 | D5: =D4/F14 -> 2.5201042 | E5: =E4/F14 -> 0.88203646 | F5: =F4/F14 -> 0.50402083 | G5: =G4/F14 -> 1.0080417 | H5: =H4/F14 -> 3.5281458
A6: BEFORE · Gouda Cheese, Carbonara Spicy (2 SKUs) | B6: =B7*F14 -> 38.4 | C6: =$B$25*F14 -> 66.996 | D6: =C6/(1-D14-C14) -> 148.88 | E6: =D6*D14 -> 52.108 | F6: =D6-C6-E6 -> 29.776 | G6: =D6*(E14-1) -> 59.552 | H6: =D6*E14 -> 208.432
B7: 0.75 | C7: =C6/F14 -> 1.3085156 | D7: =D6/F14 -> 2.9078125 | E7: =E6/F14 -> 1.0177344 | F7: =F6/F14 -> 0.5815625 | G7: =G6/F14 -> 1.163125 | H7: =H6/F14 -> 4.0709375
A8: AFTER · SIAS request (all 6 SKUs) | B8: =B9*F14 -> 16.384 | C8: =B22 -> 38.15952 | D8: =C8/(1-D14-C14) -> 84.798933 | E8: =D8*D14 -> 29.679627 | F8: =D8-C8-E8 -> 16.959787 | G8: =D8*(E14-1) -> 33.919573 | H8: =D8*E14 -> 118.71851
B9: =B20 -> 0.32 | C9: =C8/F14 -> 0.74530312 | D9: =D8/F14 -> 1.6562292 | E9: =E8/F14 -> 0.57968021 | F9: =F8/F14 -> 0.33124583 | G9: =G8/F14 -> 0.66249167 | H9: =H8/F14 -> 2.3187208
A10: CHANGE: AFTER − BEFORE (4 SKUs) | B10: =B8-B4 -> -16.896 | C10: =C8-C4 -> -19.90368 | D10: =D8-D4 -> -44.2304 | E10: =E8-E4 -> -15.48064 | F10: =F8-F4 -> -8.84608 | G10: =G8-G4 -> -17.69216 | H10: =H8-H4 -> -61.92256
B11: =B9-B5 -> -0.33 | C11: =C9-C5 -> -0.38874375 | D11: =D9-D5 -> -0.863875 | E11: =E9-E5 -> -0.30235625 | F11: =F9-F5 -> -0.172775 | G11: =G9-G5 -> -0.34555 | H11: =H9-H5 -> -1.209425
A12: INPUTS — yellow cells can be changed
B13: Shelf price, ₴ | C13: Our share of partner price | D13: Chain bonus | E13: Shelf multiplier | F13: Rate ₴/€
A14: Target and model terms | B14: 120 | C14: 0.2 | D14: 0.35 | E14: 1.4 | F14: 51.2
B15: Import VAT | C15: Financing | D15: Customs duty | E15: Batch freight, € | F15: Broker, € | G15: Other, €
B16: 0.2 | C16: 0.025 | D16: 0 | E16: 2600 | F16: 288 | G16: 42
B17: Freight share in customs value | C17: Pallets in batch | D17: Packs per pallet
B18: 0.7 | C18: 6 | D18: 1600
A20: Request to SIAS, €/pack (rounded down to the euro cent) | B20: =ROUNDDOWN(((B14/E14*(1-D14-C14))/F14/(1+C16)-(E16+F16+G16+E16*B18*(D16+B16*(1+D16)))/(C18*D18))/((1+D16)*(1+B16)),2) -> 0.32
A21: Maximum purchase price before rounding, €/pack | B21: =((B14/E14*(1-D14-C14))/F14/(1+C16)-(E16+F16+G16+E16*B18*(D16+B16*(1+D16)))/(C18*D18))/((1+D16)*(1+B16)) -> 0.32654072
A22: Landed cost in Ukraine at the request, ₴/pack | B22: =(B20*F14+(E16+F16+G16)/(C18*D18)*F14+(B20+E16*B18/(C18*D18))*D16*F14+(B20+E16*B18/(C18*D18))*(1+D16)*B16*F14)*(1+C16) -> 38.15952
A24: Landed cost today, 4 SKUs (Vegetable, Spicy, Beef, Chicken), €/pack | B24: 1.1340469
A25: Landed cost today, 2 SKUs (Gouda, Carbonara), €/pack | B25: 1.3085156

Sheet 33 pallets
A1: SIAS · from purchase price to shelf price, one line · 33 pallets (Full Truck)
A2: REQUEST TO SIAS, €/pack | B2: =B19 -> 0.54 | D2: ="now €"&B5&" (4 SKUs) / €"&B7&" (2 SKUs)" -> now €0.65 (4 SKUs) / €0.75 (2 SKUs) | F2: ="reduction −"&ROUND((1-B19/B5)*100,0)&" % / −"&ROUND((1-B19/B7)*100,0)&" %" -> reduction −17 % / −28 % | H2: one price for all 6 SKUs
A3: Scenario | B3: SIAS purchase per pack | C3: Landed cost in Ukraine product + costs in Ukraine | D3: Partner price cost ÷ (1 − bonus − our share) | E3: ="Chain bonus"&CHAR(10)&ROUND(D14*100,0)&" % of partner price" -> Chain bonus 35 % of partner price | F3: ="Left for us"&CHAR(10)&"costs & margin" -> Left for us costs & margin | G3: Store markup +40 % on partner price | H3: SHELF PRICE incl. VAT partner price × 1.40
A4: BEFORE · Vegetable, Spicy, Beef, Chicken (4 SKUs) | B4: =B5*F14 -> 33.28 | C4: =$B$23*F14 -> 45.177873 | D4: =C4/(1-D14-C14) -> 100.39527 | E4: =D4*D14 -> 35.138346 | F4: =D4-C4-E4 -> 20.079055 | G4: =D4*(E14-1) -> 40.158109 | H4: =D4*E14 -> 140.55338
B5: 0.65 | C5: =C4/F14 -> 0.88238033 | D5: =D4/F14 -> 1.9608452 | E5: =E4/F14 -> 0.68629582 | F5: =F4/F14 -> 0.39216904 | G5: =G4/F14 -> 0.78433807 | H5: =H4/F14 -> 2.7451833
A6: BEFORE · Gouda Cheese, Carbonara Spicy (2 SKUs) | B6: =B7*F14 -> 38.4 | C6: =$B$24*F14 -> 52.128315 | D6: =C6/(1-D14-C14) -> 115.8407 | E6: =D6*D14 -> 40.544245 | F6: =D6-C6-E6 -> 23.16814 | G6: =D6*(E14-1) -> 46.33628 | H6: =D6*E14 -> 162.17698
B7: 0.75 | C7: =C6/F14 -> 1.0181312 | D7: =D6/F14 -> 2.2625137 | E7: =E6/F14 -> 0.79187979 | F7: =F6/F14 -> 0.45250274 | G7: =G6/F14 -> 0.90500547 | H7: =H6/F14 -> 3.1675191
A8: AFTER · SIAS request (all 6 SKUs) | B8: =B9*F14 -> 27.648 | C8: =B21 -> 38.527476 | D8: =C8/(1-D14-C14) -> 85.616614 | E8: =D8*D14 -> 29.965815 | F8: =D8-C8-E8 -> 17.123323 | G8: =D8*(E14-1) -> 34.246646 | H8: =D8*E14 -> 119.86326
B9: =B19 -> 0.54 | C9: =C8/F14 -> 0.75248977 | D9: =D8/F14 -> 1.6721995 | E9: =E8/F14 -> 0.58526982 | F9: =F8/F14 -> 0.3344399 | G9: =G8/F14 -> 0.6688798 | H9: =H8/F14 -> 2.3410793
A10: CHANGE: AFTER − BEFORE (4 SKUs) | B10: =B8-B4 -> -5.632 | C10: =C8-C4 -> -6.6503967 | D10: =D8-D4 -> -14.778659 | E10: =E8-E4 -> -5.1725308 | F10: =F8-F4 -> -2.9557319 | G10: =G8-G4 -> -5.9114638 | H10: =H8-H4 -> -20.690123
B11: =B9-B5 -> -0.11 | C11: =C9-C5 -> -0.12989056 | D11: =D9-D5 -> -0.28864569 | E11: =E9-E5 -> -0.10102599 | F11: =F9-F5 -> -0.057729138 | G11: =G9-G5 -> -0.11545828 | H11: =H9-H5 -> -0.40410397
A12: INPUTS — yellow cells can be changed
B13: Shelf price, ₴ | C13: Our share of partner price | D13: Chain bonus | E13: Shelf multiplier | F13: Rate ₴/€
A14: Target and model terms | B14: 120 | C14: 0.2 | D14: 0.35 | E14: 1.4 | F14: 51.2
B15: Import VAT | C15: Financing | D15: Customs duty | E15: Batch freight, € | F15: Broker, € | G15: Other, €
B16: 0.2 | C16: 0.025 | D16: 0 | E16: 3700 | F16: 288 | G16: 42
B17: Freight share in customs value | C17: Pallets in batch | D17: Packs per pallet
B18: 0.7 | C18: 33 | D18: 1600
A19: Request to SIAS, €/pack (rounded down to the euro cent) | B19: =ROUNDDOWN(((B14/E14*(1-D14-C14))/F14/(1+C16)-(E16+F16+G16+E16*B18*(D16+B16*(1+D16)))/(C18*D18))/((1+D16)*(1+B16)),2) -> 0.54
A20: Maximum purchase price before rounding, €/pack | B20: =((B14/E14*(1-D14-C14))/F14/(1+C16)-(E16+F16+G16+E16*B18*(D16+B16*(1+D16)))/(C18*D18))/((1+D16)*(1+B16)) -> 0.54069792
A21: Landed cost in Ukraine at the request, ₴/pack | B21: =(B19*F14+(E16+F16+G16)/(C18*D18)*F14+(B19+E16*B18/(C18*D18))*D16*F14+(B19+E16*B18/(C18*D18))*(1+D16)*B16*F14)*(1+C16) -> 38.527476
A23: Landed cost today, 4 SKUs (Vegetable, Spicy, Beef, Chicken), €/pack | B23: 0.88238033
A24: Landed cost today, 2 SKUs (Gouda, Carbonara), €/pack | B24: 1.0181312
