Workbook

Sheet Финмодель 6 паллет
B1: Рамен. Ціна партнеру та полиця — 6 палет
B2: Сценарій поставки | D2: 6 палет | E2: Готова СС із Self-Cost_Sias: AJ6:AJ11. Склад СС збережено.
B3: Курс, грн/EUR | D3: 51.2 | E3: Курс 51,20 грн/EUR — із Self-Cost_Sias.
B4: Бонуси мережі, % | D4: 0.25 | E4: Бонус 25%; полиця = ціна партнера × 1,40.
B5: Цільова маржа, % | D5: 0.35 | E5: 35% = (ціна партнеру − собівартість − бонус) / повна ціна партнеру.
B6: Націнка мережі (x) | D6: 1.4 | E6: Прибуток після бонусу = ціна партнеру − собівартість − бонус мережі.
B7: Ціна партнера | D7: вже з ПДВ | E7: ПДВ як у прикладі: СС збережено повністю; ціна вже з ПДВ. Множення на 1,20 немає.
B8: Частка ціни для собівартості | D8: =IF(AND(COUNT(D3:D6)=4,D3>0,D4>=0,D5>=0,D4+D5<1,D6>0),1-D4-D5,NA()) -> 0.4 | E8: 100% − бонус − маржа. За поточних умов: 100% − 25% − 35% = 40%.
A9: ТОВАР | E9: СОБІВАРТІСТЬ | G9: ЦІНА ПАРТНЕРУ ТА ПРИБУТОК | K9: ПОЛИЦЯ | L9: МОДЕЛЬ: НУЛЬОВА МАРЖА | N9: ПРИБУТОК З ОДНІЄЇ УПАКОВКИ | P9: 0.3 | U9: 0.25 | Z9: 0.2 | AE9: 0.15
A10: № | B10: Група | C10: Позиція | D10: Вага, г | E10: СС, EUR/уп. | F10: 1. СС, грн/уп. | G10: 2. Ціна партнеру з ПДВ | H10: 3. Бонус мережі, грн | I10: 4. Прибуток після бонусу, грн | J10: 5. Маржа за прикладом | K10: 6. Полиця з ПДВ, грн | L10: Мін. ціна партнеру | M10: Мін. полиця | N10: Валовий прибуток за прикладом, до бонусу, грн/уп. | O10: Прибуток після бонусу за прикладом, грн/уп. | P10: Ціна партнеру з ПДВ, грн | Q10: Бонус мережі, грн | R10: Прибуток після бонусу, грн | S10: Перевірка маржі | T10: Полиця з ПДВ, грн | U10: Ціна партнеру з ПДВ, грн | V10: Бонус мережі, грн | W10: Прибуток після бонусу, грн | X10: Перевірка маржі | Y10: Полиця з ПДВ, грн | Z10: Ціна партнеру з ПДВ, грн | AA10: Бонус мережі, грн | AB10: Прибуток після бонусу, грн | AC10: Перевірка маржі | AD10: Полиця з ПДВ, грн | AE10: Ціна партнеру з ПДВ, грн | AF10: Бонус мережі, грн | AG10: Прибуток після бонусу, грн | AH10: Перевірка маржі | AI10: Полиця з ПДВ, грн
A11: 1 | B11: SIAS — рамен у пакеті | C11: Gouda Cheese 123 г | D11: 123 | E11: 1.3085156 | F11: =IF(AND(ISNUMBER(E11),ISNUMBER($D$8)),E11*$D$3,NA()) -> 66.996 | G11: =F11/$D$8 -> 167.49 | H11: =G11*$D$4 -> 41.8725 | I11: =G11-F11-H11 -> 58.6215 | J11: =I11/G11 -> 0.35 | K11: =G11*$D$6 -> 234.486 | L11: =F11/(1-$D$4) -> 89.328 | M11: =L11*$D$6 -> 125.0592 | N11: =G11-F11 -> 100.494 | O11: =N11-H11 -> 58.6215 | P11: =$F11/(1-$D$4-$P$9) -> 148.88 | Q11: =P11*$D$4 -> 37.22 | R11: =P11-$F11-Q11 -> 44.664 | S11: =R11/P11 -> 0.3 | T11: =P11*$D$6 -> 208.432 | U11: =$F11/(1-$D$4-$U$9) -> 133.992 | V11: =U11*$D$4 -> 33.498 | W11: =U11-$F11-V11 -> 33.498 | X11: =W11/U11 -> 0.25 | Y11: =U11*$D$6 -> 187.5888 | Z11: =$F11/(1-$D$4-$Z$9) -> 121.81091 | AA11: =Z11*$D$4 -> 30.452727 | AB11: =Z11-$F11-AA11 -> 24.362182 | AC11: =AB11/Z11 -> 0.2 | AD11: =Z11*$D$6 -> 170.53527 | AE11: =$F11/(1-$D$4-$AE$9) -> 111.66 | AF11: =AE11*$D$4 -> 27.915 | AG11: =AE11-$F11-AF11 -> 16.749 | AH11: =AG11/AE11 -> 0.15 | AI11: =AE11*$D$6 -> 156.324
A12: 2 | B12: SIAS — рамен у пакеті | C12: Carbonara Spicy 131 г | D12: 131 | E12: 1.3085156 | F12: =IF(AND(ISNUMBER(E12),ISNUMBER($D$8)),E12*$D$3,NA()) -> 66.996 | G12: =F12/$D$8 -> 167.49 | H12: =G12*$D$4 -> 41.8725 | I12: =G12-F12-H12 -> 58.6215 | J12: =I12/G12 -> 0.35 | K12: =G12*$D$6 -> 234.486 | L12: =F12/(1-$D$4) -> 89.328 | M12: =L12*$D$6 -> 125.0592 | N12: =G12-F12 -> 100.494 | O12: =N12-H12 -> 58.6215 | P12: =$F12/(1-$D$4-$P$9) -> 148.88 | Q12: =P12*$D$4 -> 37.22 | R12: =P12-$F12-Q12 -> 44.664 | S12: =R12/P12 -> 0.3 | T12: =P12*$D$6 -> 208.432 | U12: =$F12/(1-$D$4-$U$9) -> 133.992 | V12: =U12*$D$4 -> 33.498 | W12: =U12-$F12-V12 -> 33.498 | X12: =W12/U12 -> 0.25 | Y12: =U12*$D$6 -> 187.5888 | Z12: =$F12/(1-$D$4-$Z$9) -> 121.81091 | AA12: =Z12*$D$4 -> 30.452727 | AB12: =Z12-$F12-AA12 -> 24.362182 | AC12: =AB12/Z12 -> 0.2 | AD12: =Z12*$D$6 -> 170.53527 | AE12: =$F12/(1-$D$4-$AE$9) -> 111.66 | AF12: =AE12*$D$4 -> 27.915 | AG12: =AE12-$F12-AF12 -> 16.749 | AH12: =AG12/AE12 -> 0.15 | AI12: =AE12*$D$6 -> 156.324
A13: 3 | B13: SIAS — рамен у пакеті | C13: Vegetable Flavor 113 г | D13: 113 | E13: 1.1340469 | F13: =IF(AND(ISNUMBER(E13),ISNUMBER($D$8)),E13*$D$3,NA()) -> 58.0632 | G13: =F13/$D$8 -> 145.158 | H13: =G13*$D$4 -> 36.2895 | I13: =G13-F13-H13 -> 50.8053 | J13: =I13/G13 -> 0.35 | K13: =G13*$D$6 -> 203.2212 | L13: =F13/(1-$D$4) -> 77.4176 | M13: =L13*$D$6 -> 108.38464 | N13: =G13-F13 -> 87.0948 | O13: =N13-H13 -> 50.8053 | P13: =$F13/(1-$D$4-$P$9) -> 129.02933 | Q13: =P13*$D$4 -> 32.257333 | R13: =P13-$F13-Q13 -> 38.7088 | S13: =R13/P13 -> 0.3 | T13: =P13*$D$6 -> 180.64107 | U13: =$F13/(1-$D$4-$U$9) -> 116.1264 | V13: =U13*$D$4 -> 29.0316 | W13: =U13-$F13-V13 -> 29.0316 | X13: =W13/U13 -> 0.25 | Y13: =U13*$D$6 -> 162.57696 | Z13: =$F13/(1-$D$4-$Z$9) -> 105.56945 | AA13: =Z13*$D$4 -> 26.392364 | AB13: =Z13-$F13-AA13 -> 21.113891 | AC13: =AB13/Z13 -> 0.2 | AD13: =Z13*$D$6 -> 147.79724 | AE13: =$F13/(1-$D$4-$AE$9) -> 96.772 | AF13: =AE13*$D$4 -> 24.193 | AG13: =AE13-$F13-AF13 -> 14.5158 | AH13: =AG13/AE13 -> 0.15 | AI13: =AE13*$D$6 -> 135.4808
A14: 4 | B14: SIAS — рамен у пакеті | C14: Spicy Flavor 112.5 г | D14: 112.5 | E14: 1.1340469 | F14: =IF(AND(ISNUMBER(E14),ISNUMBER($D$8)),E14*$D$3,NA()) -> 58.0632 | G14: =F14/$D$8 -> 145.158 | H14: =G14*$D$4 -> 36.2895 | I14: =G14-F14-H14 -> 50.8053 | J14: =I14/G14 -> 0.35 | K14: =G14*$D$6 -> 203.2212 | L14: =F14/(1-$D$4) -> 77.4176 | M14: =L14*$D$6 -> 108.38464 | N14: =G14-F14 -> 87.0948 | O14: =N14-H14 -> 50.8053 | P14: =$F14/(1-$D$4-$P$9) -> 129.02933 | Q14: =P14*$D$4 -> 32.257333 | R14: =P14-$F14-Q14 -> 38.7088 | S14: =R14/P14 -> 0.3 | T14: =P14*$D$6 -> 180.64107 | U14: =$F14/(1-$D$4-$U$9) -> 116.1264 | V14: =U14*$D$4 -> 29.0316 | W14: =U14-$F14-V14 -> 29.0316 | X14: =W14/U14 -> 0.25 | Y14: =U14*$D$6 -> 162.57696 | Z14: =$F14/(1-$D$4-$Z$9) -> 105.56945 | AA14: =Z14*$D$4 -> 26.392364 | AB14: =Z14-$F14-AA14 -> 21.113891 | AC14: =AB14/Z14 -> 0.2 | AD14: =Z14*$D$6 -> 147.79724 | AE14: =$F14/(1-$D$4-$AE$9) -> 96.772 | AF14: =AE14*$D$4 -> 24.193 | AG14: =AE14-$F14-AF14 -> 14.5158 | AH14: =AG14/AE14 -> 0.15 | AI14: =AE14*$D$6 -> 135.4808
A15: 5 | B15: SIAS — рамен у пакеті | C15: Beef Flavor 113 г | D15: 113 | E15: 1.1340469 | F15: =IF(AND(ISNUMBER(E15),ISNUMBER($D$8)),E15*$D$3,NA()) -> 58.0632 | G15: =F15/$D$8 -> 145.158 | H15: =G15*$D$4 -> 36.2895 | I15: =G15-F15-H15 -> 50.8053 | J15: =I15/G15 -> 0.35 | K15: =G15*$D$6 -> 203.2212 | L15: =F15/(1-$D$4) -> 77.4176 | M15: =L15*$D$6 -> 108.38464 | N15: =G15-F15 -> 87.0948 | O15: =N15-H15 -> 50.8053 | P15: =$F15/(1-$D$4-$P$9) -> 129.02933 | Q15: =P15*$D$4 -> 32.257333 | R15: =P15-$F15-Q15 -> 38.7088 | S15: =R15/P15 -> 0.3 | T15: =P15*$D$6 -> 180.64107 | U15: =$F15/(1-$D$4-$U$9) -> 116.1264 | V15: =U15*$D$4 -> 29.0316 | W15: =U15-$F15-V15 -> 29.0316 | X15: =W15/U15 -> 0.25 | Y15: =U15*$D$6 -> 162.57696 | Z15: =$F15/(1-$D$4-$Z$9) -> 105.56945 | AA15: =Z15*$D$4 -> 26.392364 | AB15: =Z15-$F15-AA15 -> 21.113891 | AC15: =AB15/Z15 -> 0.2 | AD15: =Z15*$D$6 -> 147.79724 | AE15: =$F15/(1-$D$4-$AE$9) -> 96.772 | AF15: =AE15*$D$4 -> 24.193 | AG15: =AE15-$F15-AF15 -> 14.5158 | AH15: =AG15/AE15 -> 0.15 | AI15: =AE15*$D$6 -> 135.4808
A16: 6 | B16: SIAS — рамен у пакеті | C16: Chicken Flavor 113 г | D16: 113 | E16: 1.1340469 | F16: =IF(AND(ISNUMBER(E16),ISNUMBER($D$8)),E16*$D$3,NA()) -> 58.0632 | G16: =F16/$D$8 -> 145.158 | H16: =G16*$D$4 -> 36.2895 | I16: =G16-F16-H16 -> 50.8053 | J16: =I16/G16 -> 0.35 | K16: =G16*$D$6 -> 203.2212 | L16: =F16/(1-$D$4) -> 77.4176 | M16: =L16*$D$6 -> 108.38464 | N16: =G16-F16 -> 87.0948 | O16: =N16-H16 -> 50.8053 | P16: =$F16/(1-$D$4-$P$9) -> 129.02933 | Q16: =P16*$D$4 -> 32.257333 | R16: =P16-$F16-Q16 -> 38.7088 | S16: =R16/P16 -> 0.3 | T16: =P16*$D$6 -> 180.64107 | U16: =$F16/(1-$D$4-$U$9) -> 116.1264 | V16: =U16*$D$4 -> 29.0316 | W16: =U16-$F16-V16 -> 29.0316 | X16: =W16/U16 -> 0.25 | Y16: =U16*$D$6 -> 162.57696 | Z16: =$F16/(1-$D$4-$Z$9) -> 105.56945 | AA16: =Z16*$D$4 -> 26.392364 | AB16: =Z16-$F16-AA16 -> 21.113891 | AC16: =AB16/Z16 -> 0.2 | AD16: =Z16*$D$6 -> 147.79724 | AE16: =$F16/(1-$D$4-$AE$9) -> 96.772 | AF16: =AE16*$D$4 -> 24.193 | AG16: =AE16-$F16-AF16 -> 14.5158 | AH16: =AG16/AE16 -> 0.15 | AI16: =AE16*$D$6 -> 135.4808
B19: Кожен крок формування ціни — за вашим прикладом
A21: № | B21: Що рахуємо | D21: Дія | F21: =C11 -> Gouda Cheese 123 г | G21: =C12 -> Carbonara Spicy 131 г | H21: =C13 -> Vegetable Flavor 113 г | I21: =C14 -> Spicy Flavor 112.5 г | J21: =C15 -> Beef Flavor 113 г | K21: =C16 -> Chicken Flavor 113 г
A22: 1 | B22: Собівартість в Україні, EUR/уп. | D22: Із Self-Cost | F22: =E11 -> 1.3085156 | G22: =E12 -> 1.3085156 | H22: =E13 -> 1.1340469 | I22: =E14 -> 1.1340469 | J22: =E15 -> 1.1340469 | K22: =E16 -> 1.1340469
A23: 2 | B23: Курс, грн/EUR | D23: Умова в D3 | F23: =$D$3 -> 51.2 | G23: =$D$3 -> 51.2 | H23: =$D$3 -> 51.2 | I23: =$D$3 -> 51.2 | J23: =$D$3 -> 51.2 | K23: =$D$3 -> 51.2
A24: 3 | B24: Собівартість в Україні, грн/уп. | D24: Крок 1 × крок 2 | F24: =F11 -> 66.996 | G24: =F12 -> 66.996 | H24: =F13 -> 58.0632 | I24: =F14 -> 58.0632 | J24: =F15 -> 58.0632 | K24: =F16 -> 58.0632
A25: 4 | B25: Повна ціна партнеру, % | D25: База для всіх відсотків | F25: 1 | G25: 1 | H25: 1 | I25: 1 | J25: 1 | K25: 1
A26: 5 | B26: Бонус мережі, % | D26: Умова в D4 | F26: =$D$4 -> 0.25 | G26: =$D$4 -> 0.25 | H26: =$D$4 -> 0.25 | I26: =$D$4 -> 0.25 | J26: =$D$4 -> 0.25 | K26: =$D$4 -> 0.25
A27: 6 | B27: Частка ціни після бонусу, % | D27: Крок 4 − крок 5 | F27: =1-$D$4 -> 0.75 | G27: =1-$D$4 -> 0.75 | H27: =1-$D$4 -> 0.75 | I27: =1-$D$4 -> 0.75 | J27: =1-$D$4 -> 0.75 | K27: =1-$D$4 -> 0.75
A28: 7 | B28: Наша цільова маржа, % | D28: Умова в D5 | F28: =$D$5 -> 0.35 | G28: =$D$5 -> 0.35 | H28: =$D$5 -> 0.35 | I28: =$D$5 -> 0.35 | J28: =$D$5 -> 0.35 | K28: =$D$5 -> 0.35
A29: 8 | B29: Частка ціни для собівартості, % | D29: Крок 6 − крок 7 | F29: =$D$8 -> 0.4 | G29: =$D$8 -> 0.4 | H29: =$D$8 -> 0.4 | I29: =$D$8 -> 0.4 | J29: =$D$8 -> 0.4 | K29: =$D$8 -> 0.4
A30: 9 | B30: Ціна партнеру з ПДВ, грн/уп. | D30: Крок 3 ÷ крок 8 | F30: =G11 -> 167.49 | G30: =G12 -> 167.49 | H30: =G13 -> 145.158 | I30: =G14 -> 145.158 | J30: =G15 -> 145.158 | K30: =G16 -> 145.158
A31: 10 | B31: Валовий прибуток до бонусу, грн/уп. | D31: Крок 9 − крок 3 | F31: =N11 -> 100.494 | G31: =N12 -> 100.494 | H31: =N13 -> 87.0948 | I31: =N14 -> 87.0948 | J31: =N15 -> 87.0948 | K31: =N16 -> 87.0948
A32: 11 | B32: Бонус мережі, грн/уп. | D32: Крок 9 × крок 5 | F32: =H11 -> 41.8725 | G32: =H12 -> 41.8725 | H32: =H13 -> 36.2895 | I32: =H14 -> 36.2895 | J32: =H15 -> 36.2895 | K32: =H16 -> 36.2895
A33: 12 | B33: Нам залишається після собівартості та бонусу, грн/уп. | D33: Крок 10 − крок 11 | F33: =I11 -> 58.6215 | G33: =I12 -> 58.6215 | H33: =I13 -> 50.8053 | I33: =I14 -> 50.8053 | J33: =I15 -> 50.8053 | K33: =I16 -> 50.8053
A34: 13 | B34: Перевірка нашої маржі після бонусу, % | D34: Крок 12 ÷ крок 9 | F34: =J11 -> 0.35 | G34: =J12 -> 0.35 | H34: =J13 -> 0.35 | I34: =J14 -> 0.35 | J34: =J15 -> 0.35 | K34: =J16 -> 0.35
A35: 14 | B35: Націнка ритейлера для полиці, % | D35: Множник D6 − 1 | F35: =$D$6-1 -> 0.4 | G35: =$D$6-1 -> 0.4 | H35: =$D$6-1 -> 0.4 | I35: =$D$6-1 -> 0.4 | J35: =$D$6-1 -> 0.4 | K35: =$D$6-1 -> 0.4
A36: 15 | B36: Множник ритейлера | D36: 1 + крок 14 | F36: =$D$6 -> 1.4 | G36: =$D$6 -> 1.4 | H36: =$D$6 -> 1.4 | I36: =$D$6 -> 1.4 | J36: =$D$6 -> 1.4 | K36: =$D$6 -> 1.4
A37: 16 | B37: Ціна на полиці з ПДВ, грн/уп. | D37: Крок 9 × крок 15 | F37: =K11 -> 234.486 | G37: =K12 -> 234.486 | H37: =K13 -> 203.2212 | I37: =K14 -> 203.2212 | J37: =K15 -> 203.2212 | K37: =K16 -> 203.2212
A38: 17 | B38: Ціна партнеру при нульовому нашому прибутку, грн/уп. | D38: Крок 3 ÷ крок 6 | F38: =L11 -> 89.328 | G38: =L12 -> 89.328 | H38: =L13 -> 77.4176 | I38: =L14 -> 77.4176 | J38: =L15 -> 77.4176 | K38: =L16 -> 77.4176
A39: 18 | B39: Полиця при нульовому нашому прибутку, грн/уп. | D39: Крок 17 × крок 15 | F39: =M11 -> 125.0592 | G39: =M12 -> 125.0592 | H39: =M13 -> 108.38464 | I39: =M14 -> 108.38464 | J39: =M15 -> 108.38464 | K39: =M16 -> 108.38464

Sheet Финмодель 33 паллет
B1: Рамен. Ціна партнеру та полиця — 33 палет / Full Truck
B2: Сценарій поставки | D2: 33 палети | E2: Готова СС із Self-Cost_Sias: AJ30:AJ35. Склад СС збережено.
B3: Курс, грн/EUR | D3: 51.2 | E3: Курс 51,20 грн/EUR — із Self-Cost_Sias.
B4: Бонуси мережі, % | D4: 0.25 | E4: Бонус 25%; полиця = ціна партнера × 1,40.
B5: Цільова маржа, % | D5: 0.35 | E5: 35% = (ціна партнеру − собівартість − бонус) / повна ціна партнеру.
B6: Націнка мережі (x) | D6: 1.4 | E6: Прибуток після бонусу = ціна партнеру − собівартість − бонус мережі.
B7: Ціна партнера | D7: вже з ПДВ | E7: ПДВ як у прикладі: СС збережено повністю; ціна вже з ПДВ. Множення на 1,20 немає.
B8: Частка ціни для собівартості | D8: =IF(AND(COUNT(D3:D6)=4,D3>0,D4>=0,D5>=0,D4+D5<1,D6>0),1-D4-D5,NA()) -> 0.4 | E8: 100% − бонус − маржа. За поточних умов: 100% − 25% − 35% = 40%.
A9: ТОВАР | E9: СОБІВАРТІСТЬ | G9: ЦІНА ПАРТНЕРУ ТА ПРИБУТОК | K9: ПОЛИЦЯ | L9: МОДЕЛЬ: НУЛЬОВА МАРЖА | N9: ПРИБУТОК З ОДНІЄЇ УПАКОВКИ | P9: 0.3 | U9: 0.25 | Z9: 0.2 | AE9: 0.15
A10: № | B10: Група | C10: Позиція | D10: Вага, г | E10: СС, EUR/уп. | F10: 1. СС, грн/уп. | G10: 2. Ціна партнеру з ПДВ | H10: 3. Бонус мережі, грн | I10: 4. Прибуток після бонусу, грн | J10: 5. Маржа за прикладом | K10: 6. Полиця з ПДВ, грн | L10: Мін. ціна партнеру | M10: Мін. полиця | N10: Валовий прибуток за прикладом, до бонусу, грн/уп. | O10: Прибуток після бонусу за прикладом, грн/уп. | P10: Ціна партнеру з ПДВ, грн | Q10: Бонус мережі, грн | R10: Прибуток після бонусу, грн | S10: Перевірка маржі | T10: Полиця з ПДВ, грн | U10: Ціна партнеру з ПДВ, грн | V10: Бонус мережі, грн | W10: Прибуток після бонусу, грн | X10: Перевірка маржі | Y10: Полиця з ПДВ, грн | Z10: Ціна партнеру з ПДВ, грн | AA10: Бонус мережі, грн | AB10: Прибуток після бонусу, грн | AC10: Перевірка маржі | AD10: Полиця з ПДВ, грн | AE10: Ціна партнеру з ПДВ, грн | AF10: Бонус мережі, грн | AG10: Прибуток після бонусу, грн | AH10: Перевірка маржі | AI10: Полиця з ПДВ, грн
A11: 1 | B11: SIAS — рамен у пакеті | C11: Gouda Cheese 123 г | D11: 123 | E11: 1.0181312 | F11: =IF(AND(ISNUMBER(E11),ISNUMBER($D$8)),E11*$D$3,NA()) -> 52.128315 | G11: =F11/$D$8 -> 130.32079 | H11: =G11*$D$4 -> 32.580197 | I11: =G11-F11-H11 -> 45.612276 | J11: =I11/G11 -> 0.35 | K11: =G11*$D$6 -> 182.4491 | L11: =F11/(1-$D$4) -> 69.50442 | M11: =L11*$D$6 -> 97.306188 | N11: =G11-F11 -> 78.192473 | O11: =N11-H11 -> 45.612276 | P11: =$F11/(1-$D$4-$P$9) -> 115.8407 | Q11: =P11*$D$4 -> 28.960175 | R11: =P11-$F11-Q11 -> 34.75221 | S11: =R11/P11 -> 0.3 | T11: =P11*$D$6 -> 162.17698 | U11: =$F11/(1-$D$4-$U$9) -> 104.25663 | V11: =U11*$D$4 -> 26.064158 | W11: =U11-$F11-V11 -> 26.064158 | X11: =W11/U11 -> 0.25 | Y11: =U11*$D$6 -> 145.95928 | Z11: =$F11/(1-$D$4-$Z$9) -> 94.778755 | AA11: =Z11*$D$4 -> 23.694689 | AB11: =Z11-$F11-AA11 -> 18.955751 | AC11: =AB11/Z11 -> 0.2 | AD11: =Z11*$D$6 -> 132.69026 | AE11: =$F11/(1-$D$4-$AE$9) -> 86.880525 | AF11: =AE11*$D$4 -> 21.720131 | AG11: =AE11-$F11-AF11 -> 13.032079 | AH11: =AG11/AE11 -> 0.15 | AI11: =AE11*$D$6 -> 121.63274
A12: 2 | B12: SIAS — рамен у пакеті | C12: Carbonara Spicy 131 г | D12: 131 | E12: 1.0181312 | F12: =IF(AND(ISNUMBER(E12),ISNUMBER($D$8)),E12*$D$3,NA()) -> 52.128315 | G12: =F12/$D$8 -> 130.32079 | H12: =G12*$D$4 -> 32.580197 | I12: =G12-F12-H12 -> 45.612276 | J12: =I12/G12 -> 0.35 | K12: =G12*$D$6 -> 182.4491 | L12: =F12/(1-$D$4) -> 69.50442 | M12: =L12*$D$6 -> 97.306188 | N12: =G12-F12 -> 78.192473 | O12: =N12-H12 -> 45.612276 | P12: =$F12/(1-$D$4-$P$9) -> 115.8407 | Q12: =P12*$D$4 -> 28.960175 | R12: =P12-$F12-Q12 -> 34.75221 | S12: =R12/P12 -> 0.3 | T12: =P12*$D$6 -> 162.17698 | U12: =$F12/(1-$D$4-$U$9) -> 104.25663 | V12: =U12*$D$4 -> 26.064158 | W12: =U12-$F12-V12 -> 26.064158 | X12: =W12/U12 -> 0.25 | Y12: =U12*$D$6 -> 145.95928 | Z12: =$F12/(1-$D$4-$Z$9) -> 94.778755 | AA12: =Z12*$D$4 -> 23.694689 | AB12: =Z12-$F12-AA12 -> 18.955751 | AC12: =AB12/Z12 -> 0.2 | AD12: =Z12*$D$6 -> 132.69026 | AE12: =$F12/(1-$D$4-$AE$9) -> 86.880525 | AF12: =AE12*$D$4 -> 21.720131 | AG12: =AE12-$F12-AF12 -> 13.032079 | AH12: =AG12/AE12 -> 0.15 | AI12: =AE12*$D$6 -> 121.63274
A13: 3 | B13: SIAS — рамен у пакеті | C13: Vegetable Flavor 113 г | D13: 113 | E13: 0.88238033 | F13: =IF(AND(ISNUMBER(E13),ISNUMBER($D$8)),E13*$D$3,NA()) -> 45.177873 | G13: =F13/$D$8 -> 112.94468 | H13: =G13*$D$4 -> 28.236171 | I13: =G13-F13-H13 -> 39.530639 | J13: =I13/G13 -> 0.35 | K13: =G13*$D$6 -> 158.12256 | L13: =F13/(1-$D$4) -> 60.237164 | M13: =L13*$D$6 -> 84.33203 | N13: =G13-F13 -> 67.76681 | O13: =N13-H13 -> 39.530639 | P13: =$F13/(1-$D$4-$P$9) -> 100.39527 | Q13: =P13*$D$4 -> 25.098818 | R13: =P13-$F13-Q13 -> 30.118582 | S13: =R13/P13 -> 0.3 | T13: =P13*$D$6 -> 140.55338 | U13: =$F13/(1-$D$4-$U$9) -> 90.355746 | V13: =U13*$D$4 -> 22.588937 | W13: =U13-$F13-V13 -> 22.588937 | X13: =W13/U13 -> 0.25 | Y13: =U13*$D$6 -> 126.49804 | Z13: =$F13/(1-$D$4-$Z$9) -> 82.141587 | AA13: =Z13*$D$4 -> 20.535397 | AB13: =Z13-$F13-AA13 -> 16.428317 | AC13: =AB13/Z13 -> 0.2 | AD13: =Z13*$D$6 -> 114.99822 | AE13: =$F13/(1-$D$4-$AE$9) -> 75.296455 | AF13: =AE13*$D$4 -> 18.824114 | AG13: =AE13-$F13-AF13 -> 11.294468 | AH13: =AG13/AE13 -> 0.15 | AI13: =AE13*$D$6 -> 105.41504
A14: 4 | B14: SIAS — рамен у пакеті | C14: Spicy Flavor 112.5 г | D14: 112.5 | E14: 0.88238033 | F14: =IF(AND(ISNUMBER(E14),ISNUMBER($D$8)),E14*$D$3,NA()) -> 45.177873 | G14: =F14/$D$8 -> 112.94468 | H14: =G14*$D$4 -> 28.236171 | I14: =G14-F14-H14 -> 39.530639 | J14: =I14/G14 -> 0.35 | K14: =G14*$D$6 -> 158.12256 | L14: =F14/(1-$D$4) -> 60.237164 | M14: =L14*$D$6 -> 84.33203 | N14: =G14-F14 -> 67.76681 | O14: =N14-H14 -> 39.530639 | P14: =$F14/(1-$D$4-$P$9) -> 100.39527 | Q14: =P14*$D$4 -> 25.098818 | R14: =P14-$F14-Q14 -> 30.118582 | S14: =R14/P14 -> 0.3 | T14: =P14*$D$6 -> 140.55338 | U14: =$F14/(1-$D$4-$U$9) -> 90.355746 | V14: =U14*$D$4 -> 22.588937 | W14: =U14-$F14-V14 -> 22.588937 | X14: =W14/U14 -> 0.25 | Y14: =U14*$D$6 -> 126.49804 | Z14: =$F14/(1-$D$4-$Z$9) -> 82.141587 | AA14: =Z14*$D$4 -> 20.535397 | AB14: =Z14-$F14-AA14 -> 16.428317 | AC14: =AB14/Z14 -> 0.2 | AD14: =Z14*$D$6 -> 114.99822 | AE14: =$F14/(1-$D$4-$AE$9) -> 75.296455 | AF14: =AE14*$D$4 -> 18.824114 | AG14: =AE14-$F14-AF14 -> 11.294468 | AH14: =AG14/AE14 -> 0.15 | AI14: =AE14*$D$6 -> 105.41504
A15: 5 | B15: SIAS — рамен у пакеті | C15: Beef Flavor 113 г | D15: 113 | E15: 0.88238033 | F15: =IF(AND(ISNUMBER(E15),ISNUMBER($D$8)),E15*$D$3,NA()) -> 45.177873 | G15: =F15/$D$8 -> 112.94468 | H15: =G15*$D$4 -> 28.236171 | I15: =G15-F15-H15 -> 39.530639 | J15: =I15/G15 -> 0.35 | K15: =G15*$D$6 -> 158.12256 | L15: =F15/(1-$D$4) -> 60.237164 | M15: =L15*$D$6 -> 84.33203 | N15: =G15-F15 -> 67.76681 | O15: =N15-H15 -> 39.530639 | P15: =$F15/(1-$D$4-$P$9) -> 100.39527 | Q15: =P15*$D$4 -> 25.098818 | R15: =P15-$F15-Q15 -> 30.118582 | S15: =R15/P15 -> 0.3 | T15: =P15*$D$6 -> 140.55338 | U15: =$F15/(1-$D$4-$U$9) -> 90.355746 | V15: =U15*$D$4 -> 22.588937 | W15: =U15-$F15-V15 -> 22.588937 | X15: =W15/U15 -> 0.25 | Y15: =U15*$D$6 -> 126.49804 | Z15: =$F15/(1-$D$4-$Z$9) -> 82.141587 | AA15: =Z15*$D$4 -> 20.535397 | AB15: =Z15-$F15-AA15 -> 16.428317 | AC15: =AB15/Z15 -> 0.2 | AD15: =Z15*$D$6 -> 114.99822 | AE15: =$F15/(1-$D$4-$AE$9) -> 75.296455 | AF15: =AE15*$D$4 -> 18.824114 | AG15: =AE15-$F15-AF15 -> 11.294468 | AH15: =AG15/AE15 -> 0.15 | AI15: =AE15*$D$6 -> 105.41504
A16: 6 | B16: SIAS — рамен у пакеті | C16: Chicken Flavor 113 г | D16: 113 | E16: 0.88238033 | F16: =IF(AND(ISNUMBER(E16),ISNUMBER($D$8)),E16*$D$3,NA()) -> 45.177873 | G16: =F16/$D$8 -> 112.94468 | H16: =G16*$D$4 -> 28.236171 | I16: =G16-F16-H16 -> 39.530639 | J16: =I16/G16 -> 0.35 | K16: =G16*$D$6 -> 158.12256 | L16: =F16/(1-$D$4) -> 60.237164 | M16: =L16*$D$6 -> 84.33203 | N16: =G16-F16 -> 67.76681 | O16: =N16-H16 -> 39.530639 | P16: =$F16/(1-$D$4-$P$9) -> 100.39527 | Q16: =P16*$D$4 -> 25.098818 | R16: =P16-$F16-Q16 -> 30.118582 | S16: =R16/P16 -> 0.3 | T16: =P16*$D$6 -> 140.55338 | U16: =$F16/(1-$D$4-$U$9) -> 90.355746 | V16: =U16*$D$4 -> 22.588937 | W16: =U16-$F16-V16 -> 22.588937 | X16: =W16/U16 -> 0.25 | Y16: =U16*$D$6 -> 126.49804 | Z16: =$F16/(1-$D$4-$Z$9) -> 82.141587 | AA16: =Z16*$D$4 -> 20.535397 | AB16: =Z16-$F16-AA16 -> 16.428317 | AC16: =AB16/Z16 -> 0.2 | AD16: =Z16*$D$6 -> 114.99822 | AE16: =$F16/(1-$D$4-$AE$9) -> 75.296455 | AF16: =AE16*$D$4 -> 18.824114 | AG16: =AE16-$F16-AF16 -> 11.294468 | AH16: =AG16/AE16 -> 0.15 | AI16: =AE16*$D$6 -> 105.41504
B19: Кожен крок формування ціни — за вашим прикладом
A21: № | B21: Що рахуємо | D21: Дія | F21: =C11 -> Gouda Cheese 123 г | G21: =C12 -> Carbonara Spicy 131 г | H21: =C13 -> Vegetable Flavor 113 г | I21: =C14 -> Spicy Flavor 112.5 г | J21: =C15 -> Beef Flavor 113 г | K21: =C16 -> Chicken Flavor 113 г
A22: 1 | B22: Собівартість в Україні, EUR/уп. | D22: Із Self-Cost | F22: =E11 -> 1.0181312 | G22: =E12 -> 1.0181312 | H22: =E13 -> 0.88238033 | I22: =E14 -> 0.88238033 | J22: =E15 -> 0.88238033 | K22: =E16 -> 0.88238033
A23: 2 | B23: Курс, грн/EUR | D23: Умова в D3 | F23: =$D$3 -> 51.2 | G23: =$D$3 -> 51.2 | H23: =$D$3 -> 51.2 | I23: =$D$3 -> 51.2 | J23: =$D$3 -> 51.2 | K23: =$D$3 -> 51.2
A24: 3 | B24: Собівартість в Україні, грн/уп. | D24: Крок 1 × крок 2 | F24: =F11 -> 52.128315 | G24: =F12 -> 52.128315 | H24: =F13 -> 45.177873 | I24: =F14 -> 45.177873 | J24: =F15 -> 45.177873 | K24: =F16 -> 45.177873
A25: 4 | B25: Повна ціна партнеру, % | D25: База для всіх відсотків | F25: 1 | G25: 1 | H25: 1 | I25: 1 | J25: 1 | K25: 1
A26: 5 | B26: Бонус мережі, % | D26: Умова в D4 | F26: =$D$4 -> 0.25 | G26: =$D$4 -> 0.25 | H26: =$D$4 -> 0.25 | I26: =$D$4 -> 0.25 | J26: =$D$4 -> 0.25 | K26: =$D$4 -> 0.25
A27: 6 | B27: Частка ціни після бонусу, % | D27: Крок 4 − крок 5 | F27: =1-$D$4 -> 0.75 | G27: =1-$D$4 -> 0.75 | H27: =1-$D$4 -> 0.75 | I27: =1-$D$4 -> 0.75 | J27: =1-$D$4 -> 0.75 | K27: =1-$D$4 -> 0.75
A28: 7 | B28: Наша цільова маржа, % | D28: Умова в D5 | F28: =$D$5 -> 0.35 | G28: =$D$5 -> 0.35 | H28: =$D$5 -> 0.35 | I28: =$D$5 -> 0.35 | J28: =$D$5 -> 0.35 | K28: =$D$5 -> 0.35
A29: 8 | B29: Частка ціни для собівартості, % | D29: Крок 6 − крок 7 | F29: =$D$8 -> 0.4 | G29: =$D$8 -> 0.4 | H29: =$D$8 -> 0.4 | I29: =$D$8 -> 0.4 | J29: =$D$8 -> 0.4 | K29: =$D$8 -> 0.4
A30: 9 | B30: Ціна партнеру з ПДВ, грн/уп. | D30: Крок 3 ÷ крок 8 | F30: =G11 -> 130.32079 | G30: =G12 -> 130.32079 | H30: =G13 -> 112.94468 | I30: =G14 -> 112.94468 | J30: =G15 -> 112.94468 | K30: =G16 -> 112.94468
A31: 10 | B31: Валовий прибуток до бонусу, грн/уп. | D31: Крок 9 − крок 3 | F31: =N11 -> 78.192473 | G31: =N12 -> 78.192473 | H31: =N13 -> 67.76681 | I31: =N14 -> 67.76681 | J31: =N15 -> 67.76681 | K31: =N16 -> 67.76681
A32: 11 | B32: Бонус мережі, грн/уп. | D32: Крок 9 × крок 5 | F32: =H11 -> 32.580197 | G32: =H12 -> 32.580197 | H32: =H13 -> 28.236171 | I32: =H14 -> 28.236171 | J32: =H15 -> 28.236171 | K32: =H16 -> 28.236171
A33: 12 | B33: Нам залишається після собівартості та бонусу, грн/уп. | D33: Крок 10 − крок 11 | F33: =I11 -> 45.612276 | G33: =I12 -> 45.612276 | H33: =I13 -> 39.530639 | I33: =I14 -> 39.530639 | J33: =I15 -> 39.530639 | K33: =I16 -> 39.530639
A34: 13 | B34: Перевірка нашої маржі після бонусу, % | D34: Крок 12 ÷ крок 9 | F34: =J11 -> 0.35 | G34: =J12 -> 0.35 | H34: =J13 -> 0.35 | I34: =J14 -> 0.35 | J34: =J15 -> 0.35 | K34: =J16 -> 0.35
A35: 14 | B35: Націнка ритейлера для полиці, % | D35: Множник D6 − 1 | F35: =$D$6-1 -> 0.4 | G35: =$D$6-1 -> 0.4 | H35: =$D$6-1 -> 0.4 | I35: =$D$6-1 -> 0.4 | J35: =$D$6-1 -> 0.4 | K35: =$D$6-1 -> 0.4
A36: 15 | B36: Множник ритейлера | D36: 1 + крок 14 | F36: =$D$6 -> 1.4 | G36: =$D$6 -> 1.4 | H36: =$D$6 -> 1.4 | I36: =$D$6 -> 1.4 | J36: =$D$6 -> 1.4 | K36: =$D$6 -> 1.4
A37: 16 | B37: Ціна на полиці з ПДВ, грн/уп. | D37: Крок 9 × крок 15 | F37: =K11 -> 182.4491 | G37: =K12 -> 182.4491 | H37: =K13 -> 158.12256 | I37: =K14 -> 158.12256 | J37: =K15 -> 158.12256 | K37: =K16 -> 158.12256
A38: 17 | B38: Ціна партнеру при нульовому нашому прибутку, грн/уп. | D38: Крок 3 ÷ крок 6 | F38: =L11 -> 69.50442 | G38: =L12 -> 69.50442 | H38: =L13 -> 60.237164 | I38: =L14 -> 60.237164 | J38: =L15 -> 60.237164 | K38: =L16 -> 60.237164
A39: 18 | B39: Полиця при нульовому нашому прибутку, грн/уп. | D39: Крок 17 × крок 15 | F39: =M11 -> 97.306188 | G39: =M12 -> 97.306188 | H39: =M13 -> 84.33203 | I39: =M14 -> 84.33203 | J39: =M15 -> 84.33203 | K39: =M16 -> 84.33203

Sheet Цена 120 грн — 6 паллет
A1: SIAS · от цены закупки до полки одной линией · 6 паллет
A2: ЗАПРОС ДЛЯ SIAS, €/пачку | B2: =B20 -> 0.32 | D2: ="сейчас €"&B5&" (4 SKU) / €"&B7&" (2 SKU)" -> сейчас €0,65 (4 SKU) / €0,75 (2 SKU) | F2: ="снижение −"&ROUND((1-B20/B5)*100,0)&" % / −"&ROUND((1-B20/B7)*100,0)&" %" -> снижение −51 % / −57 % | H2: одна цена на 6 SKU
A3: Вариант | B3: Закупка SIAS за пачку | C3: Себестоимость в Украине товар + расходы в Украине | D3: Цена партнёру СС ÷ (1 − бонус − маржа) | E3: Бонус сети 25 % цены партнёру | F3: Наша прибыль 30 % цены партнёру | G3: Наценка магазина +40 % к цене партнёру | H3: ПОЛКА с НДС цена партнёру × 1,40
A4: ДО · Vegetable, Spicy, Beef, Chicken (4 SKU) | B4: =B5*F14 -> 33.28 | C4: =C5*F14 -> 58.0632 | D4: =C4/(1-D14-C14) -> 129.02933 | E4: =D4*D14 -> 32.257333 | F4: =D4-C4-E4 -> 38.7088 | G4: =D4*(E14-1) -> 51.611733 | H4: =D4*E14 -> 180.64107
B5: 0.65 | C5: ='Финмодель 6 паллет'!E13 -> 1.1340469 | D5: =D4/F14 -> 2.5201042 | E5: =E4/F14 -> 0.63002604 | F5: =F4/F14 -> 0.75603125 | G5: =G4/F14 -> 1.0080417 | H5: =H4/F14 -> 3.5281458
A6: ДО · Gouda Cheese, Carbonara Spicy (2 SKU) | B6: =B7*F14 -> 38.4 | C6: =C7*F14 -> 66.996 | D6: =C6/(1-D14-C14) -> 148.88 | E6: =D6*D14 -> 37.22 | F6: =D6-C6-E6 -> 44.664 | G6: =D6*(E14-1) -> 59.552 | H6: =D6*E14 -> 208.432
B7: 0.75 | C7: ='Финмодель 6 паллет'!E11 -> 1.3085156 | D7: =D6/F14 -> 2.9078125 | E7: =E6/F14 -> 0.72695313 | F7: =F6/F14 -> 0.87234375 | G7: =G6/F14 -> 1.163125 | H7: =H6/F14 -> 4.0709375
A8: ПОСЛЕ · запрос SIAS (все 6 SKU) | B8: =B9*F14 -> 16.384 | C8: =B22 -> 38.15952 | D8: =C8/(1-D14-C14) -> 84.798933 | E8: =D8*D14 -> 21.199733 | F8: =D8-C8-E8 -> 25.43968 | G8: =D8*(E14-1) -> 33.919573 | H8: =D8*E14 -> 118.71851
B9: =B20 -> 0.32 | C9: =C8/F14 -> 0.74530312 | D9: =D8/F14 -> 1.6562292 | E9: =E8/F14 -> 0.41405729 | F9: =F8/F14 -> 0.49686875 | G9: =G8/F14 -> 0.66249167 | H9: =H8/F14 -> 2.3187208
A10: ИЗМЕНЕНИЕ: ПОСЛЕ − ДО (4 SKU) | B10: =B8-B4 -> -16.896 | C10: =C8-C4 -> -19.90368 | D10: =D8-D4 -> -44.2304 | E10: =E8-E4 -> -11.0576 | F10: =F8-F4 -> -13.26912 | G10: =G8-G4 -> -17.69216 | H10: =H8-H4 -> -61.92256
B11: =B9-B5 -> -0.33 | C11: =C9-C5 -> -0.38874375 | D11: =D9-D5 -> -0.863875 | E11: =E9-E5 -> -0.21596875 | F11: =F9-F5 -> -0.2591625 | G11: =G9-G5 -> -0.34555 | H11: =H9-H5 -> -1.209425
A12: ИСХОДНЫЕ ДАННЫЕ — жёлтое можно менять, зелёное из вкладки «Финмодель 6 паллет»
B13: Полка, ₴ | C13: Наша маржа | D13: Бонус сети | E13: Множитель полки | F13: Курс ₴/€
A14: Цель расчёта и условия модели | B14: 120 | C14: 0.3 | D14: ='Финмодель 6 паллет'!D4 -> 0.25 | E14: ='Финмодель 6 паллет'!D6 -> 1.4 | F14: ='Финмодель 6 паллет'!D3 -> 51.2
B15: Импортный ПДВ | C15: Финансирование | D15: Пошлина | E15: Перевозка партии, € | F15: Брокер, € | G15: Прочие, €
B16: 0.2 | C16: 0.025 | D16: 0 | E16: 2600 | F16: 288 | G16: 42
B17: Доля фрахта в таможне | C17: Паллет в партии | D17: Пачек на паллете
B18: 0.7 | C18: 6 | D18: 1600
A20: Запрос SIAS, €/уп. (вниз до евроцента) | B20: =ROUNDDOWN(((B14/E14*(1-D14-C14))/F14/(1+C16)-(E16+F16+G16+E16*B18*(D16+B16*(1+D16)))/(C18*D18))/((1+D16)*(1+B16)),2) -> 0.32
A21: Предельная закупка до округления, €/уп. | B21: =((B14/E14*(1-D14-C14))/F14/(1+C16)-(E16+F16+G16+E16*B18*(D16+B16*(1+D16)))/(C18*D18))/((1+D16)*(1+B16)) -> 0.32654072
A22: Себестоимость в Украине при запросе, ₴/уп. | B22: =(B20*F14+(E16+F16+G16)/(C18*D18)*F14+(B20+E16*B18/(C18*D18))*D16*F14+(B20+E16*B18/(C18*D18))*(1+D16)*B16*F14)*(1+C16) -> 38.15952

Sheet Цена 120 грн — 33 паллет
A1: SIAS · от цены закупки до полки одной линией · 33 паллеты (Full Truck)
A2: ЗАПРОС ДЛЯ SIAS, €/пачку | B2: =B19 -> 0.54 | D2: ="сейчас €"&B5&" (4 SKU) / €"&B7&" (2 SKU)" -> сейчас €0,65 (4 SKU) / €0,75 (2 SKU) | F2: ="снижение −"&ROUND((1-B19/B5)*100,0)&" % / −"&ROUND((1-B19/B7)*100,0)&" %" -> снижение −17 % / −28 % | H2: одна цена на 6 SKU
A3: Вариант | B3: Закупка SIAS за пачку | C3: Себестоимость в Украине товар + расходы в Украине | D3: Цена партнёру СС ÷ (1 − бонус − маржа) | E3: Бонус сети 25 % цены партнёру | F3: Наша прибыль 30 % цены партнёру | G3: Наценка магазина +40 % к цене партнёру | H3: ПОЛКА с НДС цена партнёру × 1,40
A4: ДО · Vegetable, Spicy, Beef, Chicken (4 SKU) | B4: =B5*F14 -> 33.28 | C4: =C5*F14 -> 45.177873 | D4: =C4/(1-D14-C14) -> 100.39527 | E4: =D4*D14 -> 25.098818 | F4: =D4-C4-E4 -> 30.118582 | G4: =D4*(E14-1) -> 40.158109 | H4: =D4*E14 -> 140.55338
B5: 0.65 | C5: ='Финмодель 33 паллет'!E13 -> 0.88238033 | D5: =D4/F14 -> 1.9608452 | E5: =E4/F14 -> 0.4902113 | F5: =F4/F14 -> 0.58825356 | G5: =G4/F14 -> 0.78433807 | H5: =H4/F14 -> 2.7451833
A6: ДО · Gouda Cheese, Carbonara Spicy (2 SKU) | B6: =B7*F14 -> 38.4 | C6: =C7*F14 -> 52.128315 | D6: =C6/(1-D14-C14) -> 115.8407 | E6: =D6*D14 -> 28.960175 | F6: =D6-C6-E6 -> 34.75221 | G6: =D6*(E14-1) -> 46.33628 | H6: =D6*E14 -> 162.17698
B7: 0.75 | C7: ='Финмодель 33 паллет'!E11 -> 1.0181312 | D7: =D6/F14 -> 2.2625137 | E7: =E6/F14 -> 0.56562842 | F7: =F6/F14 -> 0.6787541 | G7: =G6/F14 -> 0.90500547 | H7: =H6/F14 -> 3.1675191
A8: ПОСЛЕ · запрос SIAS (все 6 SKU) | B8: =B9*F14 -> 27.648 | C8: =B21 -> 38.527476 | D8: =C8/(1-D14-C14) -> 85.616614 | E8: =D8*D14 -> 21.404154 | F8: =D8-C8-E8 -> 25.684984 | G8: =D8*(E14-1) -> 34.246646 | H8: =D8*E14 -> 119.86326
B9: =B19 -> 0.54 | C9: =C8/F14 -> 0.75248977 | D9: =D8/F14 -> 1.6721995 | E9: =E8/F14 -> 0.41804987 | F9: =F8/F14 -> 0.50165985 | G9: =G8/F14 -> 0.6688798 | H9: =H8/F14 -> 2.3410793
A10: ИЗМЕНЕНИЕ: ПОСЛЕ − ДО (4 SKU) | B10: =B8-B4 -> -5.632 | C10: =C8-C4 -> -6.6503967 | D10: =D8-D4 -> -14.778659 | E10: =E8-E4 -> -3.6946648 | F10: =F8-F4 -> -4.4335978 | G10: =G8-G4 -> -5.9114638 | H10: =H8-H4 -> -20.690123
B11: =B9-B5 -> -0.11 | C11: =C9-C5 -> -0.12989056 | D11: =D9-D5 -> -0.28864569 | E11: =E9-E5 -> -0.072161423 | F11: =F9-F5 -> -0.086593707 | G11: =G9-G5 -> -0.11545828 | H11: =H9-H5 -> -0.40410397
A12: ИСХОДНЫЕ ДАННЫЕ — жёлтое можно менять, зелёное из вкладки «Финмодель 33 паллет»
B13: Полка, ₴ | C13: Наша маржа | D13: Бонус сети | E13: Множитель полки | F13: Курс ₴/€
A14: Цель расчёта и условия модели | B14: 120 | C14: 0.3 | D14: ='Финмодель 33 паллет'!D4 -> 0.25 | E14: ='Финмодель 33 паллет'!D6 -> 1.4 | F14: ='Финмодель 33 паллет'!D3 -> 51.2
B15: Импортный ПДВ | C15: Финансирование | D15: Пошлина | E15: Перевозка партии, € | F15: Брокер, € | G15: Прочие, €
B16: 0.2 | C16: 0.025 | D16: 0 | E16: 3700 | F16: 288 | G16: 42
B17: Доля фрахта в таможне | C17: Паллет в партии | D17: Пачек на паллете
B18: 0.7 | C18: 33 | D18: 1600
A19: Запрос SIAS, €/уп. (вниз до евроцента) | B19: =ROUNDDOWN(((B14/E14*(1-D14-C14))/F14/(1+C16)-(E16+F16+G16+E16*B18*(D16+B16*(1+D16)))/(C18*D18))/((1+D16)*(1+B16)),2) -> 0.54
A20: Предельная закупка до округления, €/уп. | B20: =((B14/E14*(1-D14-C14))/F14/(1+C16)-(E16+F16+G16+E16*B18*(D16+B16*(1+D16)))/(C18*D18))/((1+D16)*(1+B16)) -> 0.54069792
A21: Себестоимость в Украине при запросе, ₴/уп. | B21: =(B19*F14+(E16+F16+G16)/(C18*D18)*F14+(B19+E16*B18/(C18*D18))*D16*F14+(B19+E16*B18/(C18*D18))*(1+D16)*B16*F14)*(1+C16) -> 38.527476
