Workbook

Sheet Финмодель 6 паллет
B1: Рамен. Ціна партнеру та полиця — 6 палет
B2: Сценарій поставки | D2: 6 палет | E2: Готова СС із Self-Cost_Sias: AJ6:AJ11. Склад СС збережено.
B3: Курс, грн/EUR | D3: 51.2 | E3: Курс 51,20 грн/EUR — із Self-Cost_Sias.
B4: Бонуси мережі, % | D4: 0.25 | E4: ="Бонус мережі "&ROUND(D4*100,0)&"%; полиця = ціна партнера × "&D6&"." -> Бонус мережі 25%; полиця = ціна партнера × 1.4.
B5: Цільова маржа, % | D5: 0.2 | E5: =ROUND(D5*100,0)&"% = (ціна партнеру − собівартість − бонус) / повна ціна партнеру." -> 20% = (ціна партнеру − собівартість − бонус) / повна ціна партнеру.
B6: Націнка мережі (x) | D6: 1.4 | E6: Прибуток після бонусу = ціна партнеру − собівартість − бонус мережі.
B7: Ціна партнера | D7: вже з ПДВ | E7: ПДВ як у прикладі: СС збережено повністю; ціна вже з ПДВ. Множення на 1,20 немає.
B8: Частка ціни для собівартості | D8: =IF(AND(COUNT(D3:D6)=4,D3>0,D4>=0,D5>=0,D4+D5<1,D6>0),1-D4-D5,NA()) -> 0.55 | E8: ="100% − бонус − маржа. За поточних умов: 100% − "&ROUND(D4*100,0)&"% − "&ROUND(D5*100,0)&"% = "&ROUND(D8*100,0)&"%." -> 100% − бонус − маржа. За поточних умов: 100% − 25% − 20% = 55%.
A9: ТОВАР | E9: СОБІВАРТІСТЬ | G9: ЦІНА ПАРТНЕРУ ТА ПРИБУТОК | K9: ПОЛИЦЯ | L9: МОДЕЛЬ: НУЛЬОВА МАРЖА | N9: ПРИБУТОК З ОДНІЄЇ УПАКОВКИ | P9: 0.3 | U9: 0.25 | Z9: 0.2 | AE9: 0.15
A10: № | B10: Група | C10: Позиція | D10: Вага, г | E10: СС, EUR/уп. | F10: 1. СС, грн/уп. | G10: 2. Ціна партнеру з ПДВ | H10: 3. Бонус мережі, грн | I10: 4. Прибуток після бонусу, грн | J10: 5. Маржа за прикладом | K10: 6. Полиця з ПДВ, грн | L10: Мін. ціна партнеру | M10: Мін. полиця | N10: Валовий прибуток за прикладом, до бонусу, грн/уп. | O10: Прибуток після бонусу за прикладом, грн/уп. | P10: Ціна партнеру з ПДВ, грн | Q10: Бонус мережі, грн | R10: Прибуток після бонусу, грн | S10: Перевірка маржі | T10: Полиця з ПДВ, грн | U10: Ціна партнеру з ПДВ, грн | V10: Бонус мережі, грн | W10: Прибуток після бонусу, грн | X10: Перевірка маржі | Y10: Полиця з ПДВ, грн | Z10: Ціна партнеру з ПДВ, грн | AA10: Бонус мережі, грн | AB10: Прибуток після бонусу, грн | AC10: Перевірка маржі | AD10: Полиця з ПДВ, грн | AE10: Ціна партнеру з ПДВ, грн | AF10: Бонус мережі, грн | AG10: Прибуток після бонусу, грн | AH10: Перевірка маржі | AI10: Полиця з ПДВ, грн
A11: 1 | B11: SIAS — рамен у пакеті | C11: Gouda Cheese 123 г | D11: 123 | E11: 1.3085156 | F11: =IF(AND(ISNUMBER(E11),ISNUMBER($D$8)),E11*$D$3,NA()) -> 66.996 | G11: =F11/$D$8 -> 121.81091 | H11: =G11*$D$4 -> 30.452727 | I11: =G11-F11-H11 -> 24.362182 | J11: =I11/G11 -> 0.2 | K11: =G11*$D$6 -> 170.53527 | L11: =F11/(1-$D$4) -> 89.328 | M11: =L11*$D$6 -> 125.0592 | N11: =G11-F11 -> 54.814909 | O11: =N11-H11 -> 24.362182 | P11: =$F11/(1-$D$4-$P$9) -> 148.88 | Q11: =P11*$D$4 -> 37.22 | R11: =P11-$F11-Q11 -> 44.664 | S11: =R11/P11 -> 0.3 | T11: =P11*$D$6 -> 208.432 | U11: =$F11/(1-$D$4-$U$9) -> 133.992 | V11: =U11*$D$4 -> 33.498 | W11: =U11-$F11-V11 -> 33.498 | X11: =W11/U11 -> 0.25 | Y11: =U11*$D$6 -> 187.5888 | Z11: =$F11/(1-$D$4-$Z$9) -> 121.81091 | AA11: =Z11*$D$4 -> 30.452727 | AB11: =Z11-$F11-AA11 -> 24.362182 | AC11: =AB11/Z11 -> 0.2 | AD11: =Z11*$D$6 -> 170.53527 | AE11: =$F11/(1-$D$4-$AE$9) -> 111.66 | AF11: =AE11*$D$4 -> 27.915 | AG11: =AE11-$F11-AF11 -> 16.749 | AH11: =AG11/AE11 -> 0.15 | AI11: =AE11*$D$6 -> 156.324
A12: 2 | B12: SIAS — рамен у пакеті | C12: Carbonara Spicy 131 г | D12: 131 | E12: 1.3085156 | F12: =IF(AND(ISNUMBER(E12),ISNUMBER($D$8)),E12*$D$3,NA()) -> 66.996 | G12: =F12/$D$8 -> 121.81091 | H12: =G12*$D$4 -> 30.452727 | I12: =G12-F12-H12 -> 24.362182 | J12: =I12/G12 -> 0.2 | K12: =G12*$D$6 -> 170.53527 | L12: =F12/(1-$D$4) -> 89.328 | M12: =L12*$D$6 -> 125.0592 | N12: =G12-F12 -> 54.814909 | O12: =N12-H12 -> 24.362182 | P12: =$F12/(1-$D$4-$P$9) -> 148.88 | Q12: =P12*$D$4 -> 37.22 | R12: =P12-$F12-Q12 -> 44.664 | S12: =R12/P12 -> 0.3 | T12: =P12*$D$6 -> 208.432 | U12: =$F12/(1-$D$4-$U$9) -> 133.992 | V12: =U12*$D$4 -> 33.498 | W12: =U12-$F12-V12 -> 33.498 | X12: =W12/U12 -> 0.25 | Y12: =U12*$D$6 -> 187.5888 | Z12: =$F12/(1-$D$4-$Z$9) -> 121.81091 | AA12: =Z12*$D$4 -> 30.452727 | AB12: =Z12-$F12-AA12 -> 24.362182 | AC12: =AB12/Z12 -> 0.2 | AD12: =Z12*$D$6 -> 170.53527 | AE12: =$F12/(1-$D$4-$AE$9) -> 111.66 | AF12: =AE12*$D$4 -> 27.915 | AG12: =AE12-$F12-AF12 -> 16.749 | AH12: =AG12/AE12 -> 0.15 | AI12: =AE12*$D$6 -> 156.324
A13: 3 | B13: SIAS — рамен у пакеті | C13: Vegetable Flavor 113 г | D13: 113 | E13: 1.1340469 | F13: =IF(AND(ISNUMBER(E13),ISNUMBER($D$8)),E13*$D$3,NA()) -> 58.0632 | G13: =F13/$D$8 -> 105.56945 | H13: =G13*$D$4 -> 26.392364 | I13: =G13-F13-H13 -> 21.113891 | J13: =I13/G13 -> 0.2 | K13: =G13*$D$6 -> 147.79724 | L13: =F13/(1-$D$4) -> 77.4176 | M13: =L13*$D$6 -> 108.38464 | N13: =G13-F13 -> 47.506255 | O13: =N13-H13 -> 21.113891 | P13: =$F13/(1-$D$4-$P$9) -> 129.02933 | Q13: =P13*$D$4 -> 32.257333 | R13: =P13-$F13-Q13 -> 38.7088 | S13: =R13/P13 -> 0.3 | T13: =P13*$D$6 -> 180.64107 | U13: =$F13/(1-$D$4-$U$9) -> 116.1264 | V13: =U13*$D$4 -> 29.0316 | W13: =U13-$F13-V13 -> 29.0316 | X13: =W13/U13 -> 0.25 | Y13: =U13*$D$6 -> 162.57696 | Z13: =$F13/(1-$D$4-$Z$9) -> 105.56945 | AA13: =Z13*$D$4 -> 26.392364 | AB13: =Z13-$F13-AA13 -> 21.113891 | AC13: =AB13/Z13 -> 0.2 | AD13: =Z13*$D$6 -> 147.79724 | AE13: =$F13/(1-$D$4-$AE$9) -> 96.772 | AF13: =AE13*$D$4 -> 24.193 | AG13: =AE13-$F13-AF13 -> 14.5158 | AH13: =AG13/AE13 -> 0.15 | AI13: =AE13*$D$6 -> 135.4808
A14: 4 | B14: SIAS — рамен у пакеті | C14: Spicy Flavor 112.5 г | D14: 112.5 | E14: 1.1340469 | F14: =IF(AND(ISNUMBER(E14),ISNUMBER($D$8)),E14*$D$3,NA()) -> 58.0632 | G14: =F14/$D$8 -> 105.56945 | H14: =G14*$D$4 -> 26.392364 | I14: =G14-F14-H14 -> 21.113891 | J14: =I14/G14 -> 0.2 | K14: =G14*$D$6 -> 147.79724 | L14: =F14/(1-$D$4) -> 77.4176 | M14: =L14*$D$6 -> 108.38464 | N14: =G14-F14 -> 47.506255 | O14: =N14-H14 -> 21.113891 | P14: =$F14/(1-$D$4-$P$9) -> 129.02933 | Q14: =P14*$D$4 -> 32.257333 | R14: =P14-$F14-Q14 -> 38.7088 | S14: =R14/P14 -> 0.3 | T14: =P14*$D$6 -> 180.64107 | U14: =$F14/(1-$D$4-$U$9) -> 116.1264 | V14: =U14*$D$4 -> 29.0316 | W14: =U14-$F14-V14 -> 29.0316 | X14: =W14/U14 -> 0.25 | Y14: =U14*$D$6 -> 162.57696 | Z14: =$F14/(1-$D$4-$Z$9) -> 105.56945 | AA14: =Z14*$D$4 -> 26.392364 | AB14: =Z14-$F14-AA14 -> 21.113891 | AC14: =AB14/Z14 -> 0.2 | AD14: =Z14*$D$6 -> 147.79724 | AE14: =$F14/(1-$D$4-$AE$9) -> 96.772 | AF14: =AE14*$D$4 -> 24.193 | AG14: =AE14-$F14-AF14 -> 14.5158 | AH14: =AG14/AE14 -> 0.15 | AI14: =AE14*$D$6 -> 135.4808
A15: 5 | B15: SIAS — рамен у пакеті | C15: Beef Flavor 113 г | D15: 113 | E15: 1.1340469 | F15: =IF(AND(ISNUMBER(E15),ISNUMBER($D$8)),E15*$D$3,NA()) -> 58.0632 | G15: =F15/$D$8 -> 105.56945 | H15: =G15*$D$4 -> 26.392364 | I15: =G15-F15-H15 -> 21.113891 | J15: =I15/G15 -> 0.2 | K15: =G15*$D$6 -> 147.79724 | L15: =F15/(1-$D$4) -> 77.4176 | M15: =L15*$D$6 -> 108.38464 | N15: =G15-F15 -> 47.506255 | O15: =N15-H15 -> 21.113891 | P15: =$F15/(1-$D$4-$P$9) -> 129.02933 | Q15: =P15*$D$4 -> 32.257333 | R15: =P15-$F15-Q15 -> 38.7088 | S15: =R15/P15 -> 0.3 | T15: =P15*$D$6 -> 180.64107 | U15: =$F15/(1-$D$4-$U$9) -> 116.1264 | V15: =U15*$D$4 -> 29.0316 | W15: =U15-$F15-V15 -> 29.0316 | X15: =W15/U15 -> 0.25 | Y15: =U15*$D$6 -> 162.57696 | Z15: =$F15/(1-$D$4-$Z$9) -> 105.56945 | AA15: =Z15*$D$4 -> 26.392364 | AB15: =Z15-$F15-AA15 -> 21.113891 | AC15: =AB15/Z15 -> 0.2 | AD15: =Z15*$D$6 -> 147.79724 | AE15: =$F15/(1-$D$4-$AE$9) -> 96.772 | AF15: =AE15*$D$4 -> 24.193 | AG15: =AE15-$F15-AF15 -> 14.5158 | AH15: =AG15/AE15 -> 0.15 | AI15: =AE15*$D$6 -> 135.4808
A16: 6 | B16: SIAS — рамен у пакеті | C16: Chicken Flavor 113 г | D16: 113 | E16: 1.1340469 | F16: =IF(AND(ISNUMBER(E16),ISNUMBER($D$8)),E16*$D$3,NA()) -> 58.0632 | G16: =F16/$D$8 -> 105.56945 | H16: =G16*$D$4 -> 26.392364 | I16: =G16-F16-H16 -> 21.113891 | J16: =I16/G16 -> 0.2 | K16: =G16*$D$6 -> 147.79724 | L16: =F16/(1-$D$4) -> 77.4176 | M16: =L16*$D$6 -> 108.38464 | N16: =G16-F16 -> 47.506255 | O16: =N16-H16 -> 21.113891 | P16: =$F16/(1-$D$4-$P$9) -> 129.02933 | Q16: =P16*$D$4 -> 32.257333 | R16: =P16-$F16-Q16 -> 38.7088 | S16: =R16/P16 -> 0.3 | T16: =P16*$D$6 -> 180.64107 | U16: =$F16/(1-$D$4-$U$9) -> 116.1264 | V16: =U16*$D$4 -> 29.0316 | W16: =U16-$F16-V16 -> 29.0316 | X16: =W16/U16 -> 0.25 | Y16: =U16*$D$6 -> 162.57696 | Z16: =$F16/(1-$D$4-$Z$9) -> 105.56945 | AA16: =Z16*$D$4 -> 26.392364 | AB16: =Z16-$F16-AA16 -> 21.113891 | AC16: =AB16/Z16 -> 0.2 | AD16: =Z16*$D$6 -> 147.79724 | AE16: =$F16/(1-$D$4-$AE$9) -> 96.772 | AF16: =AE16*$D$4 -> 24.193 | AG16: =AE16-$F16-AF16 -> 14.5158 | AH16: =AG16/AE16 -> 0.15 | AI16: =AE16*$D$6 -> 135.4808
B19: Кожен крок формування ціни — за вашим прикладом
A21: № | B21: Що рахуємо | D21: Дія | F21: =C11 -> Gouda Cheese 123 г | G21: =C12 -> Carbonara Spicy 131 г | H21: =C13 -> Vegetable Flavor 113 г | I21: =C14 -> Spicy Flavor 112.5 г | J21: =C15 -> Beef Flavor 113 г | K21: =C16 -> Chicken Flavor 113 г
A22: 1 | B22: Собівартість в Україні, EUR/уп. | D22: Із Self-Cost | F22: =E11 -> 1.3085156 | G22: =E12 -> 1.3085156 | H22: =E13 -> 1.1340469 | I22: =E14 -> 1.1340469 | J22: =E15 -> 1.1340469 | K22: =E16 -> 1.1340469
A23: 2 | B23: Курс, грн/EUR | D23: Умова в D3 | F23: =$D$3 -> 51.2 | G23: =$D$3 -> 51.2 | H23: =$D$3 -> 51.2 | I23: =$D$3 -> 51.2 | J23: =$D$3 -> 51.2 | K23: =$D$3 -> 51.2
A24: 3 | B24: Собівартість в Україні, грн/уп. | D24: Крок 1 × крок 2 | F24: =F11 -> 66.996 | G24: =F12 -> 66.996 | H24: =F13 -> 58.0632 | I24: =F14 -> 58.0632 | J24: =F15 -> 58.0632 | K24: =F16 -> 58.0632
A25: 4 | B25: Повна ціна партнеру, % | D25: База для всіх відсотків | F25: 1 | G25: 1 | H25: 1 | I25: 1 | J25: 1 | K25: 1
A26: 5 | B26: Бонус мережі, % | D26: Умова в D4 | F26: =$D$4 -> 0.25 | G26: =$D$4 -> 0.25 | H26: =$D$4 -> 0.25 | I26: =$D$4 -> 0.25 | J26: =$D$4 -> 0.25 | K26: =$D$4 -> 0.25
A27: 6 | B27: Частка ціни після бонусу, % | D27: Крок 4 − крок 5 | F27: =1-$D$4 -> 0.75 | G27: =1-$D$4 -> 0.75 | H27: =1-$D$4 -> 0.75 | I27: =1-$D$4 -> 0.75 | J27: =1-$D$4 -> 0.75 | K27: =1-$D$4 -> 0.75
A28: 7 | B28: Наша цільова маржа, % | D28: Умова в D5 | F28: =$D$5 -> 0.2 | G28: =$D$5 -> 0.2 | H28: =$D$5 -> 0.2 | I28: =$D$5 -> 0.2 | J28: =$D$5 -> 0.2 | K28: =$D$5 -> 0.2
A29: 8 | B29: Частка ціни для собівартості, % | D29: Крок 6 − крок 7 | F29: =$D$8 -> 0.55 | G29: =$D$8 -> 0.55 | H29: =$D$8 -> 0.55 | I29: =$D$8 -> 0.55 | J29: =$D$8 -> 0.55 | K29: =$D$8 -> 0.55
A30: 9 | B30: Ціна партнеру з ПДВ, грн/уп. | D30: Крок 3 ÷ крок 8 | F30: =G11 -> 121.81091 | G30: =G12 -> 121.81091 | H30: =G13 -> 105.56945 | I30: =G14 -> 105.56945 | J30: =G15 -> 105.56945 | K30: =G16 -> 105.56945
A31: 10 | B31: Валовий прибуток до бонусу, грн/уп. | D31: Крок 9 − крок 3 | F31: =N11 -> 54.814909 | G31: =N12 -> 54.814909 | H31: =N13 -> 47.506255 | I31: =N14 -> 47.506255 | J31: =N15 -> 47.506255 | K31: =N16 -> 47.506255
A32: 11 | B32: Бонус мережі, грн/уп. | D32: Крок 9 × крок 5 | F32: =H11 -> 30.452727 | G32: =H12 -> 30.452727 | H32: =H13 -> 26.392364 | I32: =H14 -> 26.392364 | J32: =H15 -> 26.392364 | K32: =H16 -> 26.392364
A33: 12 | B33: Нам залишається після собівартості та бонусу, грн/уп. | D33: Крок 10 − крок 11 | F33: =I11 -> 24.362182 | G33: =I12 -> 24.362182 | H33: =I13 -> 21.113891 | I33: =I14 -> 21.113891 | J33: =I15 -> 21.113891 | K33: =I16 -> 21.113891
A34: 13 | B34: Перевірка нашої маржі після бонусу, % | D34: Крок 12 ÷ крок 9 | F34: =J11 -> 0.2 | G34: =J12 -> 0.2 | H34: =J13 -> 0.2 | I34: =J14 -> 0.2 | J34: =J15 -> 0.2 | K34: =J16 -> 0.2
A35: 14 | B35: Націнка ритейлера для полиці, % | D35: Множник D6 − 1 | F35: =$D$6-1 -> 0.4 | G35: =$D$6-1 -> 0.4 | H35: =$D$6-1 -> 0.4 | I35: =$D$6-1 -> 0.4 | J35: =$D$6-1 -> 0.4 | K35: =$D$6-1 -> 0.4
A36: 15 | B36: Множник ритейлера | D36: 1 + крок 14 | F36: =$D$6 -> 1.4 | G36: =$D$6 -> 1.4 | H36: =$D$6 -> 1.4 | I36: =$D$6 -> 1.4 | J36: =$D$6 -> 1.4 | K36: =$D$6 -> 1.4
A37: 16 | B37: Ціна на полиці з ПДВ, грн/уп. | D37: Крок 9 × крок 15 | F37: =K11 -> 170.53527 | G37: =K12 -> 170.53527 | H37: =K13 -> 147.79724 | I37: =K14 -> 147.79724 | J37: =K15 -> 147.79724 | K37: =K16 -> 147.79724
A38: 17 | B38: Ціна партнеру при нульовому нашому прибутку, грн/уп. | D38: Крок 3 ÷ крок 6 | F38: =L11 -> 89.328 | G38: =L12 -> 89.328 | H38: =L13 -> 77.4176 | I38: =L14 -> 77.4176 | J38: =L15 -> 77.4176 | K38: =L16 -> 77.4176
A39: 18 | B39: Полиця при нульовому нашому прибутку, грн/уп. | D39: Крок 17 × крок 15 | F39: =M11 -> 125.0592 | G39: =M12 -> 125.0592 | H39: =M13 -> 108.38464 | I39: =M14 -> 108.38464 | J39: =M15 -> 108.38464 | K39: =M16 -> 108.38464

Sheet Финмодель 33 паллет
B1: Рамен. Ціна партнеру та полиця — 33 палет / Full Truck
B2: Сценарій поставки | D2: 33 палети | E2: Готова СС із Self-Cost_Sias: AJ30:AJ35. Склад СС збережено.
B3: Курс, грн/EUR | D3: 51.2 | E3: Курс 51,20 грн/EUR — із Self-Cost_Sias.
B4: Бонуси мережі, % | D4: 0.25 | E4: ="Бонус мережі "&ROUND(D4*100,0)&"%; полиця = ціна партнера × "&D6&"." -> Бонус мережі 25%; полиця = ціна партнера × 1.4.
B5: Цільова маржа, % | D5: 0.2 | E5: =ROUND(D5*100,0)&"% = (ціна партнеру − собівартість − бонус) / повна ціна партнеру." -> 20% = (ціна партнеру − собівартість − бонус) / повна ціна партнеру.
B6: Націнка мережі (x) | D6: 1.4 | E6: Прибуток після бонусу = ціна партнеру − собівартість − бонус мережі.
B7: Ціна партнера | D7: вже з ПДВ | E7: ПДВ як у прикладі: СС збережено повністю; ціна вже з ПДВ. Множення на 1,20 немає.
B8: Частка ціни для собівартості | D8: =IF(AND(COUNT(D3:D6)=4,D3>0,D4>=0,D5>=0,D4+D5<1,D6>0),1-D4-D5,NA()) -> 0.55 | E8: ="100% − бонус − маржа. За поточних умов: 100% − "&ROUND(D4*100,0)&"% − "&ROUND(D5*100,0)&"% = "&ROUND(D8*100,0)&"%." -> 100% − бонус − маржа. За поточних умов: 100% − 25% − 20% = 55%.
A9: ТОВАР | E9: СОБІВАРТІСТЬ | G9: ЦІНА ПАРТНЕРУ ТА ПРИБУТОК | K9: ПОЛИЦЯ | L9: МОДЕЛЬ: НУЛЬОВА МАРЖА | N9: ПРИБУТОК З ОДНІЄЇ УПАКОВКИ | P9: 0.3 | U9: 0.25 | Z9: 0.2 | AE9: 0.15
A10: № | B10: Група | C10: Позиція | D10: Вага, г | E10: СС, EUR/уп. | F10: 1. СС, грн/уп. | G10: 2. Ціна партнеру з ПДВ | H10: 3. Бонус мережі, грн | I10: 4. Прибуток після бонусу, грн | J10: 5. Маржа за прикладом | K10: 6. Полиця з ПДВ, грн | L10: Мін. ціна партнеру | M10: Мін. полиця | N10: Валовий прибуток за прикладом, до бонусу, грн/уп. | O10: Прибуток після бонусу за прикладом, грн/уп. | P10: Ціна партнеру з ПДВ, грн | Q10: Бонус мережі, грн | R10: Прибуток після бонусу, грн | S10: Перевірка маржі | T10: Полиця з ПДВ, грн | U10: Ціна партнеру з ПДВ, грн | V10: Бонус мережі, грн | W10: Прибуток після бонусу, грн | X10: Перевірка маржі | Y10: Полиця з ПДВ, грн | Z10: Ціна партнеру з ПДВ, грн | AA10: Бонус мережі, грн | AB10: Прибуток після бонусу, грн | AC10: Перевірка маржі | AD10: Полиця з ПДВ, грн | AE10: Ціна партнеру з ПДВ, грн | AF10: Бонус мережі, грн | AG10: Прибуток після бонусу, грн | AH10: Перевірка маржі | AI10: Полиця з ПДВ, грн
A11: 1 | B11: SIAS — рамен у пакеті | C11: Gouda Cheese 123 г | D11: 123 | E11: 1.0181312 | F11: =IF(AND(ISNUMBER(E11),ISNUMBER($D$8)),E11*$D$3,NA()) -> 52.128315 | G11: =F11/$D$8 -> 94.778755 | H11: =G11*$D$4 -> 23.694689 | I11: =G11-F11-H11 -> 18.955751 | J11: =I11/G11 -> 0.2 | K11: =G11*$D$6 -> 132.69026 | L11: =F11/(1-$D$4) -> 69.50442 | M11: =L11*$D$6 -> 97.306188 | N11: =G11-F11 -> 42.65044 | O11: =N11-H11 -> 18.955751 | P11: =$F11/(1-$D$4-$P$9) -> 115.8407 | Q11: =P11*$D$4 -> 28.960175 | R11: =P11-$F11-Q11 -> 34.75221 | S11: =R11/P11 -> 0.3 | T11: =P11*$D$6 -> 162.17698 | U11: =$F11/(1-$D$4-$U$9) -> 104.25663 | V11: =U11*$D$4 -> 26.064158 | W11: =U11-$F11-V11 -> 26.064158 | X11: =W11/U11 -> 0.25 | Y11: =U11*$D$6 -> 145.95928 | Z11: =$F11/(1-$D$4-$Z$9) -> 94.778755 | AA11: =Z11*$D$4 -> 23.694689 | AB11: =Z11-$F11-AA11 -> 18.955751 | AC11: =AB11/Z11 -> 0.2 | AD11: =Z11*$D$6 -> 132.69026 | AE11: =$F11/(1-$D$4-$AE$9) -> 86.880525 | AF11: =AE11*$D$4 -> 21.720131 | AG11: =AE11-$F11-AF11 -> 13.032079 | AH11: =AG11/AE11 -> 0.15 | AI11: =AE11*$D$6 -> 121.63274
A12: 2 | B12: SIAS — рамен у пакеті | C12: Carbonara Spicy 131 г | D12: 131 | E12: 1.0181312 | F12: =IF(AND(ISNUMBER(E12),ISNUMBER($D$8)),E12*$D$3,NA()) -> 52.128315 | G12: =F12/$D$8 -> 94.778755 | H12: =G12*$D$4 -> 23.694689 | I12: =G12-F12-H12 -> 18.955751 | J12: =I12/G12 -> 0.2 | K12: =G12*$D$6 -> 132.69026 | L12: =F12/(1-$D$4) -> 69.50442 | M12: =L12*$D$6 -> 97.306188 | N12: =G12-F12 -> 42.65044 | O12: =N12-H12 -> 18.955751 | P12: =$F12/(1-$D$4-$P$9) -> 115.8407 | Q12: =P12*$D$4 -> 28.960175 | R12: =P12-$F12-Q12 -> 34.75221 | S12: =R12/P12 -> 0.3 | T12: =P12*$D$6 -> 162.17698 | U12: =$F12/(1-$D$4-$U$9) -> 104.25663 | V12: =U12*$D$4 -> 26.064158 | W12: =U12-$F12-V12 -> 26.064158 | X12: =W12/U12 -> 0.25 | Y12: =U12*$D$6 -> 145.95928 | Z12: =$F12/(1-$D$4-$Z$9) -> 94.778755 | AA12: =Z12*$D$4 -> 23.694689 | AB12: =Z12-$F12-AA12 -> 18.955751 | AC12: =AB12/Z12 -> 0.2 | AD12: =Z12*$D$6 -> 132.69026 | AE12: =$F12/(1-$D$4-$AE$9) -> 86.880525 | AF12: =AE12*$D$4 -> 21.720131 | AG12: =AE12-$F12-AF12 -> 13.032079 | AH12: =AG12/AE12 -> 0.15 | AI12: =AE12*$D$6 -> 121.63274
A13: 3 | B13: SIAS — рамен у пакеті | C13: Vegetable Flavor 113 г | D13: 113 | E13: 0.88238033 | F13: =IF(AND(ISNUMBER(E13),ISNUMBER($D$8)),E13*$D$3,NA()) -> 45.177873 | G13: =F13/$D$8 -> 82.141587 | H13: =G13*$D$4 -> 20.535397 | I13: =G13-F13-H13 -> 16.428317 | J13: =I13/G13 -> 0.2 | K13: =G13*$D$6 -> 114.99822 | L13: =F13/(1-$D$4) -> 60.237164 | M13: =L13*$D$6 -> 84.33203 | N13: =G13-F13 -> 36.963714 | O13: =N13-H13 -> 16.428317 | P13: =$F13/(1-$D$4-$P$9) -> 100.39527 | Q13: =P13*$D$4 -> 25.098818 | R13: =P13-$F13-Q13 -> 30.118582 | S13: =R13/P13 -> 0.3 | T13: =P13*$D$6 -> 140.55338 | U13: =$F13/(1-$D$4-$U$9) -> 90.355746 | V13: =U13*$D$4 -> 22.588937 | W13: =U13-$F13-V13 -> 22.588937 | X13: =W13/U13 -> 0.25 | Y13: =U13*$D$6 -> 126.49804 | Z13: =$F13/(1-$D$4-$Z$9) -> 82.141587 | AA13: =Z13*$D$4 -> 20.535397 | AB13: =Z13-$F13-AA13 -> 16.428317 | AC13: =AB13/Z13 -> 0.2 | AD13: =Z13*$D$6 -> 114.99822 | AE13: =$F13/(1-$D$4-$AE$9) -> 75.296455 | AF13: =AE13*$D$4 -> 18.824114 | AG13: =AE13-$F13-AF13 -> 11.294468 | AH13: =AG13/AE13 -> 0.15 | AI13: =AE13*$D$6 -> 105.41504
A14: 4 | B14: SIAS — рамен у пакеті | C14: Spicy Flavor 112.5 г | D14: 112.5 | E14: 0.88238033 | F14: =IF(AND(ISNUMBER(E14),ISNUMBER($D$8)),E14*$D$3,NA()) -> 45.177873 | G14: =F14/$D$8 -> 82.141587 | H14: =G14*$D$4 -> 20.535397 | I14: =G14-F14-H14 -> 16.428317 | J14: =I14/G14 -> 0.2 | K14: =G14*$D$6 -> 114.99822 | L14: =F14/(1-$D$4) -> 60.237164 | M14: =L14*$D$6 -> 84.33203 | N14: =G14-F14 -> 36.963714 | O14: =N14-H14 -> 16.428317 | P14: =$F14/(1-$D$4-$P$9) -> 100.39527 | Q14: =P14*$D$4 -> 25.098818 | R14: =P14-$F14-Q14 -> 30.118582 | S14: =R14/P14 -> 0.3 | T14: =P14*$D$6 -> 140.55338 | U14: =$F14/(1-$D$4-$U$9) -> 90.355746 | V14: =U14*$D$4 -> 22.588937 | W14: =U14-$F14-V14 -> 22.588937 | X14: =W14/U14 -> 0.25 | Y14: =U14*$D$6 -> 126.49804 | Z14: =$F14/(1-$D$4-$Z$9) -> 82.141587 | AA14: =Z14*$D$4 -> 20.535397 | AB14: =Z14-$F14-AA14 -> 16.428317 | AC14: =AB14/Z14 -> 0.2 | AD14: =Z14*$D$6 -> 114.99822 | AE14: =$F14/(1-$D$4-$AE$9) -> 75.296455 | AF14: =AE14*$D$4 -> 18.824114 | AG14: =AE14-$F14-AF14 -> 11.294468 | AH14: =AG14/AE14 -> 0.15 | AI14: =AE14*$D$6 -> 105.41504
A15: 5 | B15: SIAS — рамен у пакеті | C15: Beef Flavor 113 г | D15: 113 | E15: 0.88238033 | F15: =IF(AND(ISNUMBER(E15),ISNUMBER($D$8)),E15*$D$3,NA()) -> 45.177873 | G15: =F15/$D$8 -> 82.141587 | H15: =G15*$D$4 -> 20.535397 | I15: =G15-F15-H15 -> 16.428317 | J15: =I15/G15 -> 0.2 | K15: =G15*$D$6 -> 114.99822 | L15: =F15/(1-$D$4) -> 60.237164 | M15: =L15*$D$6 -> 84.33203 | N15: =G15-F15 -> 36.963714 | O15: =N15-H15 -> 16.428317 | P15: =$F15/(1-$D$4-$P$9) -> 100.39527 | Q15: =P15*$D$4 -> 25.098818 | R15: =P15-$F15-Q15 -> 30.118582 | S15: =R15/P15 -> 0.3 | T15: =P15*$D$6 -> 140.55338 | U15: =$F15/(1-$D$4-$U$9) -> 90.355746 | V15: =U15*$D$4 -> 22.588937 | W15: =U15-$F15-V15 -> 22.588937 | X15: =W15/U15 -> 0.25 | Y15: =U15*$D$6 -> 126.49804 | Z15: =$F15/(1-$D$4-$Z$9) -> 82.141587 | AA15: =Z15*$D$4 -> 20.535397 | AB15: =Z15-$F15-AA15 -> 16.428317 | AC15: =AB15/Z15 -> 0.2 | AD15: =Z15*$D$6 -> 114.99822 | AE15: =$F15/(1-$D$4-$AE$9) -> 75.296455 | AF15: =AE15*$D$4 -> 18.824114 | AG15: =AE15-$F15-AF15 -> 11.294468 | AH15: =AG15/AE15 -> 0.15 | AI15: =AE15*$D$6 -> 105.41504
A16: 6 | B16: SIAS — рамен у пакеті | C16: Chicken Flavor 113 г | D16: 113 | E16: 0.88238033 | F16: =IF(AND(ISNUMBER(E16),ISNUMBER($D$8)),E16*$D$3,NA()) -> 45.177873 | G16: =F16/$D$8 -> 82.141587 | H16: =G16*$D$4 -> 20.535397 | I16: =G16-F16-H16 -> 16.428317 | J16: =I16/G16 -> 0.2 | K16: =G16*$D$6 -> 114.99822 | L16: =F16/(1-$D$4) -> 60.237164 | M16: =L16*$D$6 -> 84.33203 | N16: =G16-F16 -> 36.963714 | O16: =N16-H16 -> 16.428317 | P16: =$F16/(1-$D$4-$P$9) -> 100.39527 | Q16: =P16*$D$4 -> 25.098818 | R16: =P16-$F16-Q16 -> 30.118582 | S16: =R16/P16 -> 0.3 | T16: =P16*$D$6 -> 140.55338 | U16: =$F16/(1-$D$4-$U$9) -> 90.355746 | V16: =U16*$D$4 -> 22.588937 | W16: =U16-$F16-V16 -> 22.588937 | X16: =W16/U16 -> 0.25 | Y16: =U16*$D$6 -> 126.49804 | Z16: =$F16/(1-$D$4-$Z$9) -> 82.141587 | AA16: =Z16*$D$4 -> 20.535397 | AB16: =Z16-$F16-AA16 -> 16.428317 | AC16: =AB16/Z16 -> 0.2 | AD16: =Z16*$D$6 -> 114.99822 | AE16: =$F16/(1-$D$4-$AE$9) -> 75.296455 | AF16: =AE16*$D$4 -> 18.824114 | AG16: =AE16-$F16-AF16 -> 11.294468 | AH16: =AG16/AE16 -> 0.15 | AI16: =AE16*$D$6 -> 105.41504
B19: Кожен крок формування ціни — за вашим прикладом
A21: № | B21: Що рахуємо | D21: Дія | F21: =C11 -> Gouda Cheese 123 г | G21: =C12 -> Carbonara Spicy 131 г | H21: =C13 -> Vegetable Flavor 113 г | I21: =C14 -> Spicy Flavor 112.5 г | J21: =C15 -> Beef Flavor 113 г | K21: =C16 -> Chicken Flavor 113 г
A22: 1 | B22: Собівартість в Україні, EUR/уп. | D22: Із Self-Cost | F22: =E11 -> 1.0181312 | G22: =E12 -> 1.0181312 | H22: =E13 -> 0.88238033 | I22: =E14 -> 0.88238033 | J22: =E15 -> 0.88238033 | K22: =E16 -> 0.88238033
A23: 2 | B23: Курс, грн/EUR | D23: Умова в D3 | F23: =$D$3 -> 51.2 | G23: =$D$3 -> 51.2 | H23: =$D$3 -> 51.2 | I23: =$D$3 -> 51.2 | J23: =$D$3 -> 51.2 | K23: =$D$3 -> 51.2
A24: 3 | B24: Собівартість в Україні, грн/уп. | D24: Крок 1 × крок 2 | F24: =F11 -> 52.128315 | G24: =F12 -> 52.128315 | H24: =F13 -> 45.177873 | I24: =F14 -> 45.177873 | J24: =F15 -> 45.177873 | K24: =F16 -> 45.177873
A25: 4 | B25: Повна ціна партнеру, % | D25: База для всіх відсотків | F25: 1 | G25: 1 | H25: 1 | I25: 1 | J25: 1 | K25: 1
A26: 5 | B26: Бонус мережі, % | D26: Умова в D4 | F26: =$D$4 -> 0.25 | G26: =$D$4 -> 0.25 | H26: =$D$4 -> 0.25 | I26: =$D$4 -> 0.25 | J26: =$D$4 -> 0.25 | K26: =$D$4 -> 0.25
A27: 6 | B27: Частка ціни після бонусу, % | D27: Крок 4 − крок 5 | F27: =1-$D$4 -> 0.75 | G27: =1-$D$4 -> 0.75 | H27: =1-$D$4 -> 0.75 | I27: =1-$D$4 -> 0.75 | J27: =1-$D$4 -> 0.75 | K27: =1-$D$4 -> 0.75
A28: 7 | B28: Наша цільова маржа, % | D28: Умова в D5 | F28: =$D$5 -> 0.2 | G28: =$D$5 -> 0.2 | H28: =$D$5 -> 0.2 | I28: =$D$5 -> 0.2 | J28: =$D$5 -> 0.2 | K28: =$D$5 -> 0.2
A29: 8 | B29: Частка ціни для собівартості, % | D29: Крок 6 − крок 7 | F29: =$D$8 -> 0.55 | G29: =$D$8 -> 0.55 | H29: =$D$8 -> 0.55 | I29: =$D$8 -> 0.55 | J29: =$D$8 -> 0.55 | K29: =$D$8 -> 0.55
A30: 9 | B30: Ціна партнеру з ПДВ, грн/уп. | D30: Крок 3 ÷ крок 8 | F30: =G11 -> 94.778755 | G30: =G12 -> 94.778755 | H30: =G13 -> 82.141587 | I30: =G14 -> 82.141587 | J30: =G15 -> 82.141587 | K30: =G16 -> 82.141587
A31: 10 | B31: Валовий прибуток до бонусу, грн/уп. | D31: Крок 9 − крок 3 | F31: =N11 -> 42.65044 | G31: =N12 -> 42.65044 | H31: =N13 -> 36.963714 | I31: =N14 -> 36.963714 | J31: =N15 -> 36.963714 | K31: =N16 -> 36.963714
A32: 11 | B32: Бонус мережі, грн/уп. | D32: Крок 9 × крок 5 | F32: =H11 -> 23.694689 | G32: =H12 -> 23.694689 | H32: =H13 -> 20.535397 | I32: =H14 -> 20.535397 | J32: =H15 -> 20.535397 | K32: =H16 -> 20.535397
A33: 12 | B33: Нам залишається після собівартості та бонусу, грн/уп. | D33: Крок 10 − крок 11 | F33: =I11 -> 18.955751 | G33: =I12 -> 18.955751 | H33: =I13 -> 16.428317 | I33: =I14 -> 16.428317 | J33: =I15 -> 16.428317 | K33: =I16 -> 16.428317
A34: 13 | B34: Перевірка нашої маржі після бонусу, % | D34: Крок 12 ÷ крок 9 | F34: =J11 -> 0.2 | G34: =J12 -> 0.2 | H34: =J13 -> 0.2 | I34: =J14 -> 0.2 | J34: =J15 -> 0.2 | K34: =J16 -> 0.2
A35: 14 | B35: Націнка ритейлера для полиці, % | D35: Множник D6 − 1 | F35: =$D$6-1 -> 0.4 | G35: =$D$6-1 -> 0.4 | H35: =$D$6-1 -> 0.4 | I35: =$D$6-1 -> 0.4 | J35: =$D$6-1 -> 0.4 | K35: =$D$6-1 -> 0.4
A36: 15 | B36: Множник ритейлера | D36: 1 + крок 14 | F36: =$D$6 -> 1.4 | G36: =$D$6 -> 1.4 | H36: =$D$6 -> 1.4 | I36: =$D$6 -> 1.4 | J36: =$D$6 -> 1.4 | K36: =$D$6 -> 1.4
A37: 16 | B37: Ціна на полиці з ПДВ, грн/уп. | D37: Крок 9 × крок 15 | F37: =K11 -> 132.69026 | G37: =K12 -> 132.69026 | H37: =K13 -> 114.99822 | I37: =K14 -> 114.99822 | J37: =K15 -> 114.99822 | K37: =K16 -> 114.99822
A38: 17 | B38: Ціна партнеру при нульовому нашому прибутку, грн/уп. | D38: Крок 3 ÷ крок 6 | F38: =L11 -> 69.50442 | G38: =L12 -> 69.50442 | H38: =L13 -> 60.237164 | I38: =L14 -> 60.237164 | J38: =L15 -> 60.237164 | K38: =L16 -> 60.237164
A39: 18 | B39: Полиця при нульовому нашому прибутку, грн/уп. | D39: Крок 17 × крок 15 | F39: =M11 -> 97.306188 | G39: =M12 -> 97.306188 | H39: =M13 -> 84.33203 | I39: =M14 -> 84.33203 | J39: =M15 -> 84.33203 | K39: =M16 -> 84.33203

Sheet Цена 120 грн — 6 паллет
A1: ВНУТРЕННИЙ СЦЕНАРИЙ — только для нас, не для SIAS · бонус 25 %, маржа 20 %, доп. расходы 10 ₴ (допущение) · 6 паллет
A2: ЗАПРОС ДЛЯ SIAS, €/пачку | B2: =B20 -> 0.3 | D2: ="сейчас €"&B5&" (4 SKU) / €"&B7&" (2 SKU)" -> сейчас €0.65 (4 SKU) / €0.75 (2 SKU) | F2: ="снижение −"&ROUND((1-B20/B5)*100,0)&" % / −"&ROUND((1-B20/B7)*100,0)&" %" -> снижение −54 % / −60 % | H2: одна цена на 6 SKU
A3: Вариант | B3: Закупка SIAS за пачку | C3: ="Себестоимость в Украине"&CHAR(10)&"товар + расходы в Украине"&IF(G14>0," + "&ROUND(G14,2)&" ₴ доп.","") -> Себестоимость в Украине товар + расходы в Украине + 10 ₴ доп. | D3: Цена партнёру СС ÷ (1 − бонус − маржа) | E3: ="Бонус сети"&CHAR(10)&ROUND(D14*100,0)&" % цены партнёру" -> Бонус сети 25 % цены партнёру | F3: ="Наша прибыль"&CHAR(10)&ROUND(C14*100,0)&" % цены партнёру" -> Наша прибыль 20 % цены партнёру | G3: Наценка магазина +40 % к цене партнёру | H3: ПОЛКА с НДС цена партнёру × 1,40
A4: ДО · Vegetable, Spicy, Beef, Chicken (4 SKU) | B4: =B5*F14 -> 33.28 | C4: =$B$24*F14+$G$14 -> 68.0632 | D4: =C4/(1-D14-C14) -> 123.75127 | E4: =D4*D14 -> 30.937818 | F4: =D4-C4-E4 -> 24.750255 | G4: =D4*(E14-1) -> 49.500509 | H4: =D4*E14 -> 173.25178
B5: 0.65 | C5: =C4/F14 -> 1.3293594 | D5: =D4/F14 -> 2.417017 | E5: =E4/F14 -> 0.60425426 | F5: =F4/F14 -> 0.48340341 | G5: =G4/F14 -> 0.96680682 | H5: =H4/F14 -> 3.3838239
A6: ДО · Gouda Cheese, Carbonara Spicy (2 SKU) | B6: =B7*F14 -> 38.4 | C6: =$B$25*F14+$G$14 -> 76.996 | D6: =C6/(1-D14-C14) -> 139.99273 | E6: =D6*D14 -> 34.998182 | F6: =D6-C6-E6 -> 27.998545 | G6: =D6*(E14-1) -> 55.997091 | H6: =D6*E14 -> 195.98982
B7: 0.75 | C7: =C6/F14 -> 1.5038281 | D7: =D6/F14 -> 2.734233 | E7: =E6/F14 -> 0.68355824 | F7: =F6/F14 -> 0.54684659 | G7: =G6/F14 -> 1.0936932 | H7: =H6/F14 -> 3.8279261
A8: ПОСЛЕ · запрос SIAS (все 6 SKU) | B8: =B9*F14 -> 15.36 | C8: =B22 -> 46.9 | D8: =C8/(1-D14-C14) -> 85.272727 | E8: =D8*D14 -> 21.318182 | F8: =D8-C8-E8 -> 17.054545 | G8: =D8*(E14-1) -> 34.109091 | H8: =D8*E14 -> 119.38182
B9: =B20 -> 0.3 | C9: =C8/F14 -> 0.91601562 | D9: =D8/F14 -> 1.665483 | E9: =E8/F14 -> 0.41637074 | F9: =F8/F14 -> 0.33309659 | G9: =G8/F14 -> 0.66619318 | H9: =H8/F14 -> 2.3316761
A10: ИЗМЕНЕНИЕ: ПОСЛЕ − ДО (4 SKU) | B10: =B8-B4 -> -17.92 | C10: =C8-C4 -> -21.1632 | D10: =D8-D4 -> -38.478545 | E10: =E8-E4 -> -9.6196364 | F10: =F8-F4 -> -7.6957091 | G10: =G8-G4 -> -15.391418 | H10: =H8-H4 -> -53.869964
B11: =B9-B5 -> -0.35 | C11: =C9-C5 -> -0.41334375 | D11: =D9-D5 -> -0.75153409 | E11: =E9-E5 -> -0.18788352 | F11: =F9-F5 -> -0.15030682 | G11: =G9-G5 -> -0.30061364 | H11: =H9-H5 -> -1.0521477
A12: ИСХОДНЫЕ ДАННЫЕ — жёлтое можно менять, зелёное из вкладки «Финмодель 6 паллет»
B13: Полка, ₴ | C13: Наша маржа | D13: Бонус сети | E13: Множитель полки | F13: Курс ₴/€ | G13: Доп. расходы в СС, ₴/уп. (допущение)
A14: Цель расчёта и условия модели | B14: 120 | C14: 0.2 | D14: ='Финмодель 6 паллет'!D4 -> 0.25 | E14: ='Финмодель 6 паллет'!D6 -> 1.4 | F14: ='Финмодель 6 паллет'!D3 -> 51.2 | G14: 10
B15: Импортный ПДВ | C15: Финансирование | D15: Пошлина | E15: Перевозка партии, € | F15: Брокер, € | G15: Прочие, €
B16: 0.2 | C16: 0.025 | D16: 0 | E16: 2600 | F16: 288 | G16: 42
B17: Доля фрахта в таможне | C17: Паллет в партии | D17: Пачек на паллете
B18: 0.7 | C18: 6 | D18: 1600
A20: Запрос SIAS, €/уп. (вниз до евроцента) | B20: =ROUNDDOWN(((B14/E14*(1-D14-C14)-G14)/F14/(1+C16)-(E16+F16+G16+E16*B18*(D16+B16*(1+D16)))/(C18*D18))/((1+D16)*(1+B16)),2) -> 0.3
A21: Предельная закупка до округления, €/уп. | B21: =((B14/E14*(1-D14-C14)-G14)/F14/(1+C16)-(E16+F16+G16+E16*B18*(D16+B16*(1+D16)))/(C18*D18))/((1+D16)*(1+B16)) -> 0.30385634
A22: Себестоимость в Украине при запросе (с доп. расходами), ₴/уп. | B22: =(B20*F14+(E16+F16+G16)/(C18*D18)*F14+(B20+E16*B18/(C18*D18))*D16*F14+(B20+E16*B18/(C18*D18))*(1+D16)*B16*F14)*(1+C16)+G14 -> 46.9
A24: СС из Self-Cost, 4 SKU (Vegetable…), €/уп. — без доп. расходов | B24: ='Финмодель 6 паллет'!E13 -> 1.1340469
A25: СС из Self-Cost, 2 SKU (Gouda, Carbonara), €/уп. — без доп. расходов | B25: ='Финмодель 6 паллет'!E11 -> 1.3085156

Sheet Цена 120 грн — 33 паллет
A1: ВНУТРЕННИЙ СЦЕНАРИЙ — только для нас, не для SIAS · бонус 25 %, маржа 20 %, доп. расходы 10 ₴ (допущение) · 33 паллеты (Full Truck)
A2: ЗАПРОС ДЛЯ SIAS, €/пачку | B2: =B19 -> 0.51 | D2: ="сейчас €"&B5&" (4 SKU) / €"&B7&" (2 SKU)" -> сейчас €0.65 (4 SKU) / €0.75 (2 SKU) | F2: ="снижение −"&ROUND((1-B19/B5)*100,0)&" % / −"&ROUND((1-B19/B7)*100,0)&" %" -> снижение −22 % / −32 % | H2: одна цена на 6 SKU
A3: Вариант | B3: Закупка SIAS за пачку | C3: ="Себестоимость в Украине"&CHAR(10)&"товар + расходы в Украине"&IF(G14>0," + "&ROUND(G14,2)&" ₴ доп.","") -> Себестоимость в Украине товар + расходы в Украине + 10 ₴ доп. | D3: Цена партнёру СС ÷ (1 − бонус − маржа) | E3: ="Бонус сети"&CHAR(10)&ROUND(D14*100,0)&" % цены партнёру" -> Бонус сети 25 % цены партнёру | F3: ="Наша прибыль"&CHAR(10)&ROUND(C14*100,0)&" % цены партнёру" -> Наша прибыль 20 % цены партнёру | G3: Наценка магазина +40 % к цене партнёру | H3: ПОЛКА с НДС цена партнёру × 1,40
A4: ДО · Vegetable, Spicy, Beef, Chicken (4 SKU) | B4: =B5*F14 -> 33.28 | C4: =$B$23*F14+$G$14 -> 55.177873 | D4: =C4/(1-D14-C14) -> 100.32341 | E4: =D4*D14 -> 25.080851 | F4: =D4-C4-E4 -> 20.064681 | G4: =D4*(E14-1) -> 40.129362 | H4: =D4*E14 -> 140.45277
B5: 0.65 | C5: =C4/F14 -> 1.0776928 | D5: =D4/F14 -> 1.9594415 | E5: =E4/F14 -> 0.48986038 | F5: =F4/F14 -> 0.3918883 | G5: =G4/F14 -> 0.78377661 | H5: =H4/F14 -> 2.7432181
A6: ДО · Gouda Cheese, Carbonara Spicy (2 SKU) | B6: =B7*F14 -> 38.4 | C6: =$B$24*F14+$G$14 -> 62.128315 | D6: =C6/(1-D14-C14) -> 112.96057 | E6: =D6*D14 -> 28.240143 | F6: =D6-C6-E6 -> 22.592115 | G6: =D6*(E14-1) -> 45.184229 | H6: =D6*E14 -> 158.1448
B7: 0.75 | C7: =C6/F14 -> 1.2134437 | D7: =D6/F14 -> 2.2062612 | E7: =E6/F14 -> 0.5515653 | F7: =F6/F14 -> 0.44125224 | G7: =G6/F14 -> 0.88250448 | H7: =H6/F14 -> 3.0887657
A8: ПОСЛЕ · запрос SIAS (все 6 SKU) | B8: =B9*F14 -> 26.112 | C8: =B21 -> 46.638196 | D8: =C8/(1-D14-C14) -> 84.796721 | E8: =D8*D14 -> 21.19918 | F8: =D8-C8-E8 -> 16.959344 | G8: =D8*(E14-1) -> 33.918688 | H8: =D8*E14 -> 118.71541
B9: =B19 -> 0.51 | C9: =C8/F14 -> 0.91090227 | D9: =D8/F14 -> 1.656186 | E9: =E8/F14 -> 0.41404649 | F9: =F8/F14 -> 0.33123719 | G9: =G8/F14 -> 0.66247438 | H9: =H8/F14 -> 2.3186603
A10: ИЗМЕНЕНИЕ: ПОСЛЕ − ДО (4 SKU) | B10: =B8-B4 -> -7.168 | C10: =C8-C4 -> -8.5396767 | D10: =D8-D4 -> -15.526685 | E10: =E8-E4 -> -3.8816712 | F10: =F8-F4 -> -3.105337 | G10: =G8-G4 -> -6.210674 | H10: =H8-H4 -> -21.737359
B11: =B9-B5 -> -0.14 | C11: =C9-C5 -> -0.16679056 | D11: =D9-D5 -> -0.30325557 | E11: =E9-E5 -> -0.075813891 | F11: =F9-F5 -> -0.060651113 | G11: =G9-G5 -> -0.12130223 | H11: =H9-H5 -> -0.42455779
A12: ИСХОДНЫЕ ДАННЫЕ — жёлтое можно менять, зелёное из вкладки «Финмодель 33 паллет»
B13: Полка, ₴ | C13: Наша маржа | D13: Бонус сети | E13: Множитель полки | F13: Курс ₴/€ | G13: Доп. расходы в СС, ₴/уп. (допущение)
A14: Цель расчёта и условия модели | B14: 120 | C14: 0.2 | D14: ='Финмодель 33 паллет'!D4 -> 0.25 | E14: ='Финмодель 33 паллет'!D6 -> 1.4 | F14: ='Финмодель 33 паллет'!D3 -> 51.2 | G14: 10
B15: Импортный ПДВ | C15: Финансирование | D15: Пошлина | E15: Перевозка партии, € | F15: Брокер, € | G15: Прочие, €
B16: 0.2 | C16: 0.025 | D16: 0 | E16: 3700 | F16: 288 | G16: 42
B17: Доля фрахта в таможне | C17: Паллет в партии | D17: Пачек на паллете
B18: 0.7 | C18: 33 | D18: 1600
A19: Запрос SIAS, €/уп. (вниз до евроцента) | B19: =ROUNDDOWN(((B14/E14*(1-D14-C14)-G14)/F14/(1+C16)-(E16+F16+G16+E16*B18*(D16+B16*(1+D16)))/(C18*D18))/((1+D16)*(1+B16)),2) -> 0.51
A20: Предельная закупка до округления, €/уп. | B20: =((B14/E14*(1-D14-C14)-G14)/F14/(1+C16)-(E16+F16+G16+E16*B18*(D16+B16*(1+D16)))/(C18*D18))/((1+D16)*(1+B16)) -> 0.51801354
A21: Себестоимость в Украине при запросе (с доп. расходами), ₴/уп. | B21: =(B19*F14+(E16+F16+G16)/(C18*D18)*F14+(B19+E16*B18/(C18*D18))*D16*F14+(B19+E16*B18/(C18*D18))*(1+D16)*B16*F14)*(1+C16)+G14 -> 46.638196
A23: СС из Self-Cost, 4 SKU (Vegetable…), €/уп. — без доп. расходов | B23: ='Финмодель 33 паллет'!E13 -> 0.88238033
A24: СС из Self-Cost, 2 SKU (Gouda, Carbonara), €/уп. — без доп. расходов | B24: ='Финмодель 33 паллет'!E11 -> 1.0181312

Sheet Сценарии
A1: ВНУТРЕННИЙ ФАЙЛ — только для нас · Сценарии структуры цены: запрос к SIAS при другой марже, бонусе сети и доп. расходах
A2: ="Запрос зависит от суммы «бонус + маржа» и доп. расходов: допустимая СС = цена партнёру × (1 − бонус − маржа) − доп. расходы. 1 п.п. маржи или бонуса = "&ROUND(E5/100,2)&" ₴ на пачку = €"&ROUND(E5/100/D5/(1+C5)/((1+G5)*(1+F5)),4)&" к запросу." -> Запрос зависит от суммы «бонус + маржа» и доп. расходов: допустимая СС = цена партнёру × (1 − бонус − маржа) − доп. расходы. 1 п.п. маржи или бонуса = 0.86 ₴ на пачку = €0.0136 к запросу.
A4: Полка, ₴ | B4: Множитель полки | C4: Финансирование | D4: Курс ₴/€ | E4: Цена партнёру при полке, ₴ | F4: Импортный ПДВ | G4: Пошлина
A5: ='Цена 120 грн — 33 паллет'!B14 -> 120 | B5: ='Цена 120 грн — 33 паллет'!E14 -> 1.4 | C5: ='Цена 120 грн — 33 паллет'!C16 -> 0.025 | D5: ='Цена 120 грн — 33 паллет'!F14 -> 51.2 | E5: =A5/B5 -> 85.714286 | F5: ='Цена 120 грн — 33 паллет'!B16 -> 0.2 | G5: ='Цена 120 грн — 33 паллет'!D16 -> 0
A7: Сценарий | B7: Бонус сети | C7: Маржа, которую показываем | D7: Доп. расходы в СС, ₴/уп. | E7: Бонус сети, ₴ | F7: Наша прибыль, ₴ | G7: Бюджет СС (товар + расходы + доп.), ₴ | H7: СС товара в Украине, ₴ | I7: 33 палеты: макс. закупка, € | J7: 33 палеты: ЗАПРОС SIAS, € | K7: к текущим €0,65, % | L7: 6 палет: макс. закупка, € | M7: 6 палет: ЗАПРОС SIAS, € | N7: к текущим €0,65, %
A8: БАЗА · как было в прошлой версии модели
A9: Было: бонус 25 % + маржа 30 % | B9: 0.25 | C9: 0.3 | D9: 0 | E9: =$E$5*B9 -> 21.428571 | F9: =$E$5*C9 -> 25.714286 | G9: =$E$5-E9-F9 -> 38.571429 | H9: =G9-D9 -> 38.571429 | I9: =(($H9/$D$5/(1+$C$5)-('Цена 120 грн — 33 паллет'!E16+'Цена 120 грн — 33 паллет'!F16+'Цена 120 грн — 33 паллет'!G16+'Цена 120 грн — 33 паллет'!E16*'Цена 120 грн — 33 паллет'!B18*($G$5+$F$5*(1+$G$5)))/('Цена 120 грн — 33 паллет'!C18*'Цена 120 грн — 33 паллет'!D18))/((1+$G$5)*(1+$F$5))) -> 0.54069792 | J9: =ROUNDDOWN((($H9/$D$5/(1+$C$5)-('Цена 120 грн — 33 паллет'!E16+'Цена 120 грн — 33 паллет'!F16+'Цена 120 грн — 33 паллет'!G16+'Цена 120 грн — 33 паллет'!E16*'Цена 120 грн — 33 паллет'!B18*($G$5+$F$5*(1+$G$5)))/('Цена 120 грн — 33 паллет'!C18*'Цена 120 грн — 33 паллет'!D18))/((1+$G$5)*(1+$F$5))),2) -> 0.54 | K9: =J9/0.65-1 -> -0.16923077 | L9: =(($H9/$D$5/(1+$C$5)-('Цена 120 грн — 6 паллет'!E16+'Цена 120 грн — 6 паллет'!F16+'Цена 120 грн — 6 паллет'!G16+'Цена 120 грн — 6 паллет'!E16*'Цена 120 грн — 6 паллет'!B18*($G$5+$F$5*(1+$G$5)))/('Цена 120 грн — 6 паллет'!C18*'Цена 120 грн — 6 паллет'!D18))/((1+$G$5)*(1+$F$5))) -> 0.32654072 | M9: =ROUNDDOWN((($H9/$D$5/(1+$C$5)-('Цена 120 грн — 6 паллет'!E16+'Цена 120 грн — 6 паллет'!F16+'Цена 120 грн — 6 паллет'!G16+'Цена 120 грн — 6 паллет'!E16*'Цена 120 грн — 6 паллет'!B18*($G$5+$F$5*(1+$G$5)))/('Цена 120 грн — 6 паллет'!C18*'Цена 120 грн — 6 паллет'!D18))/((1+$G$5)*(1+$F$5))),2) -> 0.32 | N9: =M9/0.65-1 -> -0.50769231
A10: ТА ЖЕ ЦЕНА ЗАПРОСА, другая структура (сумма «бонус + маржа» и расходов не меняется)
A11: ★ Бонус сети 35 % + маржа 20 % (без доп. расходов) | B11: 0.35 | C11: 0.2 | D11: 0 | E11: =$E$5*B11 -> 30 | F11: =$E$5*C11 -> 17.142857 | G11: =$E$5-E11-F11 -> 38.571429 | H11: =G11-D11 -> 38.571429 | I11: =(($H11/$D$5/(1+$C$5)-('Цена 120 грн — 33 паллет'!E16+'Цена 120 грн — 33 паллет'!F16+'Цена 120 грн — 33 паллет'!G16+'Цена 120 грн — 33 паллет'!E16*'Цена 120 грн — 33 паллет'!B18*($G$5+$F$5*(1+$G$5)))/('Цена 120 грн — 33 паллет'!C18*'Цена 120 грн — 33 паллет'!D18))/((1+$G$5)*(1+$F$5))) -> 0.54069792 | J11: =ROUNDDOWN((($H11/$D$5/(1+$C$5)-('Цена 120 грн — 33 паллет'!E16+'Цена 120 грн — 33 паллет'!F16+'Цена 120 грн — 33 паллет'!G16+'Цена 120 грн — 33 паллет'!E16*'Цена 120 грн — 33 паллет'!B18*($G$5+$F$5*(1+$G$5)))/('Цена 120 грн — 33 паллет'!C18*'Цена 120 грн — 33 паллет'!D18))/((1+$G$5)*(1+$F$5))),2) -> 0.54 | K11: =J11/0.65-1 -> -0.16923077 | L11: =(($H11/$D$5/(1+$C$5)-('Цена 120 грн — 6 паллет'!E16+'Цена 120 грн — 6 паллет'!F16+'Цена 120 грн — 6 паллет'!G16+'Цена 120 грн — 6 паллет'!E16*'Цена 120 грн — 6 паллет'!B18*($G$5+$F$5*(1+$G$5)))/('Цена 120 грн — 6 паллет'!C18*'Цена 120 грн — 6 паллет'!D18))/((1+$G$5)*(1+$F$5))) -> 0.32654072 | M11: =ROUNDDOWN((($H11/$D$5/(1+$C$5)-('Цена 120 грн — 6 паллет'!E16+'Цена 120 грн — 6 паллет'!F16+'Цена 120 грн — 6 паллет'!G16+'Цена 120 грн — 6 паллет'!E16*'Цена 120 грн — 6 паллет'!B18*($G$5+$F$5*(1+$G$5)))/('Цена 120 грн — 6 паллет'!C18*'Цена 120 грн — 6 паллет'!D18))/((1+$G$5)*(1+$F$5))),2) -> 0.32 | N11: =M11/0.65-1 -> -0.50769231
A12: Бонус 30 % + маржа 25 % | B12: 0.3 | C12: 0.25 | D12: 0 | E12: =$E$5*B12 -> 25.714286 | F12: =$E$5*C12 -> 21.428571 | G12: =$E$5-E12-F12 -> 38.571429 | H12: =G12-D12 -> 38.571429 | I12: =(($H12/$D$5/(1+$C$5)-('Цена 120 грн — 33 паллет'!E16+'Цена 120 грн — 33 паллет'!F16+'Цена 120 грн — 33 паллет'!G16+'Цена 120 грн — 33 паллет'!E16*'Цена 120 грн — 33 паллет'!B18*($G$5+$F$5*(1+$G$5)))/('Цена 120 грн — 33 паллет'!C18*'Цена 120 грн — 33 паллет'!D18))/((1+$G$5)*(1+$F$5))) -> 0.54069792 | J12: =ROUNDDOWN((($H12/$D$5/(1+$C$5)-('Цена 120 грн — 33 паллет'!E16+'Цена 120 грн — 33 паллет'!F16+'Цена 120 грн — 33 паллет'!G16+'Цена 120 грн — 33 паллет'!E16*'Цена 120 грн — 33 паллет'!B18*($G$5+$F$5*(1+$G$5)))/('Цена 120 грн — 33 паллет'!C18*'Цена 120 грн — 33 паллет'!D18))/((1+$G$5)*(1+$F$5))),2) -> 0.54 | K12: =J12/0.65-1 -> -0.16923077 | L12: =(($H12/$D$5/(1+$C$5)-('Цена 120 грн — 6 паллет'!E16+'Цена 120 грн — 6 паллет'!F16+'Цена 120 грн — 6 паллет'!G16+'Цена 120 грн — 6 паллет'!E16*'Цена 120 грн — 6 паллет'!B18*($G$5+$F$5*(1+$G$5)))/('Цена 120 грн — 6 паллет'!C18*'Цена 120 грн — 6 паллет'!D18))/((1+$G$5)*(1+$F$5))) -> 0.32654072 | M12: =ROUNDDOWN((($H12/$D$5/(1+$C$5)-('Цена 120 грн — 6 паллет'!E16+'Цена 120 грн — 6 паллет'!F16+'Цена 120 грн — 6 паллет'!G16+'Цена 120 грн — 6 паллет'!E16*'Цена 120 грн — 6 паллет'!B18*($G$5+$F$5*(1+$G$5)))/('Цена 120 грн — 6 паллет'!C18*'Цена 120 грн — 6 паллет'!D18))/((1+$G$5)*(1+$F$5))),2) -> 0.32 | N12: =M12/0.65-1 -> -0.50769231
A13: Бонус 25 % + маржа 20 % + доп. расходы, подобранные под тот же запрос | B13: 0.25 | C13: 0.2 | D13: =ROUND($E$5*((1-B13-C13)-(1-$B$9-$C$9)),2) -> 8.57 | E13: =$E$5*B13 -> 21.428571 | F13: =$E$5*C13 -> 17.142857 | G13: =$E$5-E13-F13 -> 47.142857 | H13: =G13-D13 -> 38.572857 | I13: =(($H13/$D$5/(1+$C$5)-('Цена 120 грн — 33 паллет'!E16+'Цена 120 грн — 33 паллет'!F16+'Цена 120 грн — 33 паллет'!G16+'Цена 120 грн — 33 паллет'!E16*'Цена 120 грн — 33 паллет'!B18*($G$5+$F$5*(1+$G$5)))/('Цена 120 грн — 33 паллет'!C18*'Цена 120 грн — 33 паллет'!D18))/((1+$G$5)*(1+$F$5))) -> 0.5407206 | J13: =ROUNDDOWN((($H13/$D$5/(1+$C$5)-('Цена 120 грн — 33 паллет'!E16+'Цена 120 грн — 33 паллет'!F16+'Цена 120 грн — 33 паллет'!G16+'Цена 120 грн — 33 паллет'!E16*'Цена 120 грн — 33 паллет'!B18*($G$5+$F$5*(1+$G$5)))/('Цена 120 грн — 33 паллет'!C18*'Цена 120 грн — 33 паллет'!D18))/((1+$G$5)*(1+$F$5))),2) -> 0.54 | K13: =J13/0.65-1 -> -0.16923077 | L13: =(($H13/$D$5/(1+$C$5)-('Цена 120 грн — 6 паллет'!E16+'Цена 120 грн — 6 паллет'!F16+'Цена 120 грн — 6 паллет'!G16+'Цена 120 грн — 6 паллет'!E16*'Цена 120 грн — 6 паллет'!B18*($G$5+$F$5*(1+$G$5)))/('Цена 120 грн — 6 паллет'!C18*'Цена 120 грн — 6 паллет'!D18))/((1+$G$5)*(1+$F$5))) -> 0.32656341 | M13: =ROUNDDOWN((($H13/$D$5/(1+$C$5)-('Цена 120 грн — 6 паллет'!E16+'Цена 120 грн — 6 паллет'!F16+'Цена 120 грн — 6 паллет'!G16+'Цена 120 грн — 6 паллет'!E16*'Цена 120 грн — 6 паллет'!B18*($G$5+$F$5*(1+$G$5)))/('Цена 120 грн — 6 паллет'!C18*'Цена 120 грн — 6 паллет'!D18))/((1+$G$5)*(1+$F$5))),2) -> 0.32 | N13: =M13/0.65-1 -> -0.50769231
A14: Бонус 25 % + маржа 25 % + доп. расходы, подобранные под тот же запрос | B14: 0.25 | C14: 0.25 | D14: =ROUND($E$5*((1-B14-C14)-(1-$B$9-$C$9)),2) -> 4.29 | E14: =$E$5*B14 -> 21.428571 | F14: =$E$5*C14 -> 21.428571 | G14: =$E$5-E14-F14 -> 42.857143 | H14: =G14-D14 -> 38.567143 | I14: =(($H14/$D$5/(1+$C$5)-('Цена 120 грн — 33 паллет'!E16+'Цена 120 грн — 33 паллет'!F16+'Цена 120 грн — 33 паллет'!G16+'Цена 120 грн — 33 паллет'!E16*'Цена 120 грн — 33 паллет'!B18*($G$5+$F$5*(1+$G$5)))/('Цена 120 грн — 33 паллет'!C18*'Цена 120 грн — 33 паллет'!D18))/((1+$G$5)*(1+$F$5))) -> 0.54062987 | J14: =ROUNDDOWN((($H14/$D$5/(1+$C$5)-('Цена 120 грн — 33 паллет'!E16+'Цена 120 грн — 33 паллет'!F16+'Цена 120 грн — 33 паллет'!G16+'Цена 120 грн — 33 паллет'!E16*'Цена 120 грн — 33 паллет'!B18*($G$5+$F$5*(1+$G$5)))/('Цена 120 грн — 33 паллет'!C18*'Цена 120 грн — 33 паллет'!D18))/((1+$G$5)*(1+$F$5))),2) -> 0.54 | K14: =J14/0.65-1 -> -0.16923077 | L14: =(($H14/$D$5/(1+$C$5)-('Цена 120 грн — 6 паллет'!E16+'Цена 120 грн — 6 паллет'!F16+'Цена 120 грн — 6 паллет'!G16+'Цена 120 грн — 6 паллет'!E16*'Цена 120 грн — 6 паллет'!B18*($G$5+$F$5*(1+$G$5)))/('Цена 120 грн — 6 паллет'!C18*'Цена 120 грн — 6 паллет'!D18))/((1+$G$5)*(1+$F$5))) -> 0.32647267 | M14: =ROUNDDOWN((($H14/$D$5/(1+$C$5)-('Цена 120 грн — 6 паллет'!E16+'Цена 120 грн — 6 паллет'!F16+'Цена 120 грн — 6 паллет'!G16+'Цена 120 грн — 6 паллет'!E16*'Цена 120 грн — 6 паллет'!B18*($G$5+$F$5*(1+$G$5)))/('Цена 120 грн — 6 паллет'!C18*'Цена 120 грн — 6 паллет'!D18))/((1+$G$5)*(1+$F$5))),2) -> 0.32 | N14: =M14/0.65-1 -> -0.50769231
A15: ПРИМЕР: +10 ₴ в себестоимость (запрос становится ниже)
A16: Бонус 25 % + маржа 20 % + 10 ₴ | B16: 0.25 | C16: 0.2 | D16: 10 | E16: =$E$5*B16 -> 21.428571 | F16: =$E$5*C16 -> 17.142857 | G16: =$E$5-E16-F16 -> 47.142857 | H16: =G16-D16 -> 37.142857 | I16: =(($H16/$D$5/(1+$C$5)-('Цена 120 грн — 33 паллет'!E16+'Цена 120 грн — 33 паллет'!F16+'Цена 120 грн — 33 паллет'!G16+'Цена 120 грн — 33 паллет'!E16*'Цена 120 грн — 33 паллет'!B18*($G$5+$F$5*(1+$G$5)))/('Цена 120 грн — 33 паллет'!C18*'Цена 120 грн — 33 паллет'!D18))/((1+$G$5)*(1+$F$5))) -> 0.51801354 | J16: =ROUNDDOWN((($H16/$D$5/(1+$C$5)-('Цена 120 грн — 33 паллет'!E16+'Цена 120 грн — 33 паллет'!F16+'Цена 120 грн — 33 паллет'!G16+'Цена 120 грн — 33 паллет'!E16*'Цена 120 грн — 33 паллет'!B18*($G$5+$F$5*(1+$G$5)))/('Цена 120 грн — 33 паллет'!C18*'Цена 120 грн — 33 паллет'!D18))/((1+$G$5)*(1+$F$5))),2) -> 0.51 | K16: =J16/0.65-1 -> -0.21538462 | L16: =(($H16/$D$5/(1+$C$5)-('Цена 120 грн — 6 паллет'!E16+'Цена 120 грн — 6 паллет'!F16+'Цена 120 грн — 6 паллет'!G16+'Цена 120 грн — 6 паллет'!E16*'Цена 120 грн — 6 паллет'!B18*($G$5+$F$5*(1+$G$5)))/('Цена 120 грн — 6 паллет'!C18*'Цена 120 грн — 6 паллет'!D18))/((1+$G$5)*(1+$F$5))) -> 0.30385634 | M16: =ROUNDDOWN((($H16/$D$5/(1+$C$5)-('Цена 120 грн — 6 паллет'!E16+'Цена 120 грн — 6 паллет'!F16+'Цена 120 грн — 6 паллет'!G16+'Цена 120 грн — 6 паллет'!E16*'Цена 120 грн — 6 паллет'!B18*($G$5+$F$5*(1+$G$5)))/('Цена 120 грн — 6 паллет'!C18*'Цена 120 грн — 6 паллет'!D18))/((1+$G$5)*(1+$F$5))),2) -> 0.3 | N16: =M16/0.65-1 -> -0.53846154
A17: Бонус 25 % + маржа 25 % + 10 ₴ | B17: 0.25 | C17: 0.25 | D17: 10 | E17: =$E$5*B17 -> 21.428571 | F17: =$E$5*C17 -> 21.428571 | G17: =$E$5-E17-F17 -> 42.857143 | H17: =G17-D17 -> 32.857143 | I17: =(($H17/$D$5/(1+$C$5)-('Цена 120 грн — 33 паллет'!E16+'Цена 120 грн — 33 паллет'!F16+'Цена 120 грн — 33 паллет'!G16+'Цена 120 грн — 33 паллет'!E16*'Цена 120 грн — 33 паллет'!B18*($G$5+$F$5*(1+$G$5)))/('Цена 120 грн — 33 паллет'!C18*'Цена 120 грн — 33 паллет'!D18))/((1+$G$5)*(1+$F$5))) -> 0.44996041 | J17: =ROUNDDOWN((($H17/$D$5/(1+$C$5)-('Цена 120 грн — 33 паллет'!E16+'Цена 120 грн — 33 паллет'!F16+'Цена 120 грн — 33 паллет'!G16+'Цена 120 грн — 33 паллет'!E16*'Цена 120 грн — 33 паллет'!B18*($G$5+$F$5*(1+$G$5)))/('Цена 120 грн — 33 паллет'!C18*'Цена 120 грн — 33 паллет'!D18))/((1+$G$5)*(1+$F$5))),2) -> 0.44 | K17: =J17/0.65-1 -> -0.32307692 | L17: =(($H17/$D$5/(1+$C$5)-('Цена 120 грн — 6 паллет'!E16+'Цена 120 грн — 6 паллет'!F16+'Цена 120 грн — 6 паллет'!G16+'Цена 120 грн — 6 паллет'!E16*'Цена 120 грн — 6 паллет'!B18*($G$5+$F$5*(1+$G$5)))/('Цена 120 грн — 6 паллет'!C18*'Цена 120 грн — 6 паллет'!D18))/((1+$G$5)*(1+$F$5))) -> 0.23580321 | M17: =ROUNDDOWN((($H17/$D$5/(1+$C$5)-('Цена 120 грн — 6 паллет'!E16+'Цена 120 грн — 6 паллет'!F16+'Цена 120 грн — 6 паллет'!G16+'Цена 120 грн — 6 паллет'!E16*'Цена 120 грн — 6 паллет'!B18*($G$5+$F$5*(1+$G$5)))/('Цена 120 грн — 6 паллет'!C18*'Цена 120 грн — 6 паллет'!D18))/((1+$G$5)*(1+$F$5))),2) -> 0.23 | N17: =M17/0.65-1 -> -0.64615385
A18: Бонус 35 % + маржа 20 % + 10 ₴ | B18: 0.35 | C18: 0.2 | D18: 10 | E18: =$E$5*B18 -> 30 | F18: =$E$5*C18 -> 17.142857 | G18: =$E$5-E18-F18 -> 38.571429 | H18: =G18-D18 -> 28.571429 | I18: =(($H18/$D$5/(1+$C$5)-('Цена 120 грн — 33 паллет'!E16+'Цена 120 грн — 33 паллет'!F16+'Цена 120 грн — 33 паллет'!G16+'Цена 120 грн — 33 паллет'!E16*'Цена 120 грн — 33 паллет'!B18*($G$5+$F$5*(1+$G$5)))/('Цена 120 грн — 33 паллет'!C18*'Цена 120 грн — 33 паллет'!D18))/((1+$G$5)*(1+$F$5))) -> 0.38190727 | J18: =ROUNDDOWN((($H18/$D$5/(1+$C$5)-('Цена 120 грн — 33 паллет'!E16+'Цена 120 грн — 33 паллет'!F16+'Цена 120 грн — 33 паллет'!G16+'Цена 120 грн — 33 паллет'!E16*'Цена 120 грн — 33 паллет'!B18*($G$5+$F$5*(1+$G$5)))/('Цена 120 грн — 33 паллет'!C18*'Цена 120 грн — 33 паллет'!D18))/((1+$G$5)*(1+$F$5))),2) -> 0.38 | K18: =J18/0.65-1 -> -0.41538462 | L18: =(($H18/$D$5/(1+$C$5)-('Цена 120 грн — 6 паллет'!E16+'Цена 120 грн — 6 паллет'!F16+'Цена 120 грн — 6 паллет'!G16+'Цена 120 грн — 6 паллет'!E16*'Цена 120 грн — 6 паллет'!B18*($G$5+$F$5*(1+$G$5)))/('Цена 120 грн — 6 паллет'!C18*'Цена 120 грн — 6 паллет'!D18))/((1+$G$5)*(1+$F$5))) -> 0.16775007 | M18: =ROUNDDOWN((($H18/$D$5/(1+$C$5)-('Цена 120 грн — 6 паллет'!E16+'Цена 120 грн — 6 паллет'!F16+'Цена 120 грн — 6 паллет'!G16+'Цена 120 грн — 6 паллет'!E16*'Цена 120 грн — 6 паллет'!B18*($G$5+$F$5*(1+$G$5)))/('Цена 120 грн — 6 паллет'!C18*'Цена 120 грн — 6 паллет'!D18))/((1+$G$5)*(1+$F$5))),2) -> 0.16 | N18: =M18/0.65-1 -> -0.75384615
A19: Бонус 35 % + маржа 25 % + 10 ₴ | B19: 0.35 | C19: 0.25 | D19: 10 | E19: =$E$5*B19 -> 30 | F19: =$E$5*C19 -> 21.428571 | G19: =$E$5-E19-F19 -> 34.285714 | H19: =G19-D19 -> 24.285714 | I19: =(($H19/$D$5/(1+$C$5)-('Цена 120 грн — 33 паллет'!E16+'Цена 120 грн — 33 паллет'!F16+'Цена 120 грн — 33 паллет'!G16+'Цена 120 грн — 33 паллет'!E16*'Цена 120 грн — 33 паллет'!B18*($G$5+$F$5*(1+$G$5)))/('Цена 120 грн — 33 паллет'!C18*'Цена 120 грн — 33 паллет'!D18))/((1+$G$5)*(1+$F$5))) -> 0.31385413 | J19: =ROUNDDOWN((($H19/$D$5/(1+$C$5)-('Цена 120 грн — 33 паллет'!E16+'Цена 120 грн — 33 паллет'!F16+'Цена 120 грн — 33 паллет'!G16+'Цена 120 грн — 33 паллет'!E16*'Цена 120 грн — 33 паллет'!B18*($G$5+$F$5*(1+$G$5)))/('Цена 120 грн — 33 паллет'!C18*'Цена 120 грн — 33 паллет'!D18))/((1+$G$5)*(1+$F$5))),2) -> 0.31 | K19: =J19/0.65-1 -> -0.52307692 | L19: =(($H19/$D$5/(1+$C$5)-('Цена 120 грн — 6 паллет'!E16+'Цена 120 грн — 6 паллет'!F16+'Цена 120 грн — 6 паллет'!G16+'Цена 120 грн — 6 паллет'!E16*'Цена 120 грн — 6 паллет'!B18*($G$5+$F$5*(1+$G$5)))/('Цена 120 грн — 6 паллет'!C18*'Цена 120 грн — 6 паллет'!D18))/((1+$G$5)*(1+$F$5))) -> 0.099696937 | M19: =ROUNDDOWN((($H19/$D$5/(1+$C$5)-('Цена 120 грн — 6 паллет'!E16+'Цена 120 грн — 6 паллет'!F16+'Цена 120 грн — 6 паллет'!G16+'Цена 120 грн — 6 паллет'!E16*'Цена 120 грн — 6 паллет'!B18*($G$5+$F$5*(1+$G$5)))/('Цена 120 грн — 6 паллет'!C18*'Цена 120 грн — 6 паллет'!D18))/((1+$G$5)*(1+$F$5))),2) -> 0.09 | N19: =M19/0.65-1 -> -0.86153846
A20: БОНУС 35 %: если маржа должна остаться выше 20 %, запрос падает
A21: Бонус 35 % + маржа 25 % | B21: 0.35 | C21: 0.25 | D21: 0 | E21: =$E$5*B21 -> 30 | F21: =$E$5*C21 -> 21.428571 | G21: =$E$5-E21-F21 -> 34.285714 | H21: =G21-D21 -> 34.285714 | I21: =(($H21/$D$5/(1+$C$5)-('Цена 120 грн — 33 паллет'!E16+'Цена 120 грн — 33 паллет'!F16+'Цена 120 грн — 33 паллет'!G16+'Цена 120 грн — 33 паллет'!E16*'Цена 120 грн — 33 паллет'!B18*($G$5+$F$5*(1+$G$5)))/('Цена 120 грн — 33 паллет'!C18*'Цена 120 грн — 33 паллет'!D18))/((1+$G$5)*(1+$F$5))) -> 0.47264478 | J21: =ROUNDDOWN((($H21/$D$5/(1+$C$5)-('Цена 120 грн — 33 паллет'!E16+'Цена 120 грн — 33 паллет'!F16+'Цена 120 грн — 33 паллет'!G16+'Цена 120 грн — 33 паллет'!E16*'Цена 120 грн — 33 паллет'!B18*($G$5+$F$5*(1+$G$5)))/('Цена 120 грн — 33 паллет'!C18*'Цена 120 грн — 33 паллет'!D18))/((1+$G$5)*(1+$F$5))),2) -> 0.47 | K21: =J21/0.65-1 -> -0.27692308 | L21: =(($H21/$D$5/(1+$C$5)-('Цена 120 грн — 6 паллет'!E16+'Цена 120 грн — 6 паллет'!F16+'Цена 120 грн — 6 паллет'!G16+'Цена 120 грн — 6 паллет'!E16*'Цена 120 грн — 6 паллет'!B18*($G$5+$F$5*(1+$G$5)))/('Цена 120 грн — 6 паллет'!C18*'Цена 120 грн — 6 паллет'!D18))/((1+$G$5)*(1+$F$5))) -> 0.25848759 | M21: =ROUNDDOWN((($H21/$D$5/(1+$C$5)-('Цена 120 грн — 6 паллет'!E16+'Цена 120 грн — 6 паллет'!F16+'Цена 120 грн — 6 паллет'!G16+'Цена 120 грн — 6 паллет'!E16*'Цена 120 грн — 6 паллет'!B18*($G$5+$F$5*(1+$G$5)))/('Цена 120 грн — 6 паллет'!C18*'Цена 120 грн — 6 паллет'!D18))/((1+$G$5)*(1+$F$5))),2) -> 0.25 | N21: =M21/0.65-1 -> -0.61538462
A22: Бонус 35 % + маржа 30 % | B22: 0.35 | C22: 0.3 | D22: 0 | E22: =$E$5*B22 -> 30 | F22: =$E$5*C22 -> 25.714286 | G22: =$E$5-E22-F22 -> 30 | H22: =G22-D22 -> 30 | I22: =(($H22/$D$5/(1+$C$5)-('Цена 120 грн — 33 паллет'!E16+'Цена 120 грн — 33 паллет'!F16+'Цена 120 грн — 33 паллет'!G16+'Цена 120 грн — 33 паллет'!E16*'Цена 120 грн — 33 паллет'!B18*($G$5+$F$5*(1+$G$5)))/('Цена 120 грн — 33 паллет'!C18*'Цена 120 грн — 33 паллет'!D18))/((1+$G$5)*(1+$F$5))) -> 0.40459165 | J22: =ROUNDDOWN((($H22/$D$5/(1+$C$5)-('Цена 120 грн — 33 паллет'!E16+'Цена 120 грн — 33 паллет'!F16+'Цена 120 грн — 33 паллет'!G16+'Цена 120 грн — 33 паллет'!E16*'Цена 120 грн — 33 паллет'!B18*($G$5+$F$5*(1+$G$5)))/('Цена 120 грн — 33 паллет'!C18*'Цена 120 грн — 33 паллет'!D18))/((1+$G$5)*(1+$F$5))),2) -> 0.4 | K22: =J22/0.65-1 -> -0.38461538 | L22: =(($H22/$D$5/(1+$C$5)-('Цена 120 грн — 6 паллет'!E16+'Цена 120 грн — 6 паллет'!F16+'Цена 120 грн — 6 паллет'!G16+'Цена 120 грн — 6 паллет'!E16*'Цена 120 грн — 6 паллет'!B18*($G$5+$F$5*(1+$G$5)))/('Цена 120 грн — 6 паллет'!C18*'Цена 120 грн — 6 паллет'!D18))/((1+$G$5)*(1+$F$5))) -> 0.19043445 | M22: =ROUNDDOWN((($H22/$D$5/(1+$C$5)-('Цена 120 грн — 6 паллет'!E16+'Цена 120 грн — 6 паллет'!F16+'Цена 120 грн — 6 паллет'!G16+'Цена 120 грн — 6 паллет'!E16*'Цена 120 грн — 6 паллет'!B18*($G$5+$F$5*(1+$G$5)))/('Цена 120 грн — 6 паллет'!C18*'Цена 120 грн — 6 паллет'!D18))/((1+$G$5)*(1+$F$5))),2) -> 0.19 | N22: =M22/0.65-1 -> -0.70769231
A23: ТОЛЬКО СНИЗИЛИ МАРЖУ (бонус 25 %, без доп. расходов): допустимая закупка растёт — аргумент для SIAS ослабляется
A24: Бонус 25 % + маржа 25 % | B24: 0.25 | C24: 0.25 | D24: 0 | E24: =$E$5*B24 -> 21.428571 | F24: =$E$5*C24 -> 21.428571 | G24: =$E$5-E24-F24 -> 42.857143 | H24: =G24-D24 -> 42.857143 | I24: =(($H24/$D$5/(1+$C$5)-('Цена 120 грн — 33 паллет'!E16+'Цена 120 грн — 33 паллет'!F16+'Цена 120 грн — 33 паллет'!G16+'Цена 120 грн — 33 паллет'!E16*'Цена 120 грн — 33 паллет'!B18*($G$5+$F$5*(1+$G$5)))/('Цена 120 грн — 33 паллет'!C18*'Цена 120 грн — 33 паллет'!D18))/((1+$G$5)*(1+$F$5))) -> 0.60875106 | J24: =ROUNDDOWN((($H24/$D$5/(1+$C$5)-('Цена 120 грн — 33 паллет'!E16+'Цена 120 грн — 33 паллет'!F16+'Цена 120 грн — 33 паллет'!G16+'Цена 120 грн — 33 паллет'!E16*'Цена 120 грн — 33 паллет'!B18*($G$5+$F$5*(1+$G$5)))/('Цена 120 грн — 33 паллет'!C18*'Цена 120 грн — 33 паллет'!D18))/((1+$G$5)*(1+$F$5))),2) -> 0.6 | K24: =J24/0.65-1 -> -0.076923077 | L24: =(($H24/$D$5/(1+$C$5)-('Цена 120 грн — 6 паллет'!E16+'Цена 120 грн — 6 паллет'!F16+'Цена 120 грн — 6 паллет'!G16+'Цена 120 грн — 6 паллет'!E16*'Цена 120 грн — 6 паллет'!B18*($G$5+$F$5*(1+$G$5)))/('Цена 120 грн — 6 паллет'!C18*'Цена 120 грн — 6 паллет'!D18))/((1+$G$5)*(1+$F$5))) -> 0.39459386 | M24: =ROUNDDOWN((($H24/$D$5/(1+$C$5)-('Цена 120 грн — 6 паллет'!E16+'Цена 120 грн — 6 паллет'!F16+'Цена 120 грн — 6 паллет'!G16+'Цена 120 грн — 6 паллет'!E16*'Цена 120 грн — 6 паллет'!B18*($G$5+$F$5*(1+$G$5)))/('Цена 120 грн — 6 паллет'!C18*'Цена 120 грн — 6 паллет'!D18))/((1+$G$5)*(1+$F$5))),2) -> 0.39 | N24: =M24/0.65-1 -> -0.4
A25: Бонус 25 % + маржа 20 % | B25: 0.25 | C25: 0.2 | D25: 0 | E25: =$E$5*B25 -> 21.428571 | F25: =$E$5*C25 -> 17.142857 | G25: =$E$5-E25-F25 -> 47.142857 | H25: =G25-D25 -> 47.142857 | I25: =(($H25/$D$5/(1+$C$5)-('Цена 120 грн — 33 паллет'!E16+'Цена 120 грн — 33 паллет'!F16+'Цена 120 грн — 33 паллет'!G16+'Цена 120 грн — 33 паллет'!E16*'Цена 120 грн — 33 паллет'!B18*($G$5+$F$5*(1+$G$5)))/('Цена 120 грн — 33 паллет'!C18*'Цена 120 грн — 33 паллет'!D18))/((1+$G$5)*(1+$F$5))) -> 0.67680419 | J25: =ROUNDDOWN((($H25/$D$5/(1+$C$5)-('Цена 120 грн — 33 паллет'!E16+'Цена 120 грн — 33 паллет'!F16+'Цена 120 грн — 33 паллет'!G16+'Цена 120 грн — 33 паллет'!E16*'Цена 120 грн — 33 паллет'!B18*($G$5+$F$5*(1+$G$5)))/('Цена 120 грн — 33 паллет'!C18*'Цена 120 грн — 33 паллет'!D18))/((1+$G$5)*(1+$F$5))),2) -> 0.67 | K25: =J25/0.65-1 -> 0.030769231 | L25: =(($H25/$D$5/(1+$C$5)-('Цена 120 грн — 6 паллет'!E16+'Цена 120 грн — 6 паллет'!F16+'Цена 120 грн — 6 паллет'!G16+'Цена 120 грн — 6 паллет'!E16*'Цена 120 грн — 6 паллет'!B18*($G$5+$F$5*(1+$G$5)))/('Цена 120 грн — 6 паллет'!C18*'Цена 120 грн — 6 паллет'!D18))/((1+$G$5)*(1+$F$5))) -> 0.46264699 | M25: =ROUNDDOWN((($H25/$D$5/(1+$C$5)-('Цена 120 грн — 6 паллет'!E16+'Цена 120 грн — 6 паллет'!F16+'Цена 120 грн — 6 паллет'!G16+'Цена 120 грн — 6 паллет'!E16*'Цена 120 грн — 6 паллет'!B18*($G$5+$F$5*(1+$G$5)))/('Цена 120 грн — 6 паллет'!C18*'Цена 120 грн — 6 паллет'!D18))/((1+$G$5)*(1+$F$5))),2) -> 0.46 | N25: =M25/0.65-1 -> -0.29230769
A27: Как читать: жёлтые ячейки (бонус, маржа, доп. расходы) можно менять — запросы пересчитаются. Полка и параметры партии берутся из вкладок «Цена 120 грн».
A28: Допущения: бонус и маржа считаются от цены партнёру (с НДС) — как в основной модели; доп. расходы добавляются к СС уже после финансирования. Текущая закупка SIAS: €0,65 (4 SKU) / €0,75 (2 SKU).
A29: Что показывать SIAS — решение за вами. Показанные маржа, бонус и доп. расходы должны соответствовать реальной структуре цены: SIAS может запросить подтверждение.
