Workbook

Sheet Model 6 pallets
B1: Ramen. Partner price and shelf price — 6 pallets
B2: Delivery scenario | D2: 6 pallets | E2: Ready-made landed cost from Self-Cost_Sias: AJ6:AJ11. Cost composition preserved.
B3: Rate, UAH/EUR | D3: 51.2 | E3: Rate 51.20 UAH/EUR — from Self-Cost_Sias.
B4: Chain bonus, % | D4: 0.35 | E4: ="Chain bonus "&ROUND(D4*100,0)&"%; shelf = partner price × "&D6&"." -> Chain bonus 35%; shelf = partner price × 1.4.
B5: Target margin, % | D5: 0.2 | E5: =ROUND(D5*100,0)&"% = (partner price − landed cost − bonus) / full partner price." -> 20% = (partner price − landed cost − bonus) / full partner price.
B6: Chain markup (x) | D6: 1.4 | E6: Profit after bonus = partner price − landed cost − chain bonus.
B7: Partner price | D7: incl. VAT | E7: VAT as in the example: landed cost kept in full; the price already includes VAT. No multiplication by 1.20.
B8: Share of price for landed cost | D8: =IF(AND(COUNT(D3:D6)=4,D3>0,D4>=0,D5>=0,D4+D5<1,D6>0),1-D4-D5,NA()) -> 0.45 | E8: ="100% − bonus − margin. Current terms: 100% − "&ROUND(D4*100,0)&"% − "&ROUND(D5*100,0)&"% = "&ROUND(D8*100,0)&"%." -> 100% − bonus − margin. Current terms: 100% − 35% − 20% = 45%.
A9: PRODUCT | E9: LANDED COST | G9: PARTNER PRICE AND PROFIT | K9: SHELF | L9: MODEL: ZERO MARGIN | N9: PROFIT PER PACK | P9: 0.3 | U9: 0.25 | Z9: 0.2 | AE9: 0.15
A10: № | B10: Group | C10: Item | D10: Weight, g | E10: Landed cost, EUR/pack | F10: 1. Landed cost, UAH/pack | G10: 2. Partner price incl. VAT | H10: 3. Chain bonus, UAH | I10: 4. Profit after bonus, UAH | J10: 5. Margin per example | K10: 6. Shelf price incl. VAT, UAH | L10: Min. partner price | M10: Min. shelf price | N10: Gross profit per example, before bonus, UAH/pack | O10: Profit after bonus per example, UAH/pack | P10: Partner price incl. VAT, UAH | Q10: Chain bonus, UAH | R10: Profit after bonus, UAH | S10: Margin check | T10: Shelf price incl. VAT, UAH | U10: Partner price incl. VAT, UAH | V10: Chain bonus, UAH | W10: Profit after bonus, UAH | X10: Margin check | Y10: Shelf price incl. VAT, UAH | Z10: Partner price incl. VAT, UAH | AA10: Chain bonus, UAH | AB10: Profit after bonus, UAH | AC10: Margin check | AD10: Shelf price incl. VAT, UAH | AE10: Partner price incl. VAT, UAH | AF10: Chain bonus, UAH | AG10: Profit after bonus, UAH | AH10: Margin check | AI10: Shelf price incl. VAT, UAH
A11: 1 | B11: SIAS — pack ramen | C11: Gouda Cheese 123 g | D11: 123 | E11: 1.3085156 | F11: =IF(AND(ISNUMBER(E11),ISNUMBER($D$8)),E11*$D$3,NA()) -> 66.996 | G11: =F11/$D$8 -> 148.88 | H11: =G11*$D$4 -> 52.108 | I11: =G11-F11-H11 -> 29.776 | J11: =I11/G11 -> 0.2 | K11: =G11*$D$6 -> 208.432 | L11: =F11/(1-$D$4) -> 103.07077 | M11: =L11*$D$6 -> 144.29908 | N11: =G11-F11 -> 81.884 | O11: =N11-H11 -> 29.776 | P11: =$F11/(1-$D$4-$P$9) -> 191.41714 | Q11: =P11*$D$4 -> 66.996 | R11: =P11-$F11-Q11 -> 57.425143 | S11: =R11/P11 -> 0.3 | T11: =P11*$D$6 -> 267.984 | U11: =$F11/(1-$D$4-$U$9) -> 167.49 | V11: =U11*$D$4 -> 58.6215 | W11: =U11-$F11-V11 -> 41.8725 | X11: =W11/U11 -> 0.25 | Y11: =U11*$D$6 -> 234.486 | Z11: =$F11/(1-$D$4-$Z$9) -> 148.88 | AA11: =Z11*$D$4 -> 52.108 | AB11: =Z11-$F11-AA11 -> 29.776 | AC11: =AB11/Z11 -> 0.2 | AD11: =Z11*$D$6 -> 208.432 | AE11: =$F11/(1-$D$4-$AE$9) -> 133.992 | AF11: =AE11*$D$4 -> 46.8972 | AG11: =AE11-$F11-AF11 -> 20.0988 | AH11: =AG11/AE11 -> 0.15 | AI11: =AE11*$D$6 -> 187.5888
A12: 2 | B12: SIAS — pack ramen | C12: Carbonara Spicy 131 g | D12: 131 | E12: 1.3085156 | F12: =IF(AND(ISNUMBER(E12),ISNUMBER($D$8)),E12*$D$3,NA()) -> 66.996 | G12: =F12/$D$8 -> 148.88 | H12: =G12*$D$4 -> 52.108 | I12: =G12-F12-H12 -> 29.776 | J12: =I12/G12 -> 0.2 | K12: =G12*$D$6 -> 208.432 | L12: =F12/(1-$D$4) -> 103.07077 | M12: =L12*$D$6 -> 144.29908 | N12: =G12-F12 -> 81.884 | O12: =N12-H12 -> 29.776 | P12: =$F12/(1-$D$4-$P$9) -> 191.41714 | Q12: =P12*$D$4 -> 66.996 | R12: =P12-$F12-Q12 -> 57.425143 | S12: =R12/P12 -> 0.3 | T12: =P12*$D$6 -> 267.984 | U12: =$F12/(1-$D$4-$U$9) -> 167.49 | V12: =U12*$D$4 -> 58.6215 | W12: =U12-$F12-V12 -> 41.8725 | X12: =W12/U12 -> 0.25 | Y12: =U12*$D$6 -> 234.486 | Z12: =$F12/(1-$D$4-$Z$9) -> 148.88 | AA12: =Z12*$D$4 -> 52.108 | AB12: =Z12-$F12-AA12 -> 29.776 | AC12: =AB12/Z12 -> 0.2 | AD12: =Z12*$D$6 -> 208.432 | AE12: =$F12/(1-$D$4-$AE$9) -> 133.992 | AF12: =AE12*$D$4 -> 46.8972 | AG12: =AE12-$F12-AF12 -> 20.0988 | AH12: =AG12/AE12 -> 0.15 | AI12: =AE12*$D$6 -> 187.5888
A13: 3 | B13: SIAS — pack ramen | C13: Vegetable Flavor 113 g | D13: 113 | E13: 1.1340469 | F13: =IF(AND(ISNUMBER(E13),ISNUMBER($D$8)),E13*$D$3,NA()) -> 58.0632 | G13: =F13/$D$8 -> 129.02933 | H13: =G13*$D$4 -> 45.160267 | I13: =G13-F13-H13 -> 25.805867 | J13: =I13/G13 -> 0.2 | K13: =G13*$D$6 -> 180.64107 | L13: =F13/(1-$D$4) -> 89.328 | M13: =L13*$D$6 -> 125.0592 | N13: =G13-F13 -> 70.966133 | O13: =N13-H13 -> 25.805867 | P13: =$F13/(1-$D$4-$P$9) -> 165.89486 | Q13: =P13*$D$4 -> 58.0632 | R13: =P13-$F13-Q13 -> 49.768457 | S13: =R13/P13 -> 0.3 | T13: =P13*$D$6 -> 232.2528 | U13: =$F13/(1-$D$4-$U$9) -> 145.158 | V13: =U13*$D$4 -> 50.8053 | W13: =U13-$F13-V13 -> 36.2895 | X13: =W13/U13 -> 0.25 | Y13: =U13*$D$6 -> 203.2212 | Z13: =$F13/(1-$D$4-$Z$9) -> 129.02933 | AA13: =Z13*$D$4 -> 45.160267 | AB13: =Z13-$F13-AA13 -> 25.805867 | AC13: =AB13/Z13 -> 0.2 | AD13: =Z13*$D$6 -> 180.64107 | AE13: =$F13/(1-$D$4-$AE$9) -> 116.1264 | AF13: =AE13*$D$4 -> 40.64424 | AG13: =AE13-$F13-AF13 -> 17.41896 | AH13: =AG13/AE13 -> 0.15 | AI13: =AE13*$D$6 -> 162.57696
A14: 4 | B14: SIAS — pack ramen | C14: Spicy Flavor 112.5 g | D14: 112.5 | E14: 1.1340469 | F14: =IF(AND(ISNUMBER(E14),ISNUMBER($D$8)),E14*$D$3,NA()) -> 58.0632 | G14: =F14/$D$8 -> 129.02933 | H14: =G14*$D$4 -> 45.160267 | I14: =G14-F14-H14 -> 25.805867 | J14: =I14/G14 -> 0.2 | K14: =G14*$D$6 -> 180.64107 | L14: =F14/(1-$D$4) -> 89.328 | M14: =L14*$D$6 -> 125.0592 | N14: =G14-F14 -> 70.966133 | O14: =N14-H14 -> 25.805867 | P14: =$F14/(1-$D$4-$P$9) -> 165.89486 | Q14: =P14*$D$4 -> 58.0632 | R14: =P14-$F14-Q14 -> 49.768457 | S14: =R14/P14 -> 0.3 | T14: =P14*$D$6 -> 232.2528 | U14: =$F14/(1-$D$4-$U$9) -> 145.158 | V14: =U14*$D$4 -> 50.8053 | W14: =U14-$F14-V14 -> 36.2895 | X14: =W14/U14 -> 0.25 | Y14: =U14*$D$6 -> 203.2212 | Z14: =$F14/(1-$D$4-$Z$9) -> 129.02933 | AA14: =Z14*$D$4 -> 45.160267 | AB14: =Z14-$F14-AA14 -> 25.805867 | AC14: =AB14/Z14 -> 0.2 | AD14: =Z14*$D$6 -> 180.64107 | AE14: =$F14/(1-$D$4-$AE$9) -> 116.1264 | AF14: =AE14*$D$4 -> 40.64424 | AG14: =AE14-$F14-AF14 -> 17.41896 | AH14: =AG14/AE14 -> 0.15 | AI14: =AE14*$D$6 -> 162.57696
A15: 5 | B15: SIAS — pack ramen | C15: Beef Flavor 113 g | D15: 113 | E15: 1.1340469 | F15: =IF(AND(ISNUMBER(E15),ISNUMBER($D$8)),E15*$D$3,NA()) -> 58.0632 | G15: =F15/$D$8 -> 129.02933 | H15: =G15*$D$4 -> 45.160267 | I15: =G15-F15-H15 -> 25.805867 | J15: =I15/G15 -> 0.2 | K15: =G15*$D$6 -> 180.64107 | L15: =F15/(1-$D$4) -> 89.328 | M15: =L15*$D$6 -> 125.0592 | N15: =G15-F15 -> 70.966133 | O15: =N15-H15 -> 25.805867 | P15: =$F15/(1-$D$4-$P$9) -> 165.89486 | Q15: =P15*$D$4 -> 58.0632 | R15: =P15-$F15-Q15 -> 49.768457 | S15: =R15/P15 -> 0.3 | T15: =P15*$D$6 -> 232.2528 | U15: =$F15/(1-$D$4-$U$9) -> 145.158 | V15: =U15*$D$4 -> 50.8053 | W15: =U15-$F15-V15 -> 36.2895 | X15: =W15/U15 -> 0.25 | Y15: =U15*$D$6 -> 203.2212 | Z15: =$F15/(1-$D$4-$Z$9) -> 129.02933 | AA15: =Z15*$D$4 -> 45.160267 | AB15: =Z15-$F15-AA15 -> 25.805867 | AC15: =AB15/Z15 -> 0.2 | AD15: =Z15*$D$6 -> 180.64107 | AE15: =$F15/(1-$D$4-$AE$9) -> 116.1264 | AF15: =AE15*$D$4 -> 40.64424 | AG15: =AE15-$F15-AF15 -> 17.41896 | AH15: =AG15/AE15 -> 0.15 | AI15: =AE15*$D$6 -> 162.57696
A16: 6 | B16: SIAS — pack ramen | C16: Chicken Flavor 113 g | D16: 113 | E16: 1.1340469 | F16: =IF(AND(ISNUMBER(E16),ISNUMBER($D$8)),E16*$D$3,NA()) -> 58.0632 | G16: =F16/$D$8 -> 129.02933 | H16: =G16*$D$4 -> 45.160267 | I16: =G16-F16-H16 -> 25.805867 | J16: =I16/G16 -> 0.2 | K16: =G16*$D$6 -> 180.64107 | L16: =F16/(1-$D$4) -> 89.328 | M16: =L16*$D$6 -> 125.0592 | N16: =G16-F16 -> 70.966133 | O16: =N16-H16 -> 25.805867 | P16: =$F16/(1-$D$4-$P$9) -> 165.89486 | Q16: =P16*$D$4 -> 58.0632 | R16: =P16-$F16-Q16 -> 49.768457 | S16: =R16/P16 -> 0.3 | T16: =P16*$D$6 -> 232.2528 | U16: =$F16/(1-$D$4-$U$9) -> 145.158 | V16: =U16*$D$4 -> 50.8053 | W16: =U16-$F16-V16 -> 36.2895 | X16: =W16/U16 -> 0.25 | Y16: =U16*$D$6 -> 203.2212 | Z16: =$F16/(1-$D$4-$Z$9) -> 129.02933 | AA16: =Z16*$D$4 -> 45.160267 | AB16: =Z16-$F16-AA16 -> 25.805867 | AC16: =AB16/Z16 -> 0.2 | AD16: =Z16*$D$6 -> 180.64107 | AE16: =$F16/(1-$D$4-$AE$9) -> 116.1264 | AF16: =AE16*$D$4 -> 40.64424 | AG16: =AE16-$F16-AF16 -> 17.41896 | AH16: =AG16/AE16 -> 0.15 | AI16: =AE16*$D$6 -> 162.57696
B19: Each step of price formation — per your example
A21: № | B21: What we calculate | D21: Action | F21: =C11 -> Gouda Cheese 123 g | G21: =C12 -> Carbonara Spicy 131 g | H21: =C13 -> Vegetable Flavor 113 g | I21: =C14 -> Spicy Flavor 112.5 g | J21: =C15 -> Beef Flavor 113 g | K21: =C16 -> Chicken Flavor 113 g
A22: 1 | B22: Landed cost in Ukraine, EUR/pack | D22: From Self-Cost | F22: =E11 -> 1.3085156 | G22: =E12 -> 1.3085156 | H22: =E13 -> 1.1340469 | I22: =E14 -> 1.1340469 | J22: =E15 -> 1.1340469 | K22: =E16 -> 1.1340469
A23: 2 | B23: Rate, UAH/EUR | D23: Input in D3 | F23: =$D$3 -> 51.2 | G23: =$D$3 -> 51.2 | H23: =$D$3 -> 51.2 | I23: =$D$3 -> 51.2 | J23: =$D$3 -> 51.2 | K23: =$D$3 -> 51.2
A24: 3 | B24: Landed cost in Ukraine, UAH/pack | D24: Step 1 × step 2 | F24: =F11 -> 66.996 | G24: =F12 -> 66.996 | H24: =F13 -> 58.0632 | I24: =F14 -> 58.0632 | J24: =F15 -> 58.0632 | K24: =F16 -> 58.0632
A25: 4 | B25: Full partner price, % | D25: Base for all percentages | F25: 1 | G25: 1 | H25: 1 | I25: 1 | J25: 1 | K25: 1
A26: 5 | B26: Chain bonus, % | D26: Input in D4 | F26: =$D$4 -> 0.35 | G26: =$D$4 -> 0.35 | H26: =$D$4 -> 0.35 | I26: =$D$4 -> 0.35 | J26: =$D$4 -> 0.35 | K26: =$D$4 -> 0.35
A27: 6 | B27: Share of price after bonus, % | D27: Step 4 − step 5 | F27: =1-$D$4 -> 0.65 | G27: =1-$D$4 -> 0.65 | H27: =1-$D$4 -> 0.65 | I27: =1-$D$4 -> 0.65 | J27: =1-$D$4 -> 0.65 | K27: =1-$D$4 -> 0.65
A28: 7 | B28: Our target margin, % | D28: Input in D5 | F28: =$D$5 -> 0.2 | G28: =$D$5 -> 0.2 | H28: =$D$5 -> 0.2 | I28: =$D$5 -> 0.2 | J28: =$D$5 -> 0.2 | K28: =$D$5 -> 0.2
A29: 8 | B29: Share of price for landed cost, % | D29: Step 6 − step 7 | F29: =$D$8 -> 0.45 | G29: =$D$8 -> 0.45 | H29: =$D$8 -> 0.45 | I29: =$D$8 -> 0.45 | J29: =$D$8 -> 0.45 | K29: =$D$8 -> 0.45
A30: 9 | B30: Partner price incl. VAT, UAH/pack | D30: Step 3 ÷ step 8 | F30: =G11 -> 148.88 | G30: =G12 -> 148.88 | H30: =G13 -> 129.02933 | I30: =G14 -> 129.02933 | J30: =G15 -> 129.02933 | K30: =G16 -> 129.02933
A31: 10 | B31: Gross profit before bonus, UAH/pack | D31: Step 9 − step 3 | F31: =N11 -> 81.884 | G31: =N12 -> 81.884 | H31: =N13 -> 70.966133 | I31: =N14 -> 70.966133 | J31: =N15 -> 70.966133 | K31: =N16 -> 70.966133
A32: 11 | B32: Chain bonus, UAH/pack | D32: Step 9 × step 5 | F32: =H11 -> 52.108 | G32: =H12 -> 52.108 | H32: =H13 -> 45.160267 | I32: =H14 -> 45.160267 | J32: =H15 -> 45.160267 | K32: =H16 -> 45.160267
A33: 12 | B33: Left for us after landed cost and bonus, UAH/pack | D33: Step 10 − step 11 | F33: =I11 -> 29.776 | G33: =I12 -> 29.776 | H33: =I13 -> 25.805867 | I33: =I14 -> 25.805867 | J33: =I15 -> 25.805867 | K33: =I16 -> 25.805867
A34: 13 | B34: Check of our margin after bonus, % | D34: Step 12 ÷ step 9 | F34: =J11 -> 0.2 | G34: =J12 -> 0.2 | H34: =J13 -> 0.2 | I34: =J14 -> 0.2 | J34: =J15 -> 0.2 | K34: =J16 -> 0.2
A35: 14 | B35: Retailer markup for shelf, % | D35: Multiplier D6 − 1 | F35: =$D$6-1 -> 0.4 | G35: =$D$6-1 -> 0.4 | H35: =$D$6-1 -> 0.4 | I35: =$D$6-1 -> 0.4 | J35: =$D$6-1 -> 0.4 | K35: =$D$6-1 -> 0.4
A36: 15 | B36: Retailer multiplier | D36: 1 + step 14 | F36: =$D$6 -> 1.4 | G36: =$D$6 -> 1.4 | H36: =$D$6 -> 1.4 | I36: =$D$6 -> 1.4 | J36: =$D$6 -> 1.4 | K36: =$D$6 -> 1.4
A37: 16 | B37: Shelf price incl. VAT, UAH/pack | D37: Step 9 × step 15 | F37: =K11 -> 208.432 | G37: =K12 -> 208.432 | H37: =K13 -> 180.64107 | I37: =K14 -> 180.64107 | J37: =K15 -> 180.64107 | K37: =K16 -> 180.64107
A38: 17 | B38: Partner price at zero profit for us, UAH/pack | D38: Step 3 ÷ step 6 | F38: =L11 -> 103.07077 | G38: =L12 -> 103.07077 | H38: =L13 -> 89.328 | I38: =L14 -> 89.328 | J38: =L15 -> 89.328 | K38: =L16 -> 89.328
A39: 18 | B39: Shelf price at zero profit for us, UAH/pack | D39: Step 17 × step 15 | F39: =M11 -> 144.29908 | G39: =M12 -> 144.29908 | H39: =M13 -> 125.0592 | I39: =M14 -> 125.0592 | J39: =M15 -> 125.0592 | K39: =M16 -> 125.0592

Sheet Model 33 pallets
B1: Ramen. Partner price and shelf price — 33 pallets / Full Truck
B2: Delivery scenario | D2: 33 pallets | E2: Ready-made landed cost from Self-Cost_Sias: AJ30:AJ35. Cost composition preserved.
B3: Rate, UAH/EUR | D3: 51.2 | E3: Rate 51.20 UAH/EUR — from Self-Cost_Sias.
B4: Chain bonus, % | D4: 0.35 | E4: ="Chain bonus "&ROUND(D4*100,0)&"%; shelf = partner price × "&D6&"." -> Chain bonus 35%; shelf = partner price × 1.4.
B5: Target margin, % | D5: 0.2 | E5: =ROUND(D5*100,0)&"% = (partner price − landed cost − bonus) / full partner price." -> 20% = (partner price − landed cost − bonus) / full partner price.
B6: Chain markup (x) | D6: 1.4 | E6: Profit after bonus = partner price − landed cost − chain bonus.
B7: Partner price | D7: incl. VAT | E7: VAT as in the example: landed cost kept in full; the price already includes VAT. No multiplication by 1.20.
B8: Share of price for landed cost | D8: =IF(AND(COUNT(D3:D6)=4,D3>0,D4>=0,D5>=0,D4+D5<1,D6>0),1-D4-D5,NA()) -> 0.45 | E8: ="100% − bonus − margin. Current terms: 100% − "&ROUND(D4*100,0)&"% − "&ROUND(D5*100,0)&"% = "&ROUND(D8*100,0)&"%." -> 100% − bonus − margin. Current terms: 100% − 35% − 20% = 45%.
A9: PRODUCT | E9: LANDED COST | G9: PARTNER PRICE AND PROFIT | K9: SHELF | L9: MODEL: ZERO MARGIN | N9: PROFIT PER PACK | P9: 0.3 | U9: 0.25 | Z9: 0.2 | AE9: 0.15
A10: № | B10: Group | C10: Item | D10: Weight, g | E10: Landed cost, EUR/pack | F10: 1. Landed cost, UAH/pack | G10: 2. Partner price incl. VAT | H10: 3. Chain bonus, UAH | I10: 4. Profit after bonus, UAH | J10: 5. Margin per example | K10: 6. Shelf price incl. VAT, UAH | L10: Min. partner price | M10: Min. shelf price | N10: Gross profit per example, before bonus, UAH/pack | O10: Profit after bonus per example, UAH/pack | P10: Partner price incl. VAT, UAH | Q10: Chain bonus, UAH | R10: Profit after bonus, UAH | S10: Margin check | T10: Shelf price incl. VAT, UAH | U10: Partner price incl. VAT, UAH | V10: Chain bonus, UAH | W10: Profit after bonus, UAH | X10: Margin check | Y10: Shelf price incl. VAT, UAH | Z10: Partner price incl. VAT, UAH | AA10: Chain bonus, UAH | AB10: Profit after bonus, UAH | AC10: Margin check | AD10: Shelf price incl. VAT, UAH | AE10: Partner price incl. VAT, UAH | AF10: Chain bonus, UAH | AG10: Profit after bonus, UAH | AH10: Margin check | AI10: Shelf price incl. VAT, UAH
A11: 1 | B11: SIAS — pack ramen | C11: Gouda Cheese 123 g | D11: 123 | E11: 1.0181312 | F11: =IF(AND(ISNUMBER(E11),ISNUMBER($D$8)),E11*$D$3,NA()) -> 52.128315 | G11: =F11/$D$8 -> 115.8407 | H11: =G11*$D$4 -> 40.544245 | I11: =G11-F11-H11 -> 23.16814 | J11: =I11/G11 -> 0.2 | K11: =G11*$D$6 -> 162.17698 | L11: =F11/(1-$D$4) -> 80.197408 | M11: =L11*$D$6 -> 112.27637 | N11: =G11-F11 -> 63.712385 | O11: =N11-H11 -> 23.16814 | P11: =$F11/(1-$D$4-$P$9) -> 148.93804 | Q11: =P11*$D$4 -> 52.128315 | R11: =P11-$F11-Q11 -> 44.681413 | S11: =R11/P11 -> 0.3 | T11: =P11*$D$6 -> 208.51326 | U11: =$F11/(1-$D$4-$U$9) -> 130.32079 | V11: =U11*$D$4 -> 45.612276 | W11: =U11-$F11-V11 -> 32.580197 | X11: =W11/U11 -> 0.25 | Y11: =U11*$D$6 -> 182.4491 | Z11: =$F11/(1-$D$4-$Z$9) -> 115.8407 | AA11: =Z11*$D$4 -> 40.544245 | AB11: =Z11-$F11-AA11 -> 23.16814 | AC11: =AB11/Z11 -> 0.2 | AD11: =Z11*$D$6 -> 162.17698 | AE11: =$F11/(1-$D$4-$AE$9) -> 104.25663 | AF11: =AE11*$D$4 -> 36.489821 | AG11: =AE11-$F11-AF11 -> 15.638495 | AH11: =AG11/AE11 -> 0.15 | AI11: =AE11*$D$6 -> 145.95928
A12: 2 | B12: SIAS — pack ramen | C12: Carbonara Spicy 131 g | D12: 131 | E12: 1.0181312 | F12: =IF(AND(ISNUMBER(E12),ISNUMBER($D$8)),E12*$D$3,NA()) -> 52.128315 | G12: =F12/$D$8 -> 115.8407 | H12: =G12*$D$4 -> 40.544245 | I12: =G12-F12-H12 -> 23.16814 | J12: =I12/G12 -> 0.2 | K12: =G12*$D$6 -> 162.17698 | L12: =F12/(1-$D$4) -> 80.197408 | M12: =L12*$D$6 -> 112.27637 | N12: =G12-F12 -> 63.712385 | O12: =N12-H12 -> 23.16814 | P12: =$F12/(1-$D$4-$P$9) -> 148.93804 | Q12: =P12*$D$4 -> 52.128315 | R12: =P12-$F12-Q12 -> 44.681413 | S12: =R12/P12 -> 0.3 | T12: =P12*$D$6 -> 208.51326 | U12: =$F12/(1-$D$4-$U$9) -> 130.32079 | V12: =U12*$D$4 -> 45.612276 | W12: =U12-$F12-V12 -> 32.580197 | X12: =W12/U12 -> 0.25 | Y12: =U12*$D$6 -> 182.4491 | Z12: =$F12/(1-$D$4-$Z$9) -> 115.8407 | AA12: =Z12*$D$4 -> 40.544245 | AB12: =Z12-$F12-AA12 -> 23.16814 | AC12: =AB12/Z12 -> 0.2 | AD12: =Z12*$D$6 -> 162.17698 | AE12: =$F12/(1-$D$4-$AE$9) -> 104.25663 | AF12: =AE12*$D$4 -> 36.489821 | AG12: =AE12-$F12-AF12 -> 15.638495 | AH12: =AG12/AE12 -> 0.15 | AI12: =AE12*$D$6 -> 145.95928
A13: 3 | B13: SIAS — pack ramen | C13: Vegetable Flavor 113 g | D13: 113 | E13: 0.88238033 | F13: =IF(AND(ISNUMBER(E13),ISNUMBER($D$8)),E13*$D$3,NA()) -> 45.177873 | G13: =F13/$D$8 -> 100.39527 | H13: =G13*$D$4 -> 35.138346 | I13: =G13-F13-H13 -> 20.079055 | J13: =I13/G13 -> 0.2 | K13: =G13*$D$6 -> 140.55338 | L13: =F13/(1-$D$4) -> 69.50442 | M13: =L13*$D$6 -> 97.306188 | N13: =G13-F13 -> 55.2174 | O13: =N13-H13 -> 20.079055 | P13: =$F13/(1-$D$4-$P$9) -> 129.07964 | Q13: =P13*$D$4 -> 45.177873 | R13: =P13-$F13-Q13 -> 38.723891 | S13: =R13/P13 -> 0.3 | T13: =P13*$D$6 -> 180.71149 | U13: =$F13/(1-$D$4-$U$9) -> 112.94468 | V13: =U13*$D$4 -> 39.530639 | W13: =U13-$F13-V13 -> 28.236171 | X13: =W13/U13 -> 0.25 | Y13: =U13*$D$6 -> 158.12256 | Z13: =$F13/(1-$D$4-$Z$9) -> 100.39527 | AA13: =Z13*$D$4 -> 35.138346 | AB13: =Z13-$F13-AA13 -> 20.079055 | AC13: =AB13/Z13 -> 0.2 | AD13: =Z13*$D$6 -> 140.55338 | AE13: =$F13/(1-$D$4-$AE$9) -> 90.355746 | AF13: =AE13*$D$4 -> 31.624511 | AG13: =AE13-$F13-AF13 -> 13.553362 | AH13: =AG13/AE13 -> 0.15 | AI13: =AE13*$D$6 -> 126.49804
A14: 4 | B14: SIAS — pack ramen | C14: Spicy Flavor 112.5 g | D14: 112.5 | E14: 0.88238033 | F14: =IF(AND(ISNUMBER(E14),ISNUMBER($D$8)),E14*$D$3,NA()) -> 45.177873 | G14: =F14/$D$8 -> 100.39527 | H14: =G14*$D$4 -> 35.138346 | I14: =G14-F14-H14 -> 20.079055 | J14: =I14/G14 -> 0.2 | K14: =G14*$D$6 -> 140.55338 | L14: =F14/(1-$D$4) -> 69.50442 | M14: =L14*$D$6 -> 97.306188 | N14: =G14-F14 -> 55.2174 | O14: =N14-H14 -> 20.079055 | P14: =$F14/(1-$D$4-$P$9) -> 129.07964 | Q14: =P14*$D$4 -> 45.177873 | R14: =P14-$F14-Q14 -> 38.723891 | S14: =R14/P14 -> 0.3 | T14: =P14*$D$6 -> 180.71149 | U14: =$F14/(1-$D$4-$U$9) -> 112.94468 | V14: =U14*$D$4 -> 39.530639 | W14: =U14-$F14-V14 -> 28.236171 | X14: =W14/U14 -> 0.25 | Y14: =U14*$D$6 -> 158.12256 | Z14: =$F14/(1-$D$4-$Z$9) -> 100.39527 | AA14: =Z14*$D$4 -> 35.138346 | AB14: =Z14-$F14-AA14 -> 20.079055 | AC14: =AB14/Z14 -> 0.2 | AD14: =Z14*$D$6 -> 140.55338 | AE14: =$F14/(1-$D$4-$AE$9) -> 90.355746 | AF14: =AE14*$D$4 -> 31.624511 | AG14: =AE14-$F14-AF14 -> 13.553362 | AH14: =AG14/AE14 -> 0.15 | AI14: =AE14*$D$6 -> 126.49804
A15: 5 | B15: SIAS — pack ramen | C15: Beef Flavor 113 g | D15: 113 | E15: 0.88238033 | F15: =IF(AND(ISNUMBER(E15),ISNUMBER($D$8)),E15*$D$3,NA()) -> 45.177873 | G15: =F15/$D$8 -> 100.39527 | H15: =G15*$D$4 -> 35.138346 | I15: =G15-F15-H15 -> 20.079055 | J15: =I15/G15 -> 0.2 | K15: =G15*$D$6 -> 140.55338 | L15: =F15/(1-$D$4) -> 69.50442 | M15: =L15*$D$6 -> 97.306188 | N15: =G15-F15 -> 55.2174 | O15: =N15-H15 -> 20.079055 | P15: =$F15/(1-$D$4-$P$9) -> 129.07964 | Q15: =P15*$D$4 -> 45.177873 | R15: =P15-$F15-Q15 -> 38.723891 | S15: =R15/P15 -> 0.3 | T15: =P15*$D$6 -> 180.71149 | U15: =$F15/(1-$D$4-$U$9) -> 112.94468 | V15: =U15*$D$4 -> 39.530639 | W15: =U15-$F15-V15 -> 28.236171 | X15: =W15/U15 -> 0.25 | Y15: =U15*$D$6 -> 158.12256 | Z15: =$F15/(1-$D$4-$Z$9) -> 100.39527 | AA15: =Z15*$D$4 -> 35.138346 | AB15: =Z15-$F15-AA15 -> 20.079055 | AC15: =AB15/Z15 -> 0.2 | AD15: =Z15*$D$6 -> 140.55338 | AE15: =$F15/(1-$D$4-$AE$9) -> 90.355746 | AF15: =AE15*$D$4 -> 31.624511 | AG15: =AE15-$F15-AF15 -> 13.553362 | AH15: =AG15/AE15 -> 0.15 | AI15: =AE15*$D$6 -> 126.49804
A16: 6 | B16: SIAS — pack ramen | C16: Chicken Flavor 113 g | D16: 113 | E16: 0.88238033 | F16: =IF(AND(ISNUMBER(E16),ISNUMBER($D$8)),E16*$D$3,NA()) -> 45.177873 | G16: =F16/$D$8 -> 100.39527 | H16: =G16*$D$4 -> 35.138346 | I16: =G16-F16-H16 -> 20.079055 | J16: =I16/G16 -> 0.2 | K16: =G16*$D$6 -> 140.55338 | L16: =F16/(1-$D$4) -> 69.50442 | M16: =L16*$D$6 -> 97.306188 | N16: =G16-F16 -> 55.2174 | O16: =N16-H16 -> 20.079055 | P16: =$F16/(1-$D$4-$P$9) -> 129.07964 | Q16: =P16*$D$4 -> 45.177873 | R16: =P16-$F16-Q16 -> 38.723891 | S16: =R16/P16 -> 0.3 | T16: =P16*$D$6 -> 180.71149 | U16: =$F16/(1-$D$4-$U$9) -> 112.94468 | V16: =U16*$D$4 -> 39.530639 | W16: =U16-$F16-V16 -> 28.236171 | X16: =W16/U16 -> 0.25 | Y16: =U16*$D$6 -> 158.12256 | Z16: =$F16/(1-$D$4-$Z$9) -> 100.39527 | AA16: =Z16*$D$4 -> 35.138346 | AB16: =Z16-$F16-AA16 -> 20.079055 | AC16: =AB16/Z16 -> 0.2 | AD16: =Z16*$D$6 -> 140.55338 | AE16: =$F16/(1-$D$4-$AE$9) -> 90.355746 | AF16: =AE16*$D$4 -> 31.624511 | AG16: =AE16-$F16-AF16 -> 13.553362 | AH16: =AG16/AE16 -> 0.15 | AI16: =AE16*$D$6 -> 126.49804
B19: Each step of price formation — per your example
A21: № | B21: What we calculate | D21: Action | F21: =C11 -> Gouda Cheese 123 g | G21: =C12 -> Carbonara Spicy 131 g | H21: =C13 -> Vegetable Flavor 113 g | I21: =C14 -> Spicy Flavor 112.5 g | J21: =C15 -> Beef Flavor 113 g | K21: =C16 -> Chicken Flavor 113 g
A22: 1 | B22: Landed cost in Ukraine, EUR/pack | D22: From Self-Cost | F22: =E11 -> 1.0181312 | G22: =E12 -> 1.0181312 | H22: =E13 -> 0.88238033 | I22: =E14 -> 0.88238033 | J22: =E15 -> 0.88238033 | K22: =E16 -> 0.88238033
A23: 2 | B23: Rate, UAH/EUR | D23: Input in D3 | F23: =$D$3 -> 51.2 | G23: =$D$3 -> 51.2 | H23: =$D$3 -> 51.2 | I23: =$D$3 -> 51.2 | J23: =$D$3 -> 51.2 | K23: =$D$3 -> 51.2
A24: 3 | B24: Landed cost in Ukraine, UAH/pack | D24: Step 1 × step 2 | F24: =F11 -> 52.128315 | G24: =F12 -> 52.128315 | H24: =F13 -> 45.177873 | I24: =F14 -> 45.177873 | J24: =F15 -> 45.177873 | K24: =F16 -> 45.177873
A25: 4 | B25: Full partner price, % | D25: Base for all percentages | F25: 1 | G25: 1 | H25: 1 | I25: 1 | J25: 1 | K25: 1
A26: 5 | B26: Chain bonus, % | D26: Input in D4 | F26: =$D$4 -> 0.35 | G26: =$D$4 -> 0.35 | H26: =$D$4 -> 0.35 | I26: =$D$4 -> 0.35 | J26: =$D$4 -> 0.35 | K26: =$D$4 -> 0.35
A27: 6 | B27: Share of price after bonus, % | D27: Step 4 − step 5 | F27: =1-$D$4 -> 0.65 | G27: =1-$D$4 -> 0.65 | H27: =1-$D$4 -> 0.65 | I27: =1-$D$4 -> 0.65 | J27: =1-$D$4 -> 0.65 | K27: =1-$D$4 -> 0.65
A28: 7 | B28: Our target margin, % | D28: Input in D5 | F28: =$D$5 -> 0.2 | G28: =$D$5 -> 0.2 | H28: =$D$5 -> 0.2 | I28: =$D$5 -> 0.2 | J28: =$D$5 -> 0.2 | K28: =$D$5 -> 0.2
A29: 8 | B29: Share of price for landed cost, % | D29: Step 6 − step 7 | F29: =$D$8 -> 0.45 | G29: =$D$8 -> 0.45 | H29: =$D$8 -> 0.45 | I29: =$D$8 -> 0.45 | J29: =$D$8 -> 0.45 | K29: =$D$8 -> 0.45
A30: 9 | B30: Partner price incl. VAT, UAH/pack | D30: Step 3 ÷ step 8 | F30: =G11 -> 115.8407 | G30: =G12 -> 115.8407 | H30: =G13 -> 100.39527 | I30: =G14 -> 100.39527 | J30: =G15 -> 100.39527 | K30: =G16 -> 100.39527
A31: 10 | B31: Gross profit before bonus, UAH/pack | D31: Step 9 − step 3 | F31: =N11 -> 63.712385 | G31: =N12 -> 63.712385 | H31: =N13 -> 55.2174 | I31: =N14 -> 55.2174 | J31: =N15 -> 55.2174 | K31: =N16 -> 55.2174
A32: 11 | B32: Chain bonus, UAH/pack | D32: Step 9 × step 5 | F32: =H11 -> 40.544245 | G32: =H12 -> 40.544245 | H32: =H13 -> 35.138346 | I32: =H14 -> 35.138346 | J32: =H15 -> 35.138346 | K32: =H16 -> 35.138346
A33: 12 | B33: Left for us after landed cost and bonus, UAH/pack | D33: Step 10 − step 11 | F33: =I11 -> 23.16814 | G33: =I12 -> 23.16814 | H33: =I13 -> 20.079055 | I33: =I14 -> 20.079055 | J33: =I15 -> 20.079055 | K33: =I16 -> 20.079055
A34: 13 | B34: Check of our margin after bonus, % | D34: Step 12 ÷ step 9 | F34: =J11 -> 0.2 | G34: =J12 -> 0.2 | H34: =J13 -> 0.2 | I34: =J14 -> 0.2 | J34: =J15 -> 0.2 | K34: =J16 -> 0.2
A35: 14 | B35: Retailer markup for shelf, % | D35: Multiplier D6 − 1 | F35: =$D$6-1 -> 0.4 | G35: =$D$6-1 -> 0.4 | H35: =$D$6-1 -> 0.4 | I35: =$D$6-1 -> 0.4 | J35: =$D$6-1 -> 0.4 | K35: =$D$6-1 -> 0.4
A36: 15 | B36: Retailer multiplier | D36: 1 + step 14 | F36: =$D$6 -> 1.4 | G36: =$D$6 -> 1.4 | H36: =$D$6 -> 1.4 | I36: =$D$6 -> 1.4 | J36: =$D$6 -> 1.4 | K36: =$D$6 -> 1.4
A37: 16 | B37: Shelf price incl. VAT, UAH/pack | D37: Step 9 × step 15 | F37: =K11 -> 162.17698 | G37: =K12 -> 162.17698 | H37: =K13 -> 140.55338 | I37: =K14 -> 140.55338 | J37: =K15 -> 140.55338 | K37: =K16 -> 140.55338
A38: 17 | B38: Partner price at zero profit for us, UAH/pack | D38: Step 3 ÷ step 6 | F38: =L11 -> 80.197408 | G38: =L12 -> 80.197408 | H38: =L13 -> 69.50442 | I38: =L14 -> 69.50442 | J38: =L15 -> 69.50442 | K38: =L16 -> 69.50442
A39: 18 | B39: Shelf price at zero profit for us, UAH/pack | D39: Step 17 × step 15 | F39: =M11 -> 112.27637 | G39: =M12 -> 112.27637 | H39: =M13 -> 97.306188 | I39: =M14 -> 97.306188 | J39: =M15 -> 97.306188 | K39: =M16 -> 97.306188

Sheet Price 120 UAH - 6 pallets
A1: INTERNAL — not for SIAS · real chain bonus shown, landed cost not adjusted · 6 pallets
A2: REQUEST TO SIAS, €/pack | B2: =B20 -> 0.32 | D2: ="now €"&B5&" (4 SKUs) / €"&B7&" (2 SKUs)" -> now €0.65 (4 SKUs) / €0.75 (2 SKUs) | F2: ="reduction −"&ROUND((1-B20/B5)*100,0)&" % / −"&ROUND((1-B20/B7)*100,0)&" %" -> reduction −51 % / −57 % | H2: one price for all 6 SKUs
A3: Scenario | B3: SIAS purchase per pack | C3: ="Landed cost in Ukraine"&CHAR(10)&"product + costs in Ukraine"&IF(G14>0," + "&ROUND(G14,2)&" ₴ bonus compensation","") -> Landed cost in Ukraine product + costs in Ukraine | D3: Partner price cost ÷ (1 − bonus − margin) | E3: ="Chain bonus (shown)"&CHAR(10)&ROUND(D14*100,0)&" % of partner price" -> Chain bonus (shown) 35 % of partner price | F3: ="Our profit"&CHAR(10)&ROUND(C14*100,0)&" % of partner price" -> Our profit 20 % of partner price | G3: Store markup +40 % on partner price | H3: SHELF PRICE incl. VAT partner price × 1.40
A4: BEFORE · Vegetable, Spicy, Beef, Chicken (4 SKUs) | B4: =B5*F14 -> 33.28 | C4: =$B$24*F14+$G$14 -> 58.0632 | D4: =C4/(1-D14-C14) -> 129.02933 | E4: =D4*D14 -> 45.160267 | F4: =D4-C4-E4 -> 25.805867 | G4: =D4*(E14-1) -> 51.611733 | H4: =D4*E14 -> 180.64107
B5: 0.65 | C5: =C4/F14 -> 1.1340469 | D5: =D4/F14 -> 2.5201042 | E5: =E4/F14 -> 0.88203646 | F5: =F4/F14 -> 0.50402083 | G5: =G4/F14 -> 1.0080417 | H5: =H4/F14 -> 3.5281458
A6: BEFORE · Gouda Cheese, Carbonara Spicy (2 SKUs) | B6: =B7*F14 -> 38.4 | C6: =$B$25*F14+$G$14 -> 66.996 | D6: =C6/(1-D14-C14) -> 148.88 | E6: =D6*D14 -> 52.108 | F6: =D6-C6-E6 -> 29.776 | G6: =D6*(E14-1) -> 59.552 | H6: =D6*E14 -> 208.432
B7: 0.75 | C7: =C6/F14 -> 1.3085156 | D7: =D6/F14 -> 2.9078125 | E7: =E6/F14 -> 1.0177344 | F7: =F6/F14 -> 0.5815625 | G7: =G6/F14 -> 1.163125 | H7: =H6/F14 -> 4.0709375
A8: AFTER · SIAS request (all 6 SKUs) | B8: =B9*F14 -> 16.384 | C8: =B22 -> 38.15952 | D8: =C8/(1-D14-C14) -> 84.798933 | E8: =D8*D14 -> 29.679627 | F8: =D8-C8-E8 -> 16.959787 | G8: =D8*(E14-1) -> 33.919573 | H8: =D8*E14 -> 118.71851
B9: =B20 -> 0.32 | C9: =C8/F14 -> 0.74530312 | D9: =D8/F14 -> 1.6562292 | E9: =E8/F14 -> 0.57968021 | F9: =F8/F14 -> 0.33124583 | G9: =G8/F14 -> 0.66249167 | H9: =H8/F14 -> 2.3187208
A10: CHANGE: AFTER − BEFORE (4 SKUs) | B10: =B8-B4 -> -16.896 | C10: =C8-C4 -> -19.90368 | D10: =D8-D4 -> -44.2304 | E10: =E8-E4 -> -15.48064 | F10: =F8-F4 -> -8.84608 | G10: =G8-G4 -> -17.69216 | H10: =H8-H4 -> -61.92256
B11: =B9-B5 -> -0.33 | C11: =C9-C5 -> -0.38874375 | D11: =D9-D5 -> -0.863875 | E11: =E9-E5 -> -0.30235625 | F11: =F9-F5 -> -0.172775 | G11: =G9-G5 -> -0.34555 | H11: =H9-H5 -> -1.209425
A12: INPUTS — yellow cells can be changed, green ones are linked from the sheet "Model 6 pallets"
B13: Shelf price, ₴ | C13: Our margin | D13: Chain bonus (shown) | E13: Shelf multiplier | F13: Rate ₴/€ | G13: Extra cost, ₴/pack (bonus-gap compensation) | H13: Real chain bonus (internal)
A14: Target and model terms | B14: 120 | C14: 0.2 | D14: ='Model 6 pallets'!D4 -> 0.35 | E14: ='Model 6 pallets'!D6 -> 1.4 | F14: ='Model 6 pallets'!D3 -> 51.2 | G14: =ROUND(B14/E14*(H14-D14),2) -> 0 | H14: 0.35
B15: Import VAT | C15: Financing | D15: Customs duty | E15: Batch freight, € | F15: Broker, € | G15: Other, €
B16: 0.2 | C16: 0.025 | D16: 0 | E16: 2600 | F16: 288 | G16: 42
B17: Freight share in customs value | C17: Pallets in batch | D17: Packs per pallet
B18: 0.7 | C18: 6 | D18: 1600
A20: Request to SIAS, €/pack (rounded down to the euro cent) | B20: =ROUNDDOWN(((B14/E14*(1-D14-C14)-G14)/F14/(1+C16)-(E16+F16+G16+E16*B18*(D16+B16*(1+D16)))/(C18*D18))/((1+D16)*(1+B16)),2) -> 0.32
A21: Maximum purchase price before rounding, €/pack | B21: =((B14/E14*(1-D14-C14)-G14)/F14/(1+C16)-(E16+F16+G16+E16*B18*(D16+B16*(1+D16)))/(C18*D18))/((1+D16)*(1+B16)) -> 0.32654072
A22: Landed cost in Ukraine at the request (incl. extra cost), ₴/pack | B22: =(B20*F14+(E16+F16+G16)/(C18*D18)*F14+(B20+E16*B18/(C18*D18))*D16*F14+(B20+E16*B18/(C18*D18))*(1+D16)*B16*F14)*(1+C16)+G14 -> 38.15952
A24: Landed cost per Self-Cost, 4 SKUs (Vegetable…), €/pack — without extra cost | B24: ='Model 6 pallets'!E13 -> 1.1340469
A25: Landed cost per Self-Cost, 2 SKUs (Gouda, Carbonara), €/pack — without extra cost | B25: ='Model 6 pallets'!E11 -> 1.3085156

Sheet Price 120 UAH - 33 pallets
A1: INTERNAL — not for SIAS · real chain bonus shown, landed cost not adjusted · 33 pallets (Full Truck)
A2: REQUEST TO SIAS, €/pack | B2: =B19 -> 0.54 | D2: ="now €"&B5&" (4 SKUs) / €"&B7&" (2 SKUs)" -> now €0.65 (4 SKUs) / €0.75 (2 SKUs) | F2: ="reduction −"&ROUND((1-B19/B5)*100,0)&" % / −"&ROUND((1-B19/B7)*100,0)&" %" -> reduction −17 % / −28 % | H2: one price for all 6 SKUs
A3: Scenario | B3: SIAS purchase per pack | C3: ="Landed cost in Ukraine"&CHAR(10)&"product + costs in Ukraine"&IF(G14>0," + "&ROUND(G14,2)&" ₴ bonus compensation","") -> Landed cost in Ukraine product + costs in Ukraine | D3: Partner price cost ÷ (1 − bonus − margin) | E3: ="Chain bonus (shown)"&CHAR(10)&ROUND(D14*100,0)&" % of partner price" -> Chain bonus (shown) 35 % of partner price | F3: ="Our profit"&CHAR(10)&ROUND(C14*100,0)&" % of partner price" -> Our profit 20 % of partner price | G3: Store markup +40 % on partner price | H3: SHELF PRICE incl. VAT partner price × 1.40
A4: BEFORE · Vegetable, Spicy, Beef, Chicken (4 SKUs) | B4: =B5*F14 -> 33.28 | C4: =$B$23*F14+$G$14 -> 45.177873 | D4: =C4/(1-D14-C14) -> 100.39527 | E4: =D4*D14 -> 35.138346 | F4: =D4-C4-E4 -> 20.079055 | G4: =D4*(E14-1) -> 40.158109 | H4: =D4*E14 -> 140.55338
B5: 0.65 | C5: =C4/F14 -> 0.88238033 | D5: =D4/F14 -> 1.9608452 | E5: =E4/F14 -> 0.68629582 | F5: =F4/F14 -> 0.39216904 | G5: =G4/F14 -> 0.78433807 | H5: =H4/F14 -> 2.7451833
A6: BEFORE · Gouda Cheese, Carbonara Spicy (2 SKUs) | B6: =B7*F14 -> 38.4 | C6: =$B$24*F14+$G$14 -> 52.128315 | D6: =C6/(1-D14-C14) -> 115.8407 | E6: =D6*D14 -> 40.544245 | F6: =D6-C6-E6 -> 23.16814 | G6: =D6*(E14-1) -> 46.33628 | H6: =D6*E14 -> 162.17698
B7: 0.75 | C7: =C6/F14 -> 1.0181312 | D7: =D6/F14 -> 2.2625137 | E7: =E6/F14 -> 0.79187979 | F7: =F6/F14 -> 0.45250274 | G7: =G6/F14 -> 0.90500547 | H7: =H6/F14 -> 3.1675191
A8: AFTER · SIAS request (all 6 SKUs) | B8: =B9*F14 -> 27.648 | C8: =B21 -> 38.527476 | D8: =C8/(1-D14-C14) -> 85.616614 | E8: =D8*D14 -> 29.965815 | F8: =D8-C8-E8 -> 17.123323 | G8: =D8*(E14-1) -> 34.246646 | H8: =D8*E14 -> 119.86326
B9: =B19 -> 0.54 | C9: =C8/F14 -> 0.75248977 | D9: =D8/F14 -> 1.6721995 | E9: =E8/F14 -> 0.58526982 | F9: =F8/F14 -> 0.3344399 | G9: =G8/F14 -> 0.6688798 | H9: =H8/F14 -> 2.3410793
A10: CHANGE: AFTER − BEFORE (4 SKUs) | B10: =B8-B4 -> -5.632 | C10: =C8-C4 -> -6.6503967 | D10: =D8-D4 -> -14.778659 | E10: =E8-E4 -> -5.1725308 | F10: =F8-F4 -> -2.9557319 | G10: =G8-G4 -> -5.9114638 | H10: =H8-H4 -> -20.690123
B11: =B9-B5 -> -0.11 | C11: =C9-C5 -> -0.12989056 | D11: =D9-D5 -> -0.28864569 | E11: =E9-E5 -> -0.10102599 | F11: =F9-F5 -> -0.057729138 | G11: =G9-G5 -> -0.11545828 | H11: =H9-H5 -> -0.40410397
A12: INPUTS — yellow cells can be changed, green ones are linked from the sheet "Model 33 pallets"
B13: Shelf price, ₴ | C13: Our margin | D13: Chain bonus (shown) | E13: Shelf multiplier | F13: Rate ₴/€ | G13: Extra cost, ₴/pack (bonus-gap compensation) | H13: Real chain bonus (internal)
A14: Target and model terms | B14: 120 | C14: 0.2 | D14: ='Model 33 pallets'!D4 -> 0.35 | E14: ='Model 33 pallets'!D6 -> 1.4 | F14: ='Model 33 pallets'!D3 -> 51.2 | G14: =ROUND(B14/E14*(H14-D14),2) -> 0 | H14: 0.35
B15: Import VAT | C15: Financing | D15: Customs duty | E15: Batch freight, € | F15: Broker, € | G15: Other, €
B16: 0.2 | C16: 0.025 | D16: 0 | E16: 3700 | F16: 288 | G16: 42
B17: Freight share in customs value | C17: Pallets in batch | D17: Packs per pallet
B18: 0.7 | C18: 33 | D18: 1600
A19: Request to SIAS, €/pack (rounded down to the euro cent) | B19: =ROUNDDOWN(((B14/E14*(1-D14-C14)-G14)/F14/(1+C16)-(E16+F16+G16+E16*B18*(D16+B16*(1+D16)))/(C18*D18))/((1+D16)*(1+B16)),2) -> 0.54
A20: Maximum purchase price before rounding, €/pack | B20: =((B14/E14*(1-D14-C14)-G14)/F14/(1+C16)-(E16+F16+G16+E16*B18*(D16+B16*(1+D16)))/(C18*D18))/((1+D16)*(1+B16)) -> 0.54069792
A21: Landed cost in Ukraine at the request (incl. extra cost), ₴/pack | B21: =(B19*F14+(E16+F16+G16)/(C18*D18)*F14+(B19+E16*B18/(C18*D18))*D16*F14+(B19+E16*B18/(C18*D18))*(1+D16)*B16*F14)*(1+C16)+G14 -> 38.527476
A23: Landed cost per Self-Cost, 4 SKUs (Vegetable…), €/pack — without extra cost | B23: ='Model 33 pallets'!E13 -> 0.88238033
A24: Landed cost per Self-Cost, 2 SKUs (Gouda, Carbonara), €/pack — without extra cost | B24: ='Model 33 pallets'!E11 -> 1.0181312

Sheet Scenarios
A1: INTERNAL FILE — for us only · Price-structure scenarios: the request to SIAS at a different margin, chain bonus and extra cost
A2: ="The request depends on the sum of bonus + margin and on extra cost: allowed landed cost = partner price × (1 − bonus − margin) − extra cost. 1 p.p. of margin or bonus = "&ROUND(E5/100,2)&" ₴ per pack = €"&ROUND(E5/100/D5/(1+C5)/((1+G5)*(1+F5)),4)&" on the request." -> The request depends on the sum of bonus + margin and on extra cost: allowed landed cost = partner price × (1 − bonus − margin) − extra cost. 1 p.p. of margin or bonus = 0.86 ₴ per pack = €0.0136 on the request.
A4: Shelf price, ₴ | B4: Shelf multiplier | C4: Financing | D4: Rate ₴/€ | E4: Partner price at shelf price, ₴ | F4: Import VAT | G4: Customs duty
A5: ='Price 120 UAH - 33 pallets'!B14 -> 120 | B5: ='Price 120 UAH - 33 pallets'!E14 -> 1.4 | C5: ='Price 120 UAH - 33 pallets'!C16 -> 0.025 | D5: ='Price 120 UAH - 33 pallets'!F14 -> 51.2 | E5: =A5/B5 -> 85.714286 | F5: ='Price 120 UAH - 33 pallets'!B16 -> 0.2 | G5: ='Price 120 UAH - 33 pallets'!D16 -> 0
A7: Scenario | B7: Chain bonus | C7: Margin shown | D7: Extra cost in landed cost, ₴/pack | E7: Chain bonus, ₴ | F7: Our profit, ₴ | G7: Landed-cost budget (product + costs + extra), ₴ | H7: Product landed cost in Ukraine, ₴ | I7: 33 pallets: max purchase, € | J7: 33 pallets: REQUEST TO SIAS, € | K7: vs current €0.65, % | L7: 6 pallets: max purchase, € | M7: 6 pallets: REQUEST TO SIAS, € | N7: vs current €0.65, %
A8: BASE · previous version of the model
A9: Previous: bonus 25 % + margin 30 % | B9: 0.25 | C9: 0.3 | D9: 0 | E9: =$E$5*B9 -> 21.428571 | F9: =$E$5*C9 -> 25.714286 | G9: =$E$5-E9-F9 -> 38.571429 | H9: =G9-D9 -> 38.571429 | I9: =(($H9/$D$5/(1+$C$5)-('Price 120 UAH - 33 pallets'!E16+'Price 120 UAH - 33 pallets'!F16+'Price 120 UAH - 33 pallets'!G16+'Price 120 UAH - 33 pallets'!E16*'Price 120 UAH - 33 pallets'!B18*($G$5+$F$5*(1+$G$5)))/('Price 120 UAH - 33 pallets'!C18*'Price 120 UAH - 33 pallets'!D18))/((1+$G$5)*(1+$F$5))) -> 0.54069792 | J9: =ROUNDDOWN((($H9/$D$5/(1+$C$5)-('Price 120 UAH - 33 pallets'!E16+'Price 120 UAH - 33 pallets'!F16+'Price 120 UAH - 33 pallets'!G16+'Price 120 UAH - 33 pallets'!E16*'Price 120 UAH - 33 pallets'!B18*($G$5+$F$5*(1+$G$5)))/('Price 120 UAH - 33 pallets'!C18*'Price 120 UAH - 33 pallets'!D18))/((1+$G$5)*(1+$F$5))),2) -> 0.54 | K9: =J9/0.65-1 -> -0.16923077 | L9: =(($H9/$D$5/(1+$C$5)-('Price 120 UAH - 6 pallets'!E16+'Price 120 UAH - 6 pallets'!F16+'Price 120 UAH - 6 pallets'!G16+'Price 120 UAH - 6 pallets'!E16*'Price 120 UAH - 6 pallets'!B18*($G$5+$F$5*(1+$G$5)))/('Price 120 UAH - 6 pallets'!C18*'Price 120 UAH - 6 pallets'!D18))/((1+$G$5)*(1+$F$5))) -> 0.32654072 | M9: =ROUNDDOWN((($H9/$D$5/(1+$C$5)-('Price 120 UAH - 6 pallets'!E16+'Price 120 UAH - 6 pallets'!F16+'Price 120 UAH - 6 pallets'!G16+'Price 120 UAH - 6 pallets'!E16*'Price 120 UAH - 6 pallets'!B18*($G$5+$F$5*(1+$G$5)))/('Price 120 UAH - 6 pallets'!C18*'Price 120 UAH - 6 pallets'!D18))/((1+$G$5)*(1+$F$5))),2) -> 0.32 | N9: =M9/0.65-1 -> -0.50769231
A10: SAME REQUEST PRICE, different structure (the sum of bonus + margin + extra cost does not change)
A11: ★ Chain bonus 35 % + margin 20 % (no extra cost) | B11: 0.35 | C11: 0.2 | D11: 0 | E11: =$E$5*B11 -> 30 | F11: =$E$5*C11 -> 17.142857 | G11: =$E$5-E11-F11 -> 38.571429 | H11: =G11-D11 -> 38.571429 | I11: =(($H11/$D$5/(1+$C$5)-('Price 120 UAH - 33 pallets'!E16+'Price 120 UAH - 33 pallets'!F16+'Price 120 UAH - 33 pallets'!G16+'Price 120 UAH - 33 pallets'!E16*'Price 120 UAH - 33 pallets'!B18*($G$5+$F$5*(1+$G$5)))/('Price 120 UAH - 33 pallets'!C18*'Price 120 UAH - 33 pallets'!D18))/((1+$G$5)*(1+$F$5))) -> 0.54069792 | J11: =ROUNDDOWN((($H11/$D$5/(1+$C$5)-('Price 120 UAH - 33 pallets'!E16+'Price 120 UAH - 33 pallets'!F16+'Price 120 UAH - 33 pallets'!G16+'Price 120 UAH - 33 pallets'!E16*'Price 120 UAH - 33 pallets'!B18*($G$5+$F$5*(1+$G$5)))/('Price 120 UAH - 33 pallets'!C18*'Price 120 UAH - 33 pallets'!D18))/((1+$G$5)*(1+$F$5))),2) -> 0.54 | K11: =J11/0.65-1 -> -0.16923077 | L11: =(($H11/$D$5/(1+$C$5)-('Price 120 UAH - 6 pallets'!E16+'Price 120 UAH - 6 pallets'!F16+'Price 120 UAH - 6 pallets'!G16+'Price 120 UAH - 6 pallets'!E16*'Price 120 UAH - 6 pallets'!B18*($G$5+$F$5*(1+$G$5)))/('Price 120 UAH - 6 pallets'!C18*'Price 120 UAH - 6 pallets'!D18))/((1+$G$5)*(1+$F$5))) -> 0.32654072 | M11: =ROUNDDOWN((($H11/$D$5/(1+$C$5)-('Price 120 UAH - 6 pallets'!E16+'Price 120 UAH - 6 pallets'!F16+'Price 120 UAH - 6 pallets'!G16+'Price 120 UAH - 6 pallets'!E16*'Price 120 UAH - 6 pallets'!B18*($G$5+$F$5*(1+$G$5)))/('Price 120 UAH - 6 pallets'!C18*'Price 120 UAH - 6 pallets'!D18))/((1+$G$5)*(1+$F$5))),2) -> 0.32 | N11: =M11/0.65-1 -> -0.50769231
A12: Bonus 30 % + margin 25 % | B12: 0.3 | C12: 0.25 | D12: 0 | E12: =$E$5*B12 -> 25.714286 | F12: =$E$5*C12 -> 21.428571 | G12: =$E$5-E12-F12 -> 38.571429 | H12: =G12-D12 -> 38.571429 | I12: =(($H12/$D$5/(1+$C$5)-('Price 120 UAH - 33 pallets'!E16+'Price 120 UAH - 33 pallets'!F16+'Price 120 UAH - 33 pallets'!G16+'Price 120 UAH - 33 pallets'!E16*'Price 120 UAH - 33 pallets'!B18*($G$5+$F$5*(1+$G$5)))/('Price 120 UAH - 33 pallets'!C18*'Price 120 UAH - 33 pallets'!D18))/((1+$G$5)*(1+$F$5))) -> 0.54069792 | J12: =ROUNDDOWN((($H12/$D$5/(1+$C$5)-('Price 120 UAH - 33 pallets'!E16+'Price 120 UAH - 33 pallets'!F16+'Price 120 UAH - 33 pallets'!G16+'Price 120 UAH - 33 pallets'!E16*'Price 120 UAH - 33 pallets'!B18*($G$5+$F$5*(1+$G$5)))/('Price 120 UAH - 33 pallets'!C18*'Price 120 UAH - 33 pallets'!D18))/((1+$G$5)*(1+$F$5))),2) -> 0.54 | K12: =J12/0.65-1 -> -0.16923077 | L12: =(($H12/$D$5/(1+$C$5)-('Price 120 UAH - 6 pallets'!E16+'Price 120 UAH - 6 pallets'!F16+'Price 120 UAH - 6 pallets'!G16+'Price 120 UAH - 6 pallets'!E16*'Price 120 UAH - 6 pallets'!B18*($G$5+$F$5*(1+$G$5)))/('Price 120 UAH - 6 pallets'!C18*'Price 120 UAH - 6 pallets'!D18))/((1+$G$5)*(1+$F$5))) -> 0.32654072 | M12: =ROUNDDOWN((($H12/$D$5/(1+$C$5)-('Price 120 UAH - 6 pallets'!E16+'Price 120 UAH - 6 pallets'!F16+'Price 120 UAH - 6 pallets'!G16+'Price 120 UAH - 6 pallets'!E16*'Price 120 UAH - 6 pallets'!B18*($G$5+$F$5*(1+$G$5)))/('Price 120 UAH - 6 pallets'!C18*'Price 120 UAH - 6 pallets'!D18))/((1+$G$5)*(1+$F$5))),2) -> 0.32 | N12: =M12/0.65-1 -> -0.50769231
A13: Bonus 25 % + margin 20 % + extra cost matched to the same request | B13: 0.25 | C13: 0.2 | D13: =ROUND($E$5*((1-B13-C13)-(1-$B$9-$C$9)),2) -> 8.57 | E13: =$E$5*B13 -> 21.428571 | F13: =$E$5*C13 -> 17.142857 | G13: =$E$5-E13-F13 -> 47.142857 | H13: =G13-D13 -> 38.572857 | I13: =(($H13/$D$5/(1+$C$5)-('Price 120 UAH - 33 pallets'!E16+'Price 120 UAH - 33 pallets'!F16+'Price 120 UAH - 33 pallets'!G16+'Price 120 UAH - 33 pallets'!E16*'Price 120 UAH - 33 pallets'!B18*($G$5+$F$5*(1+$G$5)))/('Price 120 UAH - 33 pallets'!C18*'Price 120 UAH - 33 pallets'!D18))/((1+$G$5)*(1+$F$5))) -> 0.5407206 | J13: =ROUNDDOWN((($H13/$D$5/(1+$C$5)-('Price 120 UAH - 33 pallets'!E16+'Price 120 UAH - 33 pallets'!F16+'Price 120 UAH - 33 pallets'!G16+'Price 120 UAH - 33 pallets'!E16*'Price 120 UAH - 33 pallets'!B18*($G$5+$F$5*(1+$G$5)))/('Price 120 UAH - 33 pallets'!C18*'Price 120 UAH - 33 pallets'!D18))/((1+$G$5)*(1+$F$5))),2) -> 0.54 | K13: =J13/0.65-1 -> -0.16923077 | L13: =(($H13/$D$5/(1+$C$5)-('Price 120 UAH - 6 pallets'!E16+'Price 120 UAH - 6 pallets'!F16+'Price 120 UAH - 6 pallets'!G16+'Price 120 UAH - 6 pallets'!E16*'Price 120 UAH - 6 pallets'!B18*($G$5+$F$5*(1+$G$5)))/('Price 120 UAH - 6 pallets'!C18*'Price 120 UAH - 6 pallets'!D18))/((1+$G$5)*(1+$F$5))) -> 0.32656341 | M13: =ROUNDDOWN((($H13/$D$5/(1+$C$5)-('Price 120 UAH - 6 pallets'!E16+'Price 120 UAH - 6 pallets'!F16+'Price 120 UAH - 6 pallets'!G16+'Price 120 UAH - 6 pallets'!E16*'Price 120 UAH - 6 pallets'!B18*($G$5+$F$5*(1+$G$5)))/('Price 120 UAH - 6 pallets'!C18*'Price 120 UAH - 6 pallets'!D18))/((1+$G$5)*(1+$F$5))),2) -> 0.32 | N13: =M13/0.65-1 -> -0.50769231
A14: Bonus 25 % + margin 25 % + extra cost matched to the same request | B14: 0.25 | C14: 0.25 | D14: =ROUND($E$5*((1-B14-C14)-(1-$B$9-$C$9)),2) -> 4.29 | E14: =$E$5*B14 -> 21.428571 | F14: =$E$5*C14 -> 21.428571 | G14: =$E$5-E14-F14 -> 42.857143 | H14: =G14-D14 -> 38.567143 | I14: =(($H14/$D$5/(1+$C$5)-('Price 120 UAH - 33 pallets'!E16+'Price 120 UAH - 33 pallets'!F16+'Price 120 UAH - 33 pallets'!G16+'Price 120 UAH - 33 pallets'!E16*'Price 120 UAH - 33 pallets'!B18*($G$5+$F$5*(1+$G$5)))/('Price 120 UAH - 33 pallets'!C18*'Price 120 UAH - 33 pallets'!D18))/((1+$G$5)*(1+$F$5))) -> 0.54062987 | J14: =ROUNDDOWN((($H14/$D$5/(1+$C$5)-('Price 120 UAH - 33 pallets'!E16+'Price 120 UAH - 33 pallets'!F16+'Price 120 UAH - 33 pallets'!G16+'Price 120 UAH - 33 pallets'!E16*'Price 120 UAH - 33 pallets'!B18*($G$5+$F$5*(1+$G$5)))/('Price 120 UAH - 33 pallets'!C18*'Price 120 UAH - 33 pallets'!D18))/((1+$G$5)*(1+$F$5))),2) -> 0.54 | K14: =J14/0.65-1 -> -0.16923077 | L14: =(($H14/$D$5/(1+$C$5)-('Price 120 UAH - 6 pallets'!E16+'Price 120 UAH - 6 pallets'!F16+'Price 120 UAH - 6 pallets'!G16+'Price 120 UAH - 6 pallets'!E16*'Price 120 UAH - 6 pallets'!B18*($G$5+$F$5*(1+$G$5)))/('Price 120 UAH - 6 pallets'!C18*'Price 120 UAH - 6 pallets'!D18))/((1+$G$5)*(1+$F$5))) -> 0.32647267 | M14: =ROUNDDOWN((($H14/$D$5/(1+$C$5)-('Price 120 UAH - 6 pallets'!E16+'Price 120 UAH - 6 pallets'!F16+'Price 120 UAH - 6 pallets'!G16+'Price 120 UAH - 6 pallets'!E16*'Price 120 UAH - 6 pallets'!B18*($G$5+$F$5*(1+$G$5)))/('Price 120 UAH - 6 pallets'!C18*'Price 120 UAH - 6 pallets'!D18))/((1+$G$5)*(1+$F$5))),2) -> 0.32 | N14: =M14/0.65-1 -> -0.50769231
A15: EXAMPLE: +10 ₴ in landed cost (the request gets lower)
A16: Bonus 25 % + margin 20 % + 10 ₴ | B16: 0.25 | C16: 0.2 | D16: 10 | E16: =$E$5*B16 -> 21.428571 | F16: =$E$5*C16 -> 17.142857 | G16: =$E$5-E16-F16 -> 47.142857 | H16: =G16-D16 -> 37.142857 | I16: =(($H16/$D$5/(1+$C$5)-('Price 120 UAH - 33 pallets'!E16+'Price 120 UAH - 33 pallets'!F16+'Price 120 UAH - 33 pallets'!G16+'Price 120 UAH - 33 pallets'!E16*'Price 120 UAH - 33 pallets'!B18*($G$5+$F$5*(1+$G$5)))/('Price 120 UAH - 33 pallets'!C18*'Price 120 UAH - 33 pallets'!D18))/((1+$G$5)*(1+$F$5))) -> 0.51801354 | J16: =ROUNDDOWN((($H16/$D$5/(1+$C$5)-('Price 120 UAH - 33 pallets'!E16+'Price 120 UAH - 33 pallets'!F16+'Price 120 UAH - 33 pallets'!G16+'Price 120 UAH - 33 pallets'!E16*'Price 120 UAH - 33 pallets'!B18*($G$5+$F$5*(1+$G$5)))/('Price 120 UAH - 33 pallets'!C18*'Price 120 UAH - 33 pallets'!D18))/((1+$G$5)*(1+$F$5))),2) -> 0.51 | K16: =J16/0.65-1 -> -0.21538462 | L16: =(($H16/$D$5/(1+$C$5)-('Price 120 UAH - 6 pallets'!E16+'Price 120 UAH - 6 pallets'!F16+'Price 120 UAH - 6 pallets'!G16+'Price 120 UAH - 6 pallets'!E16*'Price 120 UAH - 6 pallets'!B18*($G$5+$F$5*(1+$G$5)))/('Price 120 UAH - 6 pallets'!C18*'Price 120 UAH - 6 pallets'!D18))/((1+$G$5)*(1+$F$5))) -> 0.30385634 | M16: =ROUNDDOWN((($H16/$D$5/(1+$C$5)-('Price 120 UAH - 6 pallets'!E16+'Price 120 UAH - 6 pallets'!F16+'Price 120 UAH - 6 pallets'!G16+'Price 120 UAH - 6 pallets'!E16*'Price 120 UAH - 6 pallets'!B18*($G$5+$F$5*(1+$G$5)))/('Price 120 UAH - 6 pallets'!C18*'Price 120 UAH - 6 pallets'!D18))/((1+$G$5)*(1+$F$5))),2) -> 0.3 | N16: =M16/0.65-1 -> -0.53846154
A17: Bonus 25 % + margin 25 % + 10 ₴ | B17: 0.25 | C17: 0.25 | D17: 10 | E17: =$E$5*B17 -> 21.428571 | F17: =$E$5*C17 -> 21.428571 | G17: =$E$5-E17-F17 -> 42.857143 | H17: =G17-D17 -> 32.857143 | I17: =(($H17/$D$5/(1+$C$5)-('Price 120 UAH - 33 pallets'!E16+'Price 120 UAH - 33 pallets'!F16+'Price 120 UAH - 33 pallets'!G16+'Price 120 UAH - 33 pallets'!E16*'Price 120 UAH - 33 pallets'!B18*($G$5+$F$5*(1+$G$5)))/('Price 120 UAH - 33 pallets'!C18*'Price 120 UAH - 33 pallets'!D18))/((1+$G$5)*(1+$F$5))) -> 0.44996041 | J17: =ROUNDDOWN((($H17/$D$5/(1+$C$5)-('Price 120 UAH - 33 pallets'!E16+'Price 120 UAH - 33 pallets'!F16+'Price 120 UAH - 33 pallets'!G16+'Price 120 UAH - 33 pallets'!E16*'Price 120 UAH - 33 pallets'!B18*($G$5+$F$5*(1+$G$5)))/('Price 120 UAH - 33 pallets'!C18*'Price 120 UAH - 33 pallets'!D18))/((1+$G$5)*(1+$F$5))),2) -> 0.44 | K17: =J17/0.65-1 -> -0.32307692 | L17: =(($H17/$D$5/(1+$C$5)-('Price 120 UAH - 6 pallets'!E16+'Price 120 UAH - 6 pallets'!F16+'Price 120 UAH - 6 pallets'!G16+'Price 120 UAH - 6 pallets'!E16*'Price 120 UAH - 6 pallets'!B18*($G$5+$F$5*(1+$G$5)))/('Price 120 UAH - 6 pallets'!C18*'Price 120 UAH - 6 pallets'!D18))/((1+$G$5)*(1+$F$5))) -> 0.23580321 | M17: =ROUNDDOWN((($H17/$D$5/(1+$C$5)-('Price 120 UAH - 6 pallets'!E16+'Price 120 UAH - 6 pallets'!F16+'Price 120 UAH - 6 pallets'!G16+'Price 120 UAH - 6 pallets'!E16*'Price 120 UAH - 6 pallets'!B18*($G$5+$F$5*(1+$G$5)))/('Price 120 UAH - 6 pallets'!C18*'Price 120 UAH - 6 pallets'!D18))/((1+$G$5)*(1+$F$5))),2) -> 0.23 | N17: =M17/0.65-1 -> -0.64615385
A18: Bonus 35 % + margin 20 % + 10 ₴ | B18: 0.35 | C18: 0.2 | D18: 10 | E18: =$E$5*B18 -> 30 | F18: =$E$5*C18 -> 17.142857 | G18: =$E$5-E18-F18 -> 38.571429 | H18: =G18-D18 -> 28.571429 | I18: =(($H18/$D$5/(1+$C$5)-('Price 120 UAH - 33 pallets'!E16+'Price 120 UAH - 33 pallets'!F16+'Price 120 UAH - 33 pallets'!G16+'Price 120 UAH - 33 pallets'!E16*'Price 120 UAH - 33 pallets'!B18*($G$5+$F$5*(1+$G$5)))/('Price 120 UAH - 33 pallets'!C18*'Price 120 UAH - 33 pallets'!D18))/((1+$G$5)*(1+$F$5))) -> 0.38190727 | J18: =ROUNDDOWN((($H18/$D$5/(1+$C$5)-('Price 120 UAH - 33 pallets'!E16+'Price 120 UAH - 33 pallets'!F16+'Price 120 UAH - 33 pallets'!G16+'Price 120 UAH - 33 pallets'!E16*'Price 120 UAH - 33 pallets'!B18*($G$5+$F$5*(1+$G$5)))/('Price 120 UAH - 33 pallets'!C18*'Price 120 UAH - 33 pallets'!D18))/((1+$G$5)*(1+$F$5))),2) -> 0.38 | K18: =J18/0.65-1 -> -0.41538462 | L18: =(($H18/$D$5/(1+$C$5)-('Price 120 UAH - 6 pallets'!E16+'Price 120 UAH - 6 pallets'!F16+'Price 120 UAH - 6 pallets'!G16+'Price 120 UAH - 6 pallets'!E16*'Price 120 UAH - 6 pallets'!B18*($G$5+$F$5*(1+$G$5)))/('Price 120 UAH - 6 pallets'!C18*'Price 120 UAH - 6 pallets'!D18))/((1+$G$5)*(1+$F$5))) -> 0.16775007 | M18: =ROUNDDOWN((($H18/$D$5/(1+$C$5)-('Price 120 UAH - 6 pallets'!E16+'Price 120 UAH - 6 pallets'!F16+'Price 120 UAH - 6 pallets'!G16+'Price 120 UAH - 6 pallets'!E16*'Price 120 UAH - 6 pallets'!B18*($G$5+$F$5*(1+$G$5)))/('Price 120 UAH - 6 pallets'!C18*'Price 120 UAH - 6 pallets'!D18))/((1+$G$5)*(1+$F$5))),2) -> 0.16 | N18: =M18/0.65-1 -> -0.75384615
A19: Bonus 35 % + margin 25 % + 10 ₴ | B19: 0.35 | C19: 0.25 | D19: 10 | E19: =$E$5*B19 -> 30 | F19: =$E$5*C19 -> 21.428571 | G19: =$E$5-E19-F19 -> 34.285714 | H19: =G19-D19 -> 24.285714 | I19: =(($H19/$D$5/(1+$C$5)-('Price 120 UAH - 33 pallets'!E16+'Price 120 UAH - 33 pallets'!F16+'Price 120 UAH - 33 pallets'!G16+'Price 120 UAH - 33 pallets'!E16*'Price 120 UAH - 33 pallets'!B18*($G$5+$F$5*(1+$G$5)))/('Price 120 UAH - 33 pallets'!C18*'Price 120 UAH - 33 pallets'!D18))/((1+$G$5)*(1+$F$5))) -> 0.31385413 | J19: =ROUNDDOWN((($H19/$D$5/(1+$C$5)-('Price 120 UAH - 33 pallets'!E16+'Price 120 UAH - 33 pallets'!F16+'Price 120 UAH - 33 pallets'!G16+'Price 120 UAH - 33 pallets'!E16*'Price 120 UAH - 33 pallets'!B18*($G$5+$F$5*(1+$G$5)))/('Price 120 UAH - 33 pallets'!C18*'Price 120 UAH - 33 pallets'!D18))/((1+$G$5)*(1+$F$5))),2) -> 0.31 | K19: =J19/0.65-1 -> -0.52307692 | L19: =(($H19/$D$5/(1+$C$5)-('Price 120 UAH - 6 pallets'!E16+'Price 120 UAH - 6 pallets'!F16+'Price 120 UAH - 6 pallets'!G16+'Price 120 UAH - 6 pallets'!E16*'Price 120 UAH - 6 pallets'!B18*($G$5+$F$5*(1+$G$5)))/('Price 120 UAH - 6 pallets'!C18*'Price 120 UAH - 6 pallets'!D18))/((1+$G$5)*(1+$F$5))) -> 0.099696937 | M19: =ROUNDDOWN((($H19/$D$5/(1+$C$5)-('Price 120 UAH - 6 pallets'!E16+'Price 120 UAH - 6 pallets'!F16+'Price 120 UAH - 6 pallets'!G16+'Price 120 UAH - 6 pallets'!E16*'Price 120 UAH - 6 pallets'!B18*($G$5+$F$5*(1+$G$5)))/('Price 120 UAH - 6 pallets'!C18*'Price 120 UAH - 6 pallets'!D18))/((1+$G$5)*(1+$F$5))),2) -> 0.09 | N19: =M19/0.65-1 -> -0.86153846
A20: CHAIN BONUS 35 %: if the margin must stay above 20 %, the request falls
A21: Bonus 35 % + margin 25 % | B21: 0.35 | C21: 0.25 | D21: 0 | E21: =$E$5*B21 -> 30 | F21: =$E$5*C21 -> 21.428571 | G21: =$E$5-E21-F21 -> 34.285714 | H21: =G21-D21 -> 34.285714 | I21: =(($H21/$D$5/(1+$C$5)-('Price 120 UAH - 33 pallets'!E16+'Price 120 UAH - 33 pallets'!F16+'Price 120 UAH - 33 pallets'!G16+'Price 120 UAH - 33 pallets'!E16*'Price 120 UAH - 33 pallets'!B18*($G$5+$F$5*(1+$G$5)))/('Price 120 UAH - 33 pallets'!C18*'Price 120 UAH - 33 pallets'!D18))/((1+$G$5)*(1+$F$5))) -> 0.47264478 | J21: =ROUNDDOWN((($H21/$D$5/(1+$C$5)-('Price 120 UAH - 33 pallets'!E16+'Price 120 UAH - 33 pallets'!F16+'Price 120 UAH - 33 pallets'!G16+'Price 120 UAH - 33 pallets'!E16*'Price 120 UAH - 33 pallets'!B18*($G$5+$F$5*(1+$G$5)))/('Price 120 UAH - 33 pallets'!C18*'Price 120 UAH - 33 pallets'!D18))/((1+$G$5)*(1+$F$5))),2) -> 0.47 | K21: =J21/0.65-1 -> -0.27692308 | L21: =(($H21/$D$5/(1+$C$5)-('Price 120 UAH - 6 pallets'!E16+'Price 120 UAH - 6 pallets'!F16+'Price 120 UAH - 6 pallets'!G16+'Price 120 UAH - 6 pallets'!E16*'Price 120 UAH - 6 pallets'!B18*($G$5+$F$5*(1+$G$5)))/('Price 120 UAH - 6 pallets'!C18*'Price 120 UAH - 6 pallets'!D18))/((1+$G$5)*(1+$F$5))) -> 0.25848759 | M21: =ROUNDDOWN((($H21/$D$5/(1+$C$5)-('Price 120 UAH - 6 pallets'!E16+'Price 120 UAH - 6 pallets'!F16+'Price 120 UAH - 6 pallets'!G16+'Price 120 UAH - 6 pallets'!E16*'Price 120 UAH - 6 pallets'!B18*($G$5+$F$5*(1+$G$5)))/('Price 120 UAH - 6 pallets'!C18*'Price 120 UAH - 6 pallets'!D18))/((1+$G$5)*(1+$F$5))),2) -> 0.25 | N21: =M21/0.65-1 -> -0.61538462
A22: Bonus 35 % + margin 30 % | B22: 0.35 | C22: 0.3 | D22: 0 | E22: =$E$5*B22 -> 30 | F22: =$E$5*C22 -> 25.714286 | G22: =$E$5-E22-F22 -> 30 | H22: =G22-D22 -> 30 | I22: =(($H22/$D$5/(1+$C$5)-('Price 120 UAH - 33 pallets'!E16+'Price 120 UAH - 33 pallets'!F16+'Price 120 UAH - 33 pallets'!G16+'Price 120 UAH - 33 pallets'!E16*'Price 120 UAH - 33 pallets'!B18*($G$5+$F$5*(1+$G$5)))/('Price 120 UAH - 33 pallets'!C18*'Price 120 UAH - 33 pallets'!D18))/((1+$G$5)*(1+$F$5))) -> 0.40459165 | J22: =ROUNDDOWN((($H22/$D$5/(1+$C$5)-('Price 120 UAH - 33 pallets'!E16+'Price 120 UAH - 33 pallets'!F16+'Price 120 UAH - 33 pallets'!G16+'Price 120 UAH - 33 pallets'!E16*'Price 120 UAH - 33 pallets'!B18*($G$5+$F$5*(1+$G$5)))/('Price 120 UAH - 33 pallets'!C18*'Price 120 UAH - 33 pallets'!D18))/((1+$G$5)*(1+$F$5))),2) -> 0.4 | K22: =J22/0.65-1 -> -0.38461538 | L22: =(($H22/$D$5/(1+$C$5)-('Price 120 UAH - 6 pallets'!E16+'Price 120 UAH - 6 pallets'!F16+'Price 120 UAH - 6 pallets'!G16+'Price 120 UAH - 6 pallets'!E16*'Price 120 UAH - 6 pallets'!B18*($G$5+$F$5*(1+$G$5)))/('Price 120 UAH - 6 pallets'!C18*'Price 120 UAH - 6 pallets'!D18))/((1+$G$5)*(1+$F$5))) -> 0.19043445 | M22: =ROUNDDOWN((($H22/$D$5/(1+$C$5)-('Price 120 UAH - 6 pallets'!E16+'Price 120 UAH - 6 pallets'!F16+'Price 120 UAH - 6 pallets'!G16+'Price 120 UAH - 6 pallets'!E16*'Price 120 UAH - 6 pallets'!B18*($G$5+$F$5*(1+$G$5)))/('Price 120 UAH - 6 pallets'!C18*'Price 120 UAH - 6 pallets'!D18))/((1+$G$5)*(1+$F$5))),2) -> 0.19 | N22: =M22/0.65-1 -> -0.70769231
A23: ONLY THE MARGIN LOWERED (bonus 25 %, no extra cost): the allowed purchase price rises — the argument toward SIAS weakens
A24: Bonus 25 % + margin 25 % | B24: 0.25 | C24: 0.25 | D24: 0 | E24: =$E$5*B24 -> 21.428571 | F24: =$E$5*C24 -> 21.428571 | G24: =$E$5-E24-F24 -> 42.857143 | H24: =G24-D24 -> 42.857143 | I24: =(($H24/$D$5/(1+$C$5)-('Price 120 UAH - 33 pallets'!E16+'Price 120 UAH - 33 pallets'!F16+'Price 120 UAH - 33 pallets'!G16+'Price 120 UAH - 33 pallets'!E16*'Price 120 UAH - 33 pallets'!B18*($G$5+$F$5*(1+$G$5)))/('Price 120 UAH - 33 pallets'!C18*'Price 120 UAH - 33 pallets'!D18))/((1+$G$5)*(1+$F$5))) -> 0.60875106 | J24: =ROUNDDOWN((($H24/$D$5/(1+$C$5)-('Price 120 UAH - 33 pallets'!E16+'Price 120 UAH - 33 pallets'!F16+'Price 120 UAH - 33 pallets'!G16+'Price 120 UAH - 33 pallets'!E16*'Price 120 UAH - 33 pallets'!B18*($G$5+$F$5*(1+$G$5)))/('Price 120 UAH - 33 pallets'!C18*'Price 120 UAH - 33 pallets'!D18))/((1+$G$5)*(1+$F$5))),2) -> 0.6 | K24: =J24/0.65-1 -> -0.076923077 | L24: =(($H24/$D$5/(1+$C$5)-('Price 120 UAH - 6 pallets'!E16+'Price 120 UAH - 6 pallets'!F16+'Price 120 UAH - 6 pallets'!G16+'Price 120 UAH - 6 pallets'!E16*'Price 120 UAH - 6 pallets'!B18*($G$5+$F$5*(1+$G$5)))/('Price 120 UAH - 6 pallets'!C18*'Price 120 UAH - 6 pallets'!D18))/((1+$G$5)*(1+$F$5))) -> 0.39459386 | M24: =ROUNDDOWN((($H24/$D$5/(1+$C$5)-('Price 120 UAH - 6 pallets'!E16+'Price 120 UAH - 6 pallets'!F16+'Price 120 UAH - 6 pallets'!G16+'Price 120 UAH - 6 pallets'!E16*'Price 120 UAH - 6 pallets'!B18*($G$5+$F$5*(1+$G$5)))/('Price 120 UAH - 6 pallets'!C18*'Price 120 UAH - 6 pallets'!D18))/((1+$G$5)*(1+$F$5))),2) -> 0.39 | N24: =M24/0.65-1 -> -0.4
A25: Bonus 25 % + margin 20 % | B25: 0.25 | C25: 0.2 | D25: 0 | E25: =$E$5*B25 -> 21.428571 | F25: =$E$5*C25 -> 17.142857 | G25: =$E$5-E25-F25 -> 47.142857 | H25: =G25-D25 -> 47.142857 | I25: =(($H25/$D$5/(1+$C$5)-('Price 120 UAH - 33 pallets'!E16+'Price 120 UAH - 33 pallets'!F16+'Price 120 UAH - 33 pallets'!G16+'Price 120 UAH - 33 pallets'!E16*'Price 120 UAH - 33 pallets'!B18*($G$5+$F$5*(1+$G$5)))/('Price 120 UAH - 33 pallets'!C18*'Price 120 UAH - 33 pallets'!D18))/((1+$G$5)*(1+$F$5))) -> 0.67680419 | J25: =ROUNDDOWN((($H25/$D$5/(1+$C$5)-('Price 120 UAH - 33 pallets'!E16+'Price 120 UAH - 33 pallets'!F16+'Price 120 UAH - 33 pallets'!G16+'Price 120 UAH - 33 pallets'!E16*'Price 120 UAH - 33 pallets'!B18*($G$5+$F$5*(1+$G$5)))/('Price 120 UAH - 33 pallets'!C18*'Price 120 UAH - 33 pallets'!D18))/((1+$G$5)*(1+$F$5))),2) -> 0.67 | K25: =J25/0.65-1 -> 0.030769231 | L25: =(($H25/$D$5/(1+$C$5)-('Price 120 UAH - 6 pallets'!E16+'Price 120 UAH - 6 pallets'!F16+'Price 120 UAH - 6 pallets'!G16+'Price 120 UAH - 6 pallets'!E16*'Price 120 UAH - 6 pallets'!B18*($G$5+$F$5*(1+$G$5)))/('Price 120 UAH - 6 pallets'!C18*'Price 120 UAH - 6 pallets'!D18))/((1+$G$5)*(1+$F$5))) -> 0.46264699 | M25: =ROUNDDOWN((($H25/$D$5/(1+$C$5)-('Price 120 UAH - 6 pallets'!E16+'Price 120 UAH - 6 pallets'!F16+'Price 120 UAH - 6 pallets'!G16+'Price 120 UAH - 6 pallets'!E16*'Price 120 UAH - 6 pallets'!B18*($G$5+$F$5*(1+$G$5)))/('Price 120 UAH - 6 pallets'!C18*'Price 120 UAH - 6 pallets'!D18))/((1+$G$5)*(1+$F$5))),2) -> 0.46 | N25: =M25/0.65-1 -> -0.29230769
A27: How to read: yellow cells (bonus, margin, extra cost) can be changed — requests recalculate. Shelf price and batch parameters come from the "Price 120 UAH" sheets.
A28: Assumptions: bonus and margin are taken from the partner price (incl. VAT), as in the main model; extra cost is added to landed cost after financing. Current SIAS purchase price: €0.65 (4 SKUs) / €0.75 (2 SKUs).
A29: What to show SIAS is your decision. Any margin, bonus and extra cost shown externally should match the real price structure: SIAS may ask for confirmation.
